Workbook

Sheet 재공품 (WIP)_생산실적
X1: 열고 닫는 기능 추가 필요 (좌측으로) | AH1: 열고 닫는 기능 추가 필요 (좌측으로) | AY1: 열고 닫는 기능 추가 필요 (좌측으로)
B2: 모델 Model | C2: 구분 Division | D2: 기초 / BOH | R2: 입고 / INPUT | S2: 기타입고 / Other Input (6=1+2+3+4+5) | Y2: 출고 / OUTPUT | Z2: 기타출고 / Other Output | AJ2: LOSS (SCRAP) | AM2: 재고 / EOH
D3: 1 | F3: 2 | H3: 3=1+2 | J3: 4 | L3: 5 | N3: 6=4+5 | P3: 7=1+2+4+5 | R3: 1 | S3: 1 | T3: 2 | U3: 3 | V3: 4 | W3: 5 | X3: 6 | Y3: 1 | Z3: 1 | AB3: 2 | AD3: 3 | AF3: 4 | AH3: 5 | AM3: 1 | AO3: 2 | AQ3: 3 | AS3: 4 | AU3: 5 (1+3) | AW3: 6 (2+4) | AY3: TOTAL_EOH (MES) 7=5+6
D4: LINE_WIP | F4: LINE_FGS | H4: BOH A_LEVEL SUB TOTAL | J4: B_LEVEL_WIP | L4: B_LEVEL_FGS | N4: BOH B_LEVEL SUB TOTAL | P4: T_BOH | R4: USC_INPUT (C) | S4: CODE 변경 | T4: Re-Sorting (재검사) | U4: Re-work (SI검사) | V4: 반제품 입고 | W4: 기타 | X4: 기타입고 | Y4: OUTPUT_A (C) | Z4: CODE 변경 | AB4: 반제품 출고 (유상) | AD4: 반제품 출고 (무상) | AF4: 기타 | AH4: 기타출고 (5=1+2+3+4) | AM4: LINE_WIP (A) | AO4: LINE_FGs (A) | AQ4: B_LEVEL WIP (A) | AS4: B_LEVEL FGs | AU4: T_EOH WIP | AW4: T_EOH FGs
D5: PFL전 50% | E5: PFL후 90% | F5: PFL전 50% | G5: PFL후 90% | H5: PFL전 50% | I5: PFL후 90% | J5: PFL전 50% | K5: PFL후 90% | L5: PFL전 50% | M5: PFL후 90% | N5: PFL전 50% | O5: PFL후 90% | P5: PFL전 50% | Q5: PFL후 90% | Z5: PFL전 50% | AA5: PFL후 90% | AB5: PFL전 50% | AC5: PFL후 90% | AD5: PFL전 50% | AE5: PFL후 90% | AF5: PFL전 50% | AG5: PFL후 90% | AH5: PFL전 50% | AI5: PFL후 90% | AJ5: PFL전 50% | AK5: PFL후 90% | AL5: 합계 | AM5: PFL전 50% | AN5: PFL후 90% | AO5: PFL전 50% | AP5: PFL후 90% | AQ5: PFL전 50% | AR5: PFL후 90% | AS5: PFL전 50% | AT5: PFL후 90% | AU5: PFL전 50% | AV5: PFL후 90% | AW5: PFL전 50% | AX5: PFL후 90% | AY5: PFL전 50% | AZ5: PFL후 90%
B6: 7075P | C6: MP | D6: 0 | E6: 0 | F6: 0 | G6: 0 | H6: =D6+F6 -> 0 | I6: =E6+G6 -> 0 | J6: 6 | K6: 7 | L6: 0 | M6: 0 | N6: =J6+L6 -> 6 | O6: =K6+M6 -> 7 | P6: =H6+N6 -> 6 | Q6: =I6+O6 -> 7 | R6: 0 | S6: 0 | T6: 0 | U6: 0 | V6: 0 | W6: 0 | X6: =SUM(S6:W6) -> 0 | Y6: 0 | Z6: 0 | AA6: 0 | AB6: 0 | AC6: 0 | AD6: 0 | AE6: 0 | AF6: 0 | AG6: 0 | AH6: =Z6+AB6+AD6+AF6 -> 0 | AI6: =AA6+AC6+AE6+AG6 -> 0 | AJ6: 0 | AK6: 0 | AL6: =AJ6+AK6 -> 0 | AM6: 0 | AN6: 0 | AO6: 0 | AP6: 0 | AQ6: 6 | AR6: 7 | AS6: 0 | AT6: 0 | AU6: =AM6+AQ6 -> 6 | AV6: =AN6+AR6 -> 7 | AW6: =AO6+AS6 -> 0 | AX6: =AP6+AT6 -> 0 | AY6: =AU6+AW6 -> 6 | AZ6: =AV6+AX6 -> 7
B7: 712TP | C7: MP | D7: 0 | E7: 0 | F7: 0 | G7: 0 | H7: =D7+F7 -> 0 | I7: =E7+G7 -> 0 | J7: 173 | K7: 11 | L7: 0 | M7: 0 | N7: =J7+L7 -> 173 | O7: =K7+M7 -> 11 | P7: =H7+N7 -> 173 | Q7: =I7+O7 -> 11 | R7: 0 | S7: 0 | T7: 0 | U7: 0 | V7: 0 | W7: 0 | X7: =SUM(S7:W7) -> 0 | Y7: 0 | Z7: 0 | AA7: 0 | AB7: 0 | AC7: 0 | AD7: 0 | AE7: 0 | AF7: 0 | AG7: 0 | AH7: =Z7+AB7+AD7+AF7 -> 0 | AI7: =AA7+AC7+AE7+AG7 -> 0 | AJ7: 0 | AK7: 0 | AL7: =AJ7+AK7 -> 0 | AM7: 0 | AN7: 0 | AO7: 0 | AP7: 0 | AQ7: 173 | AR7: 11 | AS7: 0 | AT7: 0 | AU7: =AM7+AQ7 -> 173 | AV7: =AN7+AR7 -> 11 | AW7: =AO7+AS7 -> 0 | AX7: =AP7+AT7 -> 0 | AY7: =AU7+AW7 -> 173 | AZ7: =AV7+AX7 -> 11
B8: 716AP | C8: MP | D8: 30912 | E8: 17821 | F8: 0 | G8: 15621 | H8: =D8+F8 -> 30912 | I8: =E8+G8 -> 33442 | J8: 2246 | K8: 292 | L8: 0 | M8: 23 | N8: =J8+L8 -> 2246 | O8: =K8+M8 -> 315 | P8: =H8+N8 -> 33158 | Q8: =I8+O8 -> 33757 | R8: 499392 | S8: 0 | T8: 260558 | U8: 9765 | V8: 0 | W8: 0 | X8: =SUM(S8:W8) -> 270323 | Y8: 757675 | Z8: 0 | AA8: 0 | AB8: 0 | AC8: 10 | AD8: 5 | AE8: 0 | AF8: 0 | AG8: 0 | AH8: =Z8+AB8+AD8+AF8 -> 5 | AI8: =AA8+AC8+AE8+AG8 -> 10 | AJ8: 10901 | AK8: 8366 | AL8: =AJ8+AK8 -> 19267 | AM8: 33958 | AN8: 13774 | AO8: 0 | AP8: 8103 | AQ8: 3283 | AR8: 502 | AS8: 0 | AT8: 53 | AU8: =AM8+AQ8 -> 37241 | AV8: =AN8+AR8 -> 14276 | AW8: =AO8+AS8 -> 0 | AX8: =AP8+AT8 -> 8156 | AY8: =AU8+AW8 -> 37241 | AZ8: =AV8+AX8 -> 22432
B9: 716BD | C9: R&D | D9: 0 | E9: 0 | F9: 0 | G9: 0 | H9: =D9+F9 -> 0 | I9: =E9+G9 -> 0 | J9: 69 | K9: 4 | L9: 0 | M9: 0 | N9: =J9+L9 -> 69 | O9: =K9+M9 -> 4 | P9: =H9+N9 -> 69 | Q9: =I9+O9 -> 4 | R9: 0 | S9: 0 | T9: 0 | U9: 0 | V9: 0 | W9: 0 | X9: =SUM(S9:W9) -> 0 | Y9: 0 | Z9: 0 | AA9: 0 | AB9: 0 | AC9: 0 | AD9: 0 | AE9: 0 | AF9: 0 | AG9: 0 | AH9: =Z9+AB9+AD9+AF9 -> 0 | AI9: =AA9+AC9+AE9+AG9 -> 0 | AJ9: 0 | AK9: 0 | AL9: =AJ9+AK9 -> 0 | AM9: 0 | AN9: 0 | AO9: 0 | AP9: 0 | AQ9: 69 | AR9: 4 | AS9: 0 | AT9: 0 | AU9: =AM9+AQ9 -> 69 | AV9: =AN9+AR9 -> 4 | AW9: =AO9+AS9 -> 0 | AX9: =AP9+AT9 -> 0 | AY9: =AU9+AW9 -> 69 | AZ9: =AV9+AX9 -> 4
B10: 716CD | C10: R&D | D10: 0 | E10: 0 | F10: 0 | G10: 0 | H10: =D10+F10 -> 0 | I10: =E10+G10 -> 0 | J10: 0 | K10: 1 | L10: 0 | M10: 0 | N10: =J10+L10 -> 0 | O10: =K10+M10 -> 1 | P10: =H10+N10 -> 0 | Q10: =I10+O10 -> 1 | R10: 0 | S10: 0 | T10: 0 | U10: 0 | V10: 0 | W10: 0 | X10: =SUM(S10:W10) -> 0 | Y10: 0 | Z10: 0 | AA10: 0 | AB10: 0 | AC10: 0 | AD10: 0 | AE10: 0 | AF10: 0 | AG10: 0 | AH10: =Z10+AB10+AD10+AF10 -> 0 | AI10: =AA10+AC10+AE10+AG10 -> 0 | AJ10: 0 | AK10: 0 | AL10: =AJ10+AK10 -> 0 | AM10: 0 | AN10: 0 | AO10: 0 | AP10: 0 | AQ10: 0 | AR10: 1 | AS10: 0 | AT10: 0 | AU10: =AM10+AQ10 -> 0 | AV10: =AN10+AR10 -> 1 | AW10: =AO10+AS10 -> 0 | AX10: =AP10+AT10 -> 0 | AY10: =AU10+AW10 -> 0 | AZ10: =AV10+AX10 -> 1
B11: 716DD | C11: R&D | D11: 0 | E11: 0 | F11: 0 | G11: 0 | H11: =D11+F11 -> 0 | I11: =E11+G11 -> 0 | J11: 328 | K11: 2161 | L11: 0 | M11: 144 | N11: =J11+L11 -> 328 | O11: =K11+M11 -> 2305 | P11: =H11+N11 -> 328 | Q11: =I11+O11 -> 2305 | R11: 0 | S11: 0 | T11: 0 | U11: 0 | V11: 0 | W11: 0 | X11: =SUM(S11:W11) -> 0 | Y11: 0 | Z11: 0 | AA11: 0 | AB11: 0 | AC11: 0 | AD11: 0 | AE11: 0 | AF11: 0 | AG11: 0 | AH11: =Z11+AB11+AD11+AF11 -> 0 | AI11: =AA11+AC11+AE11+AG11 -> 0 | AJ11: 0 | AK11: 2295 | AL11: =AJ11+AK11 -> 2295 | AM11: 0 | AN11: 0 | AO11: 0 | AP11: 0 | AQ11: 328 | AR11: 10 | AS11: 0 | AT11: 0 | AU11: =AM11+AQ11 -> 328 | AV11: =AN11+AR11 -> 10 | AW11: =AO11+AS11 -> 0 | AX11: =AP11+AT11 -> 0 | AY11: =AU11+AW11 -> 328 | AZ11: =AV11+AX11 -> 10
B12: 716DTT | C12: R&D | D12: 0 | E12: 0 | F12: 0 | G12: 0 | H12: =D12+F12 -> 0 | I12: =E12+G12 -> 0 | J12: 320 | K12: 0 | L12: 0 | M12: 0 | N12: =J12+L12 -> 320 | O12: =K12+M12 -> 0 | P12: =H12+N12 -> 320 | Q12: =I12+O12 -> 0 | R12: 16 | S12: 0 | T12: 0 | U12: 0 | V12: 0 | W12: 0 | X12: =SUM(S12:W12) -> 0 | Y12: 0 | Z12: 0 | AA12: 0 | AB12: 0 | AC12: 0 | AD12: 300 | AE12: 0 | AF12: 0 | AG12: 0 | AH12: =Z12+AB12+AD12+AF12 -> 300 | AI12: =AA12+AC12+AE12+AG12 -> 0 | AJ12: 36 | AK12: 0 | AL12: =AJ12+AK12 -> 36 | AM12: 0 | AN12: 0 | AO12: 0 | AP12: 0 | AQ12: 0 | AR12: 0 | AS12: 0 | AT12: 0 | AU12: =AM12+AQ12 -> 0 | AV12: =AN12+AR12 -> 0 | AW12: =AO12+AS12 -> 0 | AX12: =AP12+AT12 -> 0 | AY12: =AU12+AW12 -> 0 | AZ12: =AV12+AX12 -> 0
B13: 716ED | C13: R&D | D13: 0 | E13: 0 | F13: 0 | G13: 0 | H13: =D13+F13 -> 0 | I13: =E13+G13 -> 0 | J13: 31 | K13: 1 | L13: 0 | M13: 0 | N13: =J13+L13 -> 31 | O13: =K13+M13 -> 1 | P13: =H13+N13 -> 31 | Q13: =I13+O13 -> 1 | R13: 0 | S13: 0 | T13: 0 | U13: 0 | V13: 0 | W13: 0 | X13: =SUM(S13:W13) -> 0 | Y13: 0 | Z13: 0 | AA13: 0 | AB13: 0 | AC13: 0 | AD13: 0 | AE13: 0 | AF13: 0 | AG13: 0 | AH13: =Z13+AB13+AD13+AF13 -> 0 | AI13: =AA13+AC13+AE13+AG13 -> 0 | AJ13: 0 | AK13: 0 | AL13: =AJ13+AK13 -> 0 | AM13: 0 | AN13: 0 | AO13: 0 | AP13: 0 | AQ13: 31 | AR13: 1 | AS13: 0 | AT13: 0 | AU13: =AM13+AQ13 -> 31 | AV13: =AN13+AR13 -> 1 | AW13: =AO13+AS13 -> 0 | AX13: =AP13+AT13 -> 0 | AY13: =AU13+AW13 -> 31 | AZ13: =AV13+AX13 -> 1
B14: 716ETT | C14: R&D | D14: 0 | E14: 0 | F14: 0 | G14: 0 | H14: =D14+F14 -> 0 | I14: =E14+G14 -> 0 | J14: 576 | K14: 0 | L14: 0 | M14: 0 | N14: =J14+L14 -> 576 | O14: =K14+M14 -> 0 | P14: =H14+N14 -> 576 | Q14: =I14+O14 -> 0 | R14: 256 | S14: 0 | T14: 0 | U14: 0 | V14: 0 | W14: 0 | X14: =SUM(S14:W14) -> 0 | Y14: 0 | Z14: 0 | AA14: 0 | AB14: 350 | AC14: 0 | AD14: 0 | AE14: 0 | AF14: 0 | AG14: 0 | AH14: =Z14+AB14+AD14+AF14 -> 350 | AI14: =AA14+AC14+AE14+AG14 -> 0 | AJ14: 418 | AK14: 0 | AL14: =AJ14+AK14 -> 418 | AM14: 0 | AN14: 0 | AO14: 0 | AP14: 0 | AQ14: 64 | AR14: 0 | AS14: 0 | AT14: 0 | AU14: =AM14+AQ14 -> 64 | AV14: =AN14+AR14 -> 0 | AW14: =AO14+AS14 -> 0 | AX14: =AP14+AT14 -> 0 | AY14: =AU14+AW14 -> 64 | AZ14: =AV14+AX14 -> 0
B15: 716FD | C15: R&D | D15: 0 | E15: 0 | F15: 0 | G15: 0 | H15: =D15+F15 -> 0 | I15: =E15+G15 -> 0 | J15: 67 | K15: 1 | L15: 0 | M15: 0 | N15: =J15+L15 -> 67 | O15: =K15+M15 -> 1 | P15: =H15+N15 -> 67 | Q15: =I15+O15 -> 1 | R15: 0 | S15: 0 | T15: 0 | U15: 0 | V15: 0 | W15: 0 | X15: =SUM(S15:W15) -> 0 | Y15: 0 | Z15: 0 | AA15: 0 | AB15: 0 | AC15: 0 | AD15: 0 | AE15: 0 | AF15: 0 | AG15: 0 | AH15: =Z15+AB15+AD15+AF15 -> 0 | AI15: =AA15+AC15+AE15+AG15 -> 0 | AJ15: 0 | AK15: 0 | AL15: =AJ15+AK15 -> 0 | AM15: 0 | AN15: 0 | AO15: 0 | AP15: 0 | AQ15: 67 | AR15: 1 | AS15: 0 | AT15: 0 | AU15: =AM15+AQ15 -> 67 | AV15: =AN15+AR15 -> 1 | AW15: =AO15+AS15 -> 0 | AX15: =AP15+AT15 -> 0 | AY15: =AU15+AW15 -> 67 | AZ15: =AV15+AX15 -> 1
B16: 716GD | C16: R&D | D16: 0 | E16: 0 | F16: 0 | G16: 0 | H16: =D16+F16 -> 0 | I16: =E16+G16 -> 0 | J16: 2 | K16: 1 | L16: 0 | M16: 0 | N16: =J16+L16 -> 2 | O16: =K16+M16 -> 1 | P16: =H16+N16 -> 2 | Q16: =I16+O16 -> 1 | R16: 0 | S16: 0 | T16: 0 | U16: 0 | V16: 0 | W16: 0 | X16: =SUM(S16:W16) -> 0 | Y16: 0 | Z16: 0 | AA16: 0 | AB16: 0 | AC16: 0 | AD16: 0 | AE16: 0 | AF16: 0 | AG16: 0 | AH16: =Z16+AB16+AD16+AF16 -> 0 | AI16: =AA16+AC16+AE16+AG16 -> 0 | AJ16: 0 | AK16: 0 | AL16: =AJ16+AK16 -> 0 | AM16: 0 | AN16: 0 | AO16: 0 | AP16: 0 | AQ16: 2 | AR16: 1 | AS16: 0 | AT16: 0 | AU16: =AM16+AQ16 -> 2 | AV16: =AN16+AR16 -> 1 | AW16: =AO16+AS16 -> 0 | AX16: =AP16+AT16 -> 0 | AY16: =AU16+AW16 -> 2 | AZ16: =AV16+AX16 -> 1
B17: 716JD | C17: R&D | D17: 0 | E17: 0 | F17: 0 | G17: 0 | H17: =D17+F17 -> 0 | I17: =E17+G17 -> 0 | J17: 15 | K17: 1 | L17: 0 | M17: 0 | N17: =J17+L17 -> 15 | O17: =K17+M17 -> 1 | P17: =H17+N17 -> 15 | Q17: =I17+O17 -> 1 | R17: 0 | S17: 0 | T17: 0 | U17: 0 | V17: 0 | W17: 0 | X17: =SUM(S17:W17) -> 0 | Y17: 0 | Z17: 0 | AA17: 0 | AB17: 0 | AC17: 0 | AD17: 0 | AE17: 0 | AF17: 0 | AG17: 0 | AH17: =Z17+AB17+AD17+AF17 -> 0 | AI17: =AA17+AC17+AE17+AG17 -> 0 | AJ17: 0 | AK17: 0 | AL17: =AJ17+AK17 -> 0 | AM17: 0 | AN17: 0 | AO17: 0 | AP17: 0 | AQ17: 15 | AR17: 1 | AS17: 0 | AT17: 0 | AU17: =AM17+AQ17 -> 15 | AV17: =AN17+AR17 -> 1 | AW17: =AO17+AS17 -> 0 | AX17: =AP17+AT17 -> 0 | AY17: =AU17+AW17 -> 15 | AZ17: =AV17+AX17 -> 1
... B77: 8191D | C77: R&D | D77: 0 | E77: 0 | F77: 0 | G77: 0 | H77: =D77+F77 -> 0 | I77: =E77+G77 -> 0 | J77: 30 | K77: 1 | L77: 0 | M77: 0 | N77: =J77+L77 -> 30 | O77: =K77+M77 -> 1 | P77: =H77+N77 -> 30 | Q77: =I77+O77 -> 1 | R77: 0 | S77: 0 | T77: 0 | U77: 0 | V77: 0 | W77: 0 | X77: =SUM(S77:W77) -> 0 | Y77: 0 | Z77: 0 | AA77: 0 | AB77: 0 | AC77: 0 | AD77: 0 | AE77: 0 | AF77: 0 | AG77: 0 | AH77: =Z77+AB77+AD77+AF77 -> 0 | AI77: =AA77+AC77+AE77+AG77 -> 0 | AJ77: 0 | AK77: 0 | AL77: =AJ77+AK77 -> 0 | AM77: 0 | AN77: 0 | AO77: 0 | AP77: 0 | AQ77: 30 | AR77: 1 | AS77: 0 | AT77: 0 | AU77: =AM77+AQ77 -> 30 | AV77: =AN77+AR77 -> 1 | AW77: =AO77+AS77 -> 0 | AX77: =AP77+AT77 -> 0 | AY77: =AU77+AW77 -> 30 | AZ77: =AV77+AX77 -> 1
B78: TOTAL | D78: =SUM(D6:D77) -> 36254 | E78: =SUM(E6:E77) -> 20177 | F78: =SUM(F6:F77) -> 0 | G78: =SUM(G6:G77) -> 15624 | H78: =SUM(H6:H77) -> 36254 | I78: =SUM(I6:I77) -> 35801 | J78: =SUM(J6:J77) -> 13148 | K78: =SUM(K6:K77) -> 5431 | ... AZ78: =SUM(AZ6:AZ77) -> 31145

Sheet 제품(TP)_제품수불부
M1: 열고 닫는 기능 추가 필요 (좌측으로) | R1: 열고 닫는 기능 추가 필요 (좌측으로) | U1: 열고 닫는 기능 추가 필요 (좌측으로) | Z1: 열고 닫는 기능 추가 필요 (좌측으로)
B2: 모델 Model | C2: 구분 Division | D2: BOH | E2: INPUT | N2: 기타입고 | S2: OUTPUT | V2: 기타출고 | AA2: LOSS | AB2: EOH WH0006
E3: 1 | F3: 2 | G3: 3 | H3: 4 | I3: 5 | J3: 6 | K3: 7 | L3: 8 | M3: 9=1+…+8 | N3: 1 | O3: 2 | P3: 3 | Q3: 4 | R3: 5=1+2+3+4 | S3: 1 | T3: 2 | U3: 3=1+2 | V3: 1 | W3: 2 | X3: 3 | Y3: 4 | Z3: 5=1+2+3+4
E4: NORMAL FG INPUT | G4: RW FROM LINE → FG-WAREHOUSE / REWORK 생산라인 → 완제품 창고 CELL 입고 | M4: T_INPUT | N4: RMA | O4: 반제품 (유상) | P4: 반제품 (무상) | Q4: 기타 | R4: 기타입고 | S4: SHIP (A 급) | T4: SHIP (B 급) | U4: T_OUTPUT | V4: Re-Sorting (재검사) | W4: Re-work (SI검사) | X4: 무상매출 | Y4: 기타 | Z4: 기타출고
E5: LAST-MONTH | F5: THIS-MONTH | G5: BACK-SHIP (SORTING) | H5: BACK-SHIP (PF-RW) | I5: BACK-SHIP (PL-RW) | J5: WH RETURN (SORTING) | K5: WH RETURN (PF-RW) | L5: WH RETURN (PL-RW) | S5: PAID | T5: PAID | AD5: 검증
B6: 7075P | C6: =VLOOKUP(B6,'재공품 (WIP)_생산실적'!$B$6:$C$88,2,FALSE) -> MP | D6: =IFERROR(VLOOKUP(B6,'(A) Inventory'!$A$7:$C$89,3,0),0) -> 10030 | E6: =IFERROR(VLOOKUP(B6,'(B) FGs'!$B$6:$D$55,3,0),0) -> 0 | F6: =IFERROR(VLOOKUP(B6,'(B) FGs'!$B$6:$E$55,4,0),0) -> 0 | G6: =IFERROR(VLOOKUP(B6,'(B) FGs'!$B$6:$G$55,6,0),0) -> 0 | H6: =IFERROR(VLOOKUP(B6,'(B) FGs'!$B$6:$H$55,7,0),0) -> 0 | I6: =IFERROR(VLOOKUP(B6,'(B) FGs'!$B$6:$I$55,8,0),0) -> 0 | J6: =IFERROR(VLOOKUP(B6,'(B) FGs'!$B$6:$J$55,9,0),0) -> 0 | K6: =IFERROR(VLOOKUP(B6,'(B) FGs'!$B$6:$K$55,10,0),0) -> 0 | L6: =IFERROR(VLOOKUP(B6,'(B) FGs'!$B$6:$L$55,11,0),0) -> 0 | M6: =SUM(E6:L6) -> 0 | N6: =IFERROR(VLOOKUP(B6,'(B) FGs'!$B$6:$R$55,13,0),0) -> 0 | O6: =IFERROR(VLOOKUP(B6,'(A) Inventory'!$A$7:$R$89,18,0),0) -> 0 | P6: =IFERROR(VLOOKUP(B6,'(A) Inventory'!$A$7:$S$89,19,0),0) -> 0 | Q6: 0 | R6: =SUM(N6:Q6) -> 0 | S6: =IFERROR(VLOOKUP(B6,'(A) Inventory'!$A$7:$P$89,16,0),0) -> 0 | T6: =IFERROR(VLOOKUP(B6,'(A) Inventory'!$A$7:$R$89,18,0),0) -> 0 | U6: =SUM(S6:T6) -> 0 | V6: =IFERROR(VLOOKUP(B6,'(B) FGs'!$B$6:$S$55,18,0),0)-IFERROR(VLOOKUP(B6,'(B) FGs'!$B$6:$M$55,12,0),0) -> 0 | W6: =IFERROR(VLOOKUP(B6,'(B) FGs'!$B$6:$M$55,12,0),0) -> 0 | X6: =IFERROR(VLOOKUP(B6,'(A) Inventory'!$A$7:$S$89,19,0),0) -> 0 | Y6: 0 | Z6: =SUM(V6:Y6) -> 0 | AA6: 0 | AB6: 10030 | AD6: =D6+M6+R6-U6-Z6-AA6=AB6 -> TRUE | AE6: =D6+M6+R6-U6-Z6-AA6-AB6 -> 0
B7: 712TP | C7: =VLOOKUP(B7,'재공품 (WIP)_생산실적'!$B$6:$C$88,2,FALSE) -> MP | D7: =IFERROR(VLOOKUP(B7,'(A) Inventory'!$A$7:$C$89,3,0),0) -> 0 | E7: =IFERROR(VLOOKUP(B7,'(B) FGs'!$B$6:$D$55,3,0),0) -> 0 | F7: =IFERROR(VLOOKUP(B7,'(B) FGs'!$B$6:$E$55,4,0),0) -> 0 | G7: =IFERROR(VLOOKUP(B7,'(B) FGs'!$B$6:$G$55,6,0),0) -> 0 | H7: =IFERROR(VLOOKUP(B7,'(B) FGs'!$B$6:$H$55,7,0),0) -> 0 | I7: =IFERROR(VLOOKUP(B7,'(B) FGs'!$B$6:$I$55,8,0),0) -> 0 | J7: =IFERROR(VLOOKUP(B7,'(B) FGs'!$B$6:$J$55,9,0),0) -> 0 | K7: 0 | L7: =IFERROR(VLOOKUP(B7,'(B) FGs'!$B$6:$L$55,11,0),0) -> 0 | M7: =SUM(E7:L7) -> 0 | N7: =IFERROR(VLOOKUP(B7,'(B) FGs'!$B$6:$R$55,13,0),0) -> 0 | O7: =IFERROR(VLOOKUP(B7,'(A) Inventory'!$A$7:$R$89,18,0),0) -> 0 | P7: =IFERROR(VLOOKUP(B7,'(A) Inventory'!$A$7:$S$89,19,0),0) -> 0 | Q7: 0 | R7: =SUM(N7:Q7) -> 0 | S7: =IFERROR(VLOOKUP(B7,'(A) Inventory'!$A$7:$P$89,16,0),0) -> 0 | T7: =IFERROR(VLOOKUP(B7,'(A) Inventory'!$A$7:$R$89,18,0),0) -> 0 | U7: =SUM(S7:T7) -> 0 | V7: =IFERROR(VLOOKUP(B7,'(B) FGs'!$B$6:$S$55,18,0),0)-IFERROR(VLOOKUP(B7,'(B) FGs'!$B$6:$M$55,12,0),0) -> 0 | W7: =IFERROR(VLOOKUP(B7,'(B) FGs'!$B$6:$M$55,12,0),0) -> 0 | X7: =IFERROR(VLOOKUP(B7,'(A) Inventory'!$A$7:$S$89,19,0),0) -> 0 | Y7: 0 | Z7: =SUM(V7:Y7) -> 0 | AA7: 0 | AB7: 0 | AD7: =D7+M7+R7-U7-Z7-AA7=AB7 -> TRUE | AE7: =D7+M7+R7-U7-Z7-AA7-AB7 -> 0
B8: 716AP | C8: =VLOOKUP(B8,'재공품 (WIP)_생산실적'!$B$6:$C$88,2,FALSE) -> MP | D8: =IFERROR(VLOOKUP(B8,'(A) Inventory'!$A$7:$C$89,3,0),0) -> 387259 | E8: =IFERROR(VLOOKUP(B8,'(B) FGs'!$B$6:$D$55,3,0),0) -> 39672 | F8: =IFERROR(VLOOKUP(B8,'(B) FGs'!$B$6:$E$55,4,0),0) -> 441648 | G8: =IFERROR(VLOOKUP(B8,'(B) FGs'!$B$6:$G$55,6,0),0) -> 23934 | H8: =IFERROR(VLOOKUP(B8,'(B) FGs'!$B$6:$H$55,7,0),0) -> 0 | I8: =IFERROR(VLOOKUP(B8,'(B) FGs'!$B$6:$I$55,8,0),0) -> 0 | J8: =IFERROR(VLOOKUP(B8,'(B) FGs'!$B$6:$J$55,9,0),0) -> 242656 | K8: 9765 | L8: =IFERROR(VLOOKUP(B8,'(B) FGs'!$B$6:$L$55,11,0),0) -> 0 | M8: =SUM(E8:L8) -> 757675 | N8: =IFERROR(VLOOKUP(B8,'(B) FGs'!$B$6:$R$55,13,0),0) -> 0 | O8: =IFERROR(VLOOKUP(B8,'(A) Inventory'!$A$7:$R$89,18,0),0) -> 10 | P8: =IFERROR(VLOOKUP(B8,'(A) Inventory'!$A$7:$S$89,19,0),0) -> 5 | Q8: 0 | R8: =SUM(N8:Q8) -> 15 | S8: =IFERROR(VLOOKUP(B8,'(A) Inventory'!$A$7:$P$89,16,0),0) -> 594080 | T8: =IFERROR(VLOOKUP(B8,'(A) Inventory'!$A$7:$R$89,18,0),0) -> 10 | U8: =SUM(S8:T8) -> 594090 | V8: =IFERROR(VLOOKUP(B8,'(B) FGs'!$B$6:$S$55,18,0),0)-IFERROR(VLOOKUP(B8,'(B) FGs'!$B$6:$M$55,12,0),0) -> 260558 | W8: =IFERROR(VLOOKUP(B8,'(B) FGs'!$B$6:$M$55,12,0),0) -> 9765 | X8: =IFERROR(VLOOKUP(B8,'(A) Inventory'!$A$7:$S$89,19,0),0) -> 5 | Y8: 0 | Z8: =SUM(V8:Y8) -> 270328 | AA8: 0 | AB8: 280531 | AD8: =D8+M8+R8-U8-Z8-AA8=AB8 -> TRUE | AE8: =D8+M8+R8-U8-Z8-AA8-AB8 -> 0
B9: 716BD | C9: =VLOOKUP(B9,'재공품 (WIP)_생산실적'!$B$6:$C$88,2,FALSE) -> R&D | D9: =IFERROR(VLOOKUP(B9,'(A) Inventory'!$A$7:$C$89,3,0),0) -> 987 | E9: =IFERROR(VLOOKUP(B9,'(B) FGs'!$B$6:$D$55,3,0),0) -> 0 | F9: =IFERROR(VLOOKUP(B9,'(B) FGs'!$B$6:$E$55,4,0),0) -> 0 | G9: =IFERROR(VLOOKUP(B9,'(B) FGs'!$B$6:$G$55,6,0),0) -> 0 | H9: =IFERROR(VLOOKUP(B9,'(B) FGs'!$B$6:$H$55,7,0),0) -> 0 | I9: =IFERROR(VLOOKUP(B9,'(B) FGs'!$B$6:$I$55,8,0),0) -> 0 | J9: =IFERROR(VLOOKUP(B9,'(B) FGs'!$B$6:$J$55,9,0),0) -> 0 | K9: 0 | L9: =IFERROR(VLOOKUP(B9,'(B) FGs'!$B$6:$L$55,11,0),0) -> 0 | M9: =SUM(E9:L9) -> 0 | N9: =IFERROR(VLOOKUP(B9,'(B) FGs'!$B$6:$R$55,13,0),0) -> 0 | O9: =IFERROR(VLOOKUP(B9,'(A) Inventory'!$A$7:$R$89,18,0),0) -> 0 | P9: =IFERROR(VLOOKUP(B9,'(A) Inventory'!$A$7:$S$89,19,0),0) -> 0 | Q9: 0 | R9: =SUM(N9:Q9) -> 0 | S9: =IFERROR(VLOOKUP(B9,'(A) Inventory'!$A$7:$P$89,16,0),0) -> 0 | T9: =IFERROR(VLOOKUP(B9,'(A) Inventory'!$A$7:$R$89,18,0),0) -> 0 | U9: =SUM(S9:T9) -> 0 | V9: =IFERROR(VLOOKUP(B9,'(B) FGs'!$B$6:$S$55,18,0),0)-IFERROR(VLOOKUP(B9,'(B) FGs'!$B$6:$M$55,12,0),0) -> 0 | W9: =IFERROR(VLOOKUP(B9,'(B) FGs'!$B$6:$M$55,12,0),0) -> 0 | X9: =IFERROR(VLOOKUP(B9,'(A) Inventory'!$A$7:$S$89,19,0),0) -> 0 | Y9: 0 | Z9: =SUM(V9:Y9) -> 0 | AA9: 0 | AB9: 987 | AD9: =D9+M9+R9-U9-Z9-AA9=AB9 -> TRUE | AE9: =D9+M9+R9-U9-Z9-AA9-AB9 -> 0
B10: 716CD | C10: =VLOOKUP(B10,'재공품 (WIP)_생산실적'!$B$6:$C$88,2,FALSE) -> R&D | D10: =IFERROR(VLOOKUP(B10,'(A) Inventory'!$A$7:$C$89,3,0),0) -> 38 | E10: =IFERROR(VLOOKUP(B10,'(B) FGs'!$B$6:$D$55,3,0),0) -> 0 | F10: =IFERROR(VLOOKUP(B10,'(B) FGs'!$B$6:$E$55,4,0),0) -> 0 | G10: =IFERROR(VLOOKUP(B10,'(B) FGs'!$B$6:$G$55,6,0),0) -> 0 | H10: =IFERROR(VLOOKUP(B10,'(B) FGs'!$B$6:$H$55,7,0),0) -> 0 | I10: =IFERROR(VLOOKUP(B10,'(B) FGs'!$B$6:$I$55,8,0),0) -> 0 | J10: =IFERROR(VLOOKUP(B10,'(B) FGs'!$B$6:$J$55,9,0),0) -> 0 | K10: 0 | L10: =IFERROR(VLOOKUP(B10,'(B) FGs'!$B$6:$L$55,11,0),0) -> 0 | M10: =SUM(E10:L10) -> 0 | N10: =IFERROR(VLOOKUP(B10,'(B) FGs'!$B$6:$R$55,13,0),0) -> 0 | O10: =IFERROR(VLOOKUP(B10,'(A) Inventory'!$A$7:$R$89,18,0),0) -> 0 | P10: =IFERROR(VLOOKUP(B10,'(A) Inventory'!$A$7:$S$89,19,0),0) -> 0 | Q10: 0 | R10: =SUM(N10:Q10) -> 0 | S10: =IFERROR(VLOOKUP(B10,'(A) Inventory'!$A$7:$P$89,16,0),0) -> 0 | T10: =IFERROR(VLOOKUP(B10,'(A) Inventory'!$A$7:$R$89,18,0),0) -> 0 | U10: =SUM(S10:T10) -> 0 | V10: =IFERROR(VLOOKUP(B10,'(B) FGs'!$B$6:$S$55,18,0),0)-IFERROR(VLOOKUP(B10,'(B) FGs'!$B$6:$M$55,12,0),0) -> 0 | W10: =IFERROR(VLOOKUP(B10,'(B) FGs'!$B$6:$M$55,12,0),0) -> 0 | X10: =IFERROR(VLOOKUP(B10,'(A) Inventory'!$A$7:$S$89,19,0),0) -> 0 | Y10: 0 | Z10: =SUM(V10:Y10) -> 0 | AA10: 0 | AB10: 38 | AD10: =D10+M10+R10-U10-Z10-AA10=AB10 -> TRUE | AE10: =D10+M10+R10-U10-Z10-AA10-AB10 -> 0
B11: 716DD | C11: =VLOOKUP(B11,'재공품 (WIP)_생산실적'!$B$6:$C$88,2,FALSE) -> R&D | D11: =IFERROR(VLOOKUP(B11,'(A) Inventory'!$A$7:$C$89,3,0),0) -> 14976 | E11: =IFERROR(VLOOKUP(B11,'(B) FGs'!$B$6:$D$55,3,0),0) -> 0 | F11: =IFERROR(VLOOKUP(B11,'(B) FGs'!$B$6:$E$55,4,0),0) -> 0 | G11: =IFERROR(VLOOKUP(B11,'(B) FGs'!$B$6:$G$55,6,0),0) -> 0 | H11: =IFERROR(VLOOKUP(B11,'(B) FGs'!$B$6:$H$55,7,0),0) -> 0 | I11: =IFERROR(VLOOKUP(B11,'(B) FGs'!$B$6:$I$55,8,0),0) -> 0 | J11: =IFERROR(VLOOKUP(B11,'(B) FGs'!$B$6:$J$55,9,0),0) -> 0 | K11: 0 | L11: =IFERROR(VLOOKUP(B11,'(B) FGs'!$B$6:$L$55,11,0),0) -> 0 | M11: =SUM(E11:L11) -> 0 | N11: =IFERROR(VLOOKUP(B11,'(B) FGs'!$B$6:$R$55,13,0),0) -> 0 | O11: =IFERROR(VLOOKUP(B11,'(A) Inventory'!$A$7:$R$89,18,0),0) -> 0 | P11: =IFERROR(VLOOKUP(B11,'(A) Inventory'!$A$7:$S$89,19,0),0) -> 0 | Q11: 0 | R11: =SUM(N11:Q11) -> 0 | S11: =IFERROR(VLOOKUP(B11,'(A) Inventory'!$A$7:$P$89,16,0),0) -> 0 | T11: =IFERROR(VLOOKUP(B11,'(A) Inventory'!$A$7:$R$89,18,0),0) -> 0 | U11: =SUM(S11:T11) -> 0 | V11: =IFERROR(VLOOKUP(B11,'(B) FGs'!$B$6:$S$55,18,0),0)-IFERROR(VLOOKUP(B11,'(B) FGs'!$B$6:$M$55,12,0),0) -> 0 | W11: =IFERROR(VLOOKUP(B11,'(B) FGs'!$B$6:$M$55,12,0),0) -> 0 | X11: =IFERROR(VLOOKUP(B11,'(A) Inventory'!$A$7:$S$89,19,0),0) -> 0 | Y11: 0 | Z11: =SUM(V11:Y11) -> 0 | AA11: 0 | AB11: 14976 | AD11: =D11+M11+R11-U11-Z11-AA11=AB11 -> TRUE | AE11: =D11+M11+R11-U11-Z11-AA11-AB11 -> 0
B12: 716DTT | C12: =VLOOKUP(B12,'재공품 (WIP)_생산실적'!$B$6:$C$88,2,FALSE) -> R&D | D12: =IFERROR(VLOOKUP(B12,'(A) Inventory'!$A$7:$C$89,3,0),0) -> 0 | E12: =IFERROR(VLOOKUP(B12,'(B) FGs'!$B$6:$D$55,3,0),0) -> 0 | F12: =IFERROR(VLOOKUP(B12,'(B) FGs'!$B$6:$E$55,4,0),0) -> 0 | G12: =IFERROR(VLOOKUP(B12,'(B) FGs'!$B$6:$G$55,6,0),0) -> 0 | H12: =IFERROR(VLOOKUP(B12,'(B) FGs'!$B$6:$H$55,7,0),0) -> 0 | I12: =IFERROR(VLOOKUP(B12,'(B) FGs'!$B$6:$I$55,8,0),0) -> 0 | J12: =IFERROR(VLOOKUP(B12,'(B) FGs'!$B$6:$J$55,9,0),0) -> 0 | K12: 0 | L12: =IFERROR(VLOOKUP(B12,'(B) FGs'!$B$6:$L$55,11,0),0) -> 0 | M12: =SUM(E12:L12) -> 0 | N12: =IFERROR(VLOOKUP(B12,'(B) FGs'!$B$6:$R$55,13,0),0) -> 0 | O12: =IFERROR(VLOOKUP(B12,'(A) Inventory'!$A$7:$R$89,18,0),0) -> 0 | P12: =IFERROR(VLOOKUP(B12,'(A) Inventory'!$A$7:$S$89,19,0),0) -> 300 | Q12: 0 | R12: =SUM(N12:Q12) -> 300 | S12: =IFERROR(VLOOKUP(B12,'(A) Inventory'!$A$7:$P$89,16,0),0) -> 0 | T12: =IFERROR(VLOOKUP(B12,'(A) Inventory'!$A$7:$R$89,18,0),0) -> 0 | U12: =SUM(S12:T12) -> 0 | V12: =IFERROR(VLOOKUP(B12,'(B) FGs'!$B$6:$S$55,18,0),0)-IFERROR(VLOOKUP(B12,'(B) FGs'!$B$6:$M$55,12,0),0) -> 0 | W12: =IFERROR(VLOOKUP(B12,'(B) FGs'!$B$6:$M$55,12,0),0) -> 0 | X12: =IFERROR(VLOOKUP(B12,'(A) Inventory'!$A$7:$S$89,19,0),0) -> 300 | Y12: 0 | Z12: =SUM(V12:Y12) -> 300 | AA12: 0 | AB12: 0 | AD12: =D12+M12+R12-U12-Z12-AA12=AB12 -> TRUE | AE12: =D12+M12+R12-U12-Z12-AA12-AB12 -> 0
B13: 716ED | C13: =VLOOKUP(B13,'재공품 (WIP)_생산실적'!$B$6:$C$88,2,FALSE) -> R&D | D13: =IFERROR(VLOOKUP(B13,'(A) Inventory'!$A$7:$C$89,3,0),0) -> 0 | E13: =IFERROR(VLOOKUP(B13,'(B) FGs'!$B$6:$D$55,3,0),0) -> 0 | F13: =IFERROR(VLOOKUP(B13,'(B) FGs'!$B$6:$E$55,4,0),0) -> 0 | G13: =IFERROR(VLOOKUP(B13,'(B) FGs'!$B$6:$G$55,6,0),0) -> 0 | H13: =IFERROR(VLOOKUP(B13,'(B) FGs'!$B$6:$H$55,7,0),0) -> 0 | I13: =IFERROR(VLOOKUP(B13,'(B) FGs'!$B$6:$I$55,8,0),0) -> 0 | J13: =IFERROR(VLOOKUP(B13,'(B) FGs'!$B$6:$J$55,9,0),0) -> 0 | K13: 0 | L13: =IFERROR(VLOOKUP(B13,'(B) FGs'!$B$6:$L$55,11,0),0) -> 0 | M13: =SUM(E13:L13) -> 0 | N13: =IFERROR(VLOOKUP(B13,'(B) FGs'!$B$6:$R$55,13,0),0) -> 0 | O13: =IFERROR(VLOOKUP(B13,'(A) Inventory'!$A$7:$R$89,18,0),0) -> 0 | P13: =IFERROR(VLOOKUP(B13,'(A) Inventory'!$A$7:$S$89,19,0),0) -> 0 | Q13: 0 | R13: =SUM(N13:Q13) -> 0 | S13: =IFERROR(VLOOKUP(B13,'(A) Inventory'!$A$7:$P$89,16,0),0) -> 0 | T13: =IFERROR(VLOOKUP(B13,'(A) Inventory'!$A$7:$R$89,18,0),0) -> 0 | U13: =SUM(S13:T13) -> 0 | V13: =IFERROR(VLOOKUP(B13,'(B) FGs'!$B$6:$S$55,18,0),0)-IFERROR(VLOOKUP(B13,'(B) FGs'!$B$6:$M$55,12,0),0) -> 0 | W13: =IFERROR(VLOOKUP(B13,'(B) FGs'!$B$6:$M$55,12,0),0) -> 0 | X13: =IFERROR(VLOOKUP(B13,'(A) Inventory'!$A$7:$S$89,19,0),0) -> 0 | Y13: 0 | Z13: =SUM(V13:Y13) -> 0 | AA13: 0 | AB13: 0 | AD13: =D13+M13+R13-U13-Z13-AA13=AB13 -> TRUE | AE13: =D13+M13+R13-U13-Z13-AA13-AB13 -> 0
B14: 716ETT | C14: =VLOOKUP(B14,'재공품 (WIP)_생산실적'!$B$6:$C$88,2,FALSE) -> R&D | D14: =IFERROR(VLOOKUP(B14,'(A) Inventory'!$A$7:$C$89,3,0),0) -> 0 | E14: =IFERROR(VLOOKUP(B14,'(B) FGs'!$B$6:$D$55,3,0),0) -> 0 | F14: =IFERROR(VLOOKUP(B14,'(B) FGs'!$B$6:$E$55,4,0),0) -> 0 | G14: =IFERROR(VLOOKUP(B14,'(B) FGs'!$B$6:$G$55,6,0),0) -> 0 | H14: =IFERROR(VLOOKUP(B14,'(B) FGs'!$B$6:$H$55,7,0),0) -> 0 | I14: =IFERROR(VLOOKUP(B14,'(B) FGs'!$B$6:$I$55,8,0),0) -> 0 | J14: =IFERROR(VLOOKUP(B14,'(B) FGs'!$B$6:$J$55,9,0),0) -> 0 | K14: 0 | L14: =IFERROR(VLOOKUP(B14,'(B) FGs'!$B$6:$L$55,11,0),0) -> 0 | M14: =SUM(E14:L14) -> 0 | N14: =IFERROR(VLOOKUP(B14,'(B) FGs'!$B$6:$R$55,13,0),0) -> 0 | O14: =IFERROR(VLOOKUP(B14,'(A) Inventory'!$A$7:$R$89,18,0),0) -> 350 | P14: =IFERROR(VLOOKUP(B14,'(A) Inventory'!$A$7:$S$89,19,0),0) -> 0 | Q14: 0 | R14: =SUM(N14:Q14) -> 350 | S14: =IFERROR(VLOOKUP(B14,'(A) Inventory'!$A$7:$P$89,16,0),0) -> 0 | T14: =IFERROR(VLOOKUP(B14,'(A) Inventory'!$A$7:$R$89,18,0),0) -> 350 | U14: =SUM(S14:T14) -> 350 | V14: =IFERROR(VLOOKUP(B14,'(B) FGs'!$B$6:$S$55,18,0),0)-IFERROR(VLOOKUP(B14,'(B) FGs'!$B$6:$M$55,12,0),0) -> 0 | W14: =IFERROR(VLOOKUP(B14,'(B) FGs'!$B$6:$M$55,12,0),0) -> 0 | X14: =IFERROR(VLOOKUP(B14,'(A) Inventory'!$A$7:$S$89,19,0),0) -> 0 | Y14: 0 | Z14: =SUM(V14:Y14) -> 0 | AA14: 0 | AB14: 0 | AD14: =D14+M14+R14-U14-Z14-AA14=AB14 -> TRUE | AE14: =D14+M14+R14-U14-Z14-AA14-AB14 -> 0
B15: 716FD | C15: =VLOOKUP(B15,'재공품 (WIP)_생산실적'!$B$6:$C$88,2,FALSE) -> R&D | D15: =IFERROR(VLOOKUP(B15,'(A) Inventory'!$A$7:$C$89,3,0),0) -> 0 | E15: =IFERROR(VLOOKUP(B15,'(B) FGs'!$B$6:$D$55,3,0),0) -> 0 | F15: =IFERROR(VLOOKUP(B15,'(B) FGs'!$B$6:$E$55,4,0),0) -> 0 | G15: =IFERROR(VLOOKUP(B15,'(B) FGs'!$B$6:$G$55,6,0),0) -> 0 | H15: =IFERROR(VLOOKUP(B15,'(B) FGs'!$B$6:$H$55,7,0),0) -> 0 | I15: =IFERROR(VLOOKUP(B15,'(B) FGs'!$B$6:$I$55,8,0),0) -> 0 | J15: =IFERROR(VLOOKUP(B15,'(B) FGs'!$B$6:$J$55,9,0),0) -> 0 | K15: 0 | L15: =IFERROR(VLOOKUP(B15,'(B) FGs'!$B$6:$L$55,11,0),0) -> 0 | M15: =SUM(E15:L15) -> 0 | N15: =IFERROR(VLOOKUP(B15,'(B) FGs'!$B$6:$R$55,13,0),0) -> 0 | O15: =IFERROR(VLOOKUP(B15,'(A) Inventory'!$A$7:$R$89,18,0),0) -> 0 | P15: =IFERROR(VLOOKUP(B15,'(A) Inventory'!$A$7:$S$89,19,0),0) -> 0 | Q15: 0 | R15: =SUM(N15:Q15) -> 0 | S15: =IFERROR(VLOOKUP(B15,'(A) Inventory'!$A$7:$P$89,16,0),0) -> 0 | T15: =IFERROR(VLOOKUP(B15,'(A) Inventory'!$A$7:$R$89,18,0),0) -> 0 | U15: =SUM(S15:T15) -> 0 | V15: =IFERROR(VLOOKUP(B15,'(B) FGs'!$B$6:$S$55,18,0),0)-IFERROR(VLOOKUP(B15,'(B) FGs'!$B$6:$M$55,12,0),0) -> 0 | W15: =IFERROR(VLOOKUP(B15,'(B) FGs'!$B$6:$M$55,12,0),0) -> 0 | X15: =IFERROR(VLOOKUP(B15,'(A) Inventory'!$A$7:$S$89,19,0),0) -> 0 | Y15: 0 | Z15: =SUM(V15:Y15) -> 0 | AA15: 0 | AB15: 0 | AD15: =D15+M15+R15-U15-Z15-AA15=AB15 -> TRUE | AE15: =D15+M15+R15-U15-Z15-AA15-AB15 -> 0
B16: 716GD | C16: =VLOOKUP(B16,'재공품 (WIP)_생산실적'!$B$6:$C$88,2,FALSE) -> R&D | D16: =IFERROR(VLOOKUP(B16,'(A) Inventory'!$A$7:$C$89,3,0),0) -> 0 | E16: =IFERROR(VLOOKUP(B16,'(B) FGs'!$B$6:$D$55,3,0),0) -> 0 | F16: =IFERROR(VLOOKUP(B16,'(B) FGs'!$B$6:$E$55,4,0),0) -> 0 | G16: =IFERROR(VLOOKUP(B16,'(B) FGs'!$B$6:$G$55,6,0),0) -> 0 | H16: =IFERROR(VLOOKUP(B16,'(B) FGs'!$B$6:$H$55,7,0),0) -> 0 | I16: =IFERROR(VLOOKUP(B16,'(B) FGs'!$B$6:$I$55,8,0),0) -> 0 | J16: =IFERROR(VLOOKUP(B16,'(B) FGs'!$B$6:$J$55,9,0),0) -> 0 | K16: 0 | L16: =IFERROR(VLOOKUP(B16,'(B) FGs'!$B$6:$L$55,11,0),0) -> 0 | M16: =SUM(E16:L16) -> 0 | N16: =IFERROR(VLOOKUP(B16,'(B) FGs'!$B$6:$R$55,13,0),0) -> 0 | O16: =IFERROR(VLOOKUP(B16,'(A) Inventory'!$A$7:$R$89,18,0),0) -> 0 | P16: =IFERROR(VLOOKUP(B16,'(A) Inventory'!$A$7:$S$89,19,0),0) -> 0 | Q16: 0 | R16: =SUM(N16:Q16) -> 0 | S16: =IFERROR(VLOOKUP(B16,'(A) Inventory'!$A$7:$P$89,16,0),0) -> 0 | T16: =IFERROR(VLOOKUP(B16,'(A) Inventory'!$A$7:$R$89,18,0),0) -> 0 | U16: =SUM(S16:T16) -> 0 | V16: =IFERROR(VLOOKUP(B16,'(B) FGs'!$B$6:$S$55,18,0),0)-IFERROR(VLOOKUP(B16,'(B) FGs'!$B$6:$M$55,12,0),0) -> 0 | W16: =IFERROR(VLOOKUP(B16,'(B) FGs'!$B$6:$M$55,12,0),0) -> 0 | X16: =IFERROR(VLOOKUP(B16,'(A) Inventory'!$A$7:$S$89,19,0),0) -> 0 | Y16: 0 | Z16: =SUM(V16:Y16) -> 0 | AA16: 0 | AB16: 0 | AD16: =D16+M16+R16-U16-Z16-AA16=AB16 -> TRUE | AE16: =D16+M16+R16-U16-Z16-AA16-AB16 -> 0
B17: 716JD | C17: =VLOOKUP(B17,'재공품 (WIP)_생산실적'!$B$6:$C$88,2,FALSE) -> R&D | D17: =IFERROR(VLOOKUP(B17,'(A) Inventory'!$A$7:$C$89,3,0),0) -> 3773 | E17: =IFERROR(VLOOKUP(B17,'(B) FGs'!$B$6:$D$55,3,0),0) -> 0 | F17: =IFERROR(VLOOKUP(B17,'(B) FGs'!$B$6:$E$55,4,0),0) -> 0 | G17: =IFERROR(VLOOKUP(B17,'(B) FGs'!$B$6:$G$55,6,0),0) -> 0 | H17: =IFERROR(VLOOKUP(B17,'(B) FGs'!$B$6:$H$55,7,0),0) -> 0 | I17: =IFERROR(VLOOKUP(B17,'(B) FGs'!$B$6:$I$55,8,0),0) -> 0 | J17: =IFERROR(VLOOKUP(B17,'(B) FGs'!$B$6:$J$55,9,0),0) -> 0 | K17: 0 | L17: =IFERROR(VLOOKUP(B17,'(B) FGs'!$B$6:$L$55,11,0),0) -> 0 | M17: =SUM(E17:L17) -> 0 | N17: =IFERROR(VLOOKUP(B17,'(B) FGs'!$B$6:$R$55,13,0),0) -> 0 | O17: =IFERROR(VLOOKUP(B17,'(A) Inventory'!$A$7:$R$89,18,0),0) -> 0 | P17: =IFERROR(VLOOKUP(B17,'(A) Inventory'!$A$7:$S$89,19,0),0) -> 0 | Q17: 0 | R17: =SUM(N17:Q17) -> 0 | S17: =IFERROR(VLOOKUP(B17,'(A) Inventory'!$A$7:$P$89,16,0),0) -> 0 | T17: =IFERROR(VLOOKUP(B17,'(A) Inventory'!$A$7:$R$89,18,0),0) -> 0 | U17: =SUM(S17:T17) -> 0 | V17: =IFERROR(VLOOKUP(B17,'(B) FGs'!$B$6:$S$55,18,0),0)-IFERROR(VLOOKUP(B17,'(B) FGs'!$B$6:$M$55,12,0),0) -> 0 | W17: =IFERROR(VLOOKUP(B17,'(B) FGs'!$B$6:$M$55,12,0),0) -> 0 | X17: =IFERROR(VLOOKUP(B17,'(A) Inventory'!$A$7:$S$89,19,0),0) -> 0 | Y17: 0 | Z17: =SUM(V17:Y17) -> 0 | AA17: 0 | AB17: 3773 | AD17: =D17+M17+R17-U17-Z17-AA17=AB17 -> TRUE | AE17: =D17+M17+R17-U17-Z17-AA17-AB17 -> 0
B18: 716KD | C18: =VLOOKUP(B18,'재공품 (WIP)_생산실적'!$B$6:$C$88,2,FALSE) -> R&D | D18: =IFERROR(VLOOKUP(B18,'(A) Inventory'!$A$7:$C$89,3,0),0) -> 1943 | E18: =IFERROR(VLOOKUP(B18,'(B) FGs'!$B$6:$D$55,3,0),0) -> 393 | F18: =IFERROR(VLOOKUP(B18,'(B) FGs'!$B$6:$E$55,4,0),0) -> 0 | G18: =IFERROR(VLOOKUP(B18,'(B) FGs'!$B$6:$G$55,6,0),0) -> 0 | H18: =IFERROR(VLOOKUP(B18,'(B) FGs'!$B$6:$H$55,7,0),0) -> 0 | I18: =IFERROR(VLOOKUP(B18,'(B) FGs'!$B$6:$I$55,8,0),0) -> 0 | J18: =IFERROR(VLOOKUP(B18,'(B) FGs'!$B$6:$J$55,9,0),0) -> 0 | K18: 0 | L18: =IFERROR(VLOOKUP(B18,'(B) FGs'!$B$6:$L$55,11,0),0) -> 0 | M18: =SUM(E18:L18) -> 393 | N18: =IFERROR(VLOOKUP(B18,'(B) FGs'!$B$6:$R$55,13,0),0) -> 0 | O18: =IFERROR(VLOOKUP(B18,'(A) Inventory'!$A$7:$R$89,18,0),0) -> 0 | P18: =IFERROR(VLOOKUP(B18,'(A) Inventory'!$A$7:$S$89,19,0),0) -> 0 | Q18: 0 | R18: =SUM(N18:Q18) -> 0 | S18: =IFERROR(VLOOKUP(B18,'(A) Inventory'!$A$7:$P$89,16,0),0) -> 0 | T18: =IFERROR(VLOOKUP(B18,'(A) Inventory'!$A$7:$R$89,18,0),0) -> 0 | U18: =SUM(S18:T18) -> 0 | V18: =IFERROR(VLOOKUP(B18,'(B) FGs'!$B$6:$S$55,18,0),0)-IFERROR(VLOOKUP(B18,'(B) FGs'!$B$6:$M$55,12,0),0) -> 0 | W18: =IFERROR(VLOOKUP(B18,'(B) FGs'!$B$6:$M$55,12,0),0) -> 0 | X18: =IFERROR(VLOOKUP(B18,'(A) Inventory'!$A$7:$S$89,19,0),0) -> 0 | Y18: 0 | Z18: =SUM(V18:Y18) -> 0 | AA18: 0 | AB18: 2336 | AD18: =D18+M18+R18-U18-Z18-AA18=AB18 -> TRUE | AE18: =D18+M18+R18-U18-Z18-AA18-AB18 -> 0
... B88: 8191D | C88: =VLOOKUP(B88,'재공품 (WIP)_생산실적'!$B$6:$C$88,2,FALSE) -> R&D | D88: =IFERROR(VLOOKUP(B88,'(A) Inventory'!$A$7:$C$89,3,0),0) -> 120 | E88: =IFERROR(VLOOKUP(B88,'(B) FGs'!$B$6:$D$55,3,0),0) -> 0 | F88: =IFERROR(VLOOKUP(B88,'(B) FGs'!$B$6:$E$55,4,0),0) -> 0 | G88: =IFERROR(VLOOKUP(B88,'(B) FGs'!$B$6:$G$55,6,0),0) -> 0 | H88: =IFERROR(VLOOKUP(B88,'(B) FGs'!$B$6:$H$55,7,0),0) -> 0 | I88: =IFERROR(VLOOKUP(B88,'(B) FGs'!$B$6:$I$55,8,0),0) -> 0 | J88: =IFERROR(VLOOKUP(B88,'(B) FGs'!$B$6:$J$55,9,0),0) -> 0 | K88: 0 | L88: =IFERROR(VLOOKUP(B88,'(B) FGs'!$B$6:$L$55,11,0),0) -> 0 | M88: =SUM(E88:L88) -> 0 | N88: =IFERROR(VLOOKUP(B88,'(B) FGs'!$B$6:$R$55,13,0),0) -> 0 | O88: =IFERROR(VLOOKUP(B88,'(A) Inventory'!$A$7:$R$89,18,0),0) -> 0 | P88: =IFERROR(VLOOKUP(B88,'(A) Inventory'!$A$7:$S$89,19,0),0) -> 0 | Q88: 0 | R88: =SUM(N88:Q88) -> 0 | S88: =IFERROR(VLOOKUP(B88,'(A) Inventory'!$A$7:$P$89,16,0),0) -> 0 | T88: =IFERROR(VLOOKUP(B88,'(A) Inventory'!$A$7:$R$89,18,0),0) -> 0 | U88: =SUM(S88:T88) -> 0 | V88: =IFERROR(VLOOKUP(B88,'(B) FGs'!$B$6:$S$55,18,0),0)-IFERROR(VLOOKUP(B88,'(B) FGs'!$B$6:$M$55,12,0),0) -> 0 | W88: =IFERROR(VLOOKUP(B88,'(B) FGs'!$B$6:$M$55,12,0),0) -> 0 | X88: =IFERROR(VLOOKUP(B88,'(A) Inventory'!$A$7:$S$89,19,0),0) -> 0 | Y88: 0 | Z88: =SUM(V88:Y88) -> 0 | AA88: 0 | AB88: 120 | AD88: =D88+M88+R88-U88-Z88-AA88=AB88 -> TRUE | AE88: =D88+M88+R88-U88-Z88-AA88-AB88 -> 0
B89: TOTAL | D89: =SUM(D6:D88) -> 679860 | E89: =SUM(E6:E88) -> 50800 | F89: =SUM(F6:F88) -> 646966 | G89: =SUM(G6:G88) -> 23934 | H89: =SUM(H6:H88) -> 0 | I89: =SUM(I6:I88) -> 0 | J89: =SUM(J6:J88) -> 257976 | K89: =SUM(K6:K88) -> 9997 | ... AB89: =SUM(AB6:AB88) -> 414135 | AD89: =D89+M89+R89-U89-Z89-AA89=AB89 -> TRUE | AE89: =D89+M89+R89-U89-Z89-AA89-AB89 -> 0

Sheet 재공품 (WIP) (제조원가_재공)
AB1: 열고 닫는 기능 추가 필요 (좌측으로) | AH1: 전월 재공평가 단가 사용 | AR1: 열고 닫는 기능 추가 필요 (좌측으로) | AV1: 전월 재공평가 단가 사용 | BL1: 열고 닫는 기능 추가 필요 (좌측으로) | CT1: 열고 닫는 기능 추가 필요 (좌측으로)
B2: 모델 Model | C2: 구분 Division | D2: 기초 / BOH | AF2: 입고 / INPUT | AH2: 기타입고 / Other Input (6=1+2+3+4+5) | AT2: 출고 / OUTPUT | AV2: 기타출고 / Other Output | BP2: LOSS (SCRAP) | BV2: 재고 / EOH
D3: 1 | H3: 2 | L3: 3=1+2 | P3: 4 | T3: 5 | X3: 6=4+5 | AB3: 7=3+6 | AF3: 1 | AH3: 1 | AJ3: 2 | AL3: 3 | AN3: 4 | AP3: 5 | AR3: 6 | AT3: 1 | AV3: 1 | AZ3: 2 | BD3: 3 | BH3: 4 | BL3: 5 | BV3: 1 | BZ3: 2 | CD3: 3 | CH3: 4 | CL3: 5 (1+3) | CP3: 6 (2+4) | CT3: TOTAL_EOH (MES) 7=5+6
D4: LINE_WIP | H4: LINE_FGS | L4: BOH A_LEVEL SUB TOTAL | P4: B_LEVEL_WIP | T4: B_LEVEL_FGS | X4: BOH B_LEVEL SUB TOTAL | AB4: T_BOH | AF4: USC_INPUT (C) | AH4: CODE 변경 | AJ4: Re-Sorting (재검사) | AL4: Re-work (SI검사) | AN4: 반제품 입고 | AP4: 기타 | AR4: 기타입고 | AT4: OUTPUT_A (C) | AV4: CODE 변경 | AZ4: 반제품 출고 (유상) | BD4: 반제품 출고 (무상) | BH4: 기타 | BL4: 기타출고 (5=1+2+3+4) | BV4: LINE_WIP (A) | BZ4: LINE_FGs (A) | CD4: B_LEVEL WIP (A) | CH4: B_LEVEL FGs | CL4: T_EOH WIP | CP4: T_EOH FGs
D5: PFL전 50% | F5: PFL후 90% | H5: PFL전 50% | J5: PFL후 90% | L5: PFL전 50% | N5: PFL후 90% | P5: PFL전 50% | R5: PFL후 90% | T5: PFL전 50% | V5: PFL후 90% | X5: PFL전 50% | Z5: PFL후 90% | AB5: PFL전 50% | AD5: PFL후 90% | AV5: PFL전 50% | AX5: PFL후 90% | AZ5: PFL전 50% | BB5: PFL후 90% | BD5: PFL전 50% | BF5: PFL후 90% | BH5: PFL전 50% | BJ5: PFL후 90% | BL5: PFL전 50% | BN5: PFL후 90% | BP5: PFL전 50% | BR5: PFL후 90% | BT5: 합계 | BV5: PFL전 50% | BX5: PFL후 90% | BZ5: PFL전 50% | CB5: PFL후 90% | CD5: PFL전 50% | CF5: PFL후 90% | CH5: PFL전 50% | CJ5: PFL후 90% | CL5: PFL전 50% | CN5: PFL후 90% | CP5: PFL전 50% | CR5: PFL후 90% | CT5: PFL전 50% | CV5: PFL후 90%
D6: 수량 | E6: 금액 | F6: 수량 | G6: 금액 | H6: 수량 | I6: 금액 | J6: 수량 | K6: 금액 | L6: 수량 | M6: 금액 | N6: 수량 | O6: 금액 | P6: 수량 | Q6: 금액 | R6: 수량 | S6: 금액 | T6: 수량 | U6: 금액 | V6: 수량 | W6: 금액 | X6: 수량 | Y6: 금액 | Z6: 수량 | AA6: 금액 | AB6: 수량 | AC6: 금액 | AD6: 수량 | AE6: 금액 | AF6: 수량 | AG6: 금액 | AH6: 수량 | AI6: 금액 | AJ6: 수량 | AK6: 금액 | AL6: 수량 | AM6: 금액 | AN6: 수량 | AO6: 금액 | AP6: 수량 | AQ6: 금액 | AR6: 수량 | AS6: 금액 | AT6: 수량 | AU6: 금액 | AV6: 수량 | AW6: 금액 | AX6: 수량 | AY6: 금액 | AZ6: 수량 | BA6: 금액 | BB6: 수량 | BC6: 금액 | BD6: 수량 | BE6: 금액 | BF6: 수량 | BG6: 금액 | BH6: 수량 | BI6: 금액 | BJ6: 수량 | BK6: 금액 | BL6: 수량 | BM6: 금액 | BN6: 수량 | BO6: 금액 | BP6: 수량 | BQ6: 금액 | BR6: 수량 | BS6: 금액 | BT6: 수량 | BU6: 금액 | BV6: 수량 | BW6: 금액 | BX6: 수량 | BY6: 금액 | BZ6: 수량 | CA6: 금액 | CB6: 수량 | CC6: 금액 | CD6: 수량 | CE6: 금액 | CF6: 수량 | CG6: 금액 | CH6: 수량 | CI6: 금액 | CJ6: 수량 | CK6: 금액 | CL6: 수량 | CM6: 금액 | CN6: 수량 | CO6: 금액 | CP6: 수량 | CQ6: 금액 | CR6: 수량 | CS6: 금액 | CT6: 수량 | CU6: 금액 | CV6: 수량 | CW6: 금액
B7: 7075P | C7: MP | D7: 0 | F7: 0 | H7: 0 | J7: 0 | L7: =D7+H7 -> 0 | M7: =E7+I7 -> 0 | N7: =F7+J7 -> 0 | O7: =G7+K7 -> 0 | P7: 6 | R7: 7 | T7: 0 | V7: 0 | X7: =P7+T7 -> 6 | Y7: =Q7+U7 -> 0 | Z7: =R7+V7 -> 7 | AA7: =S7+W7 -> 0 | AB7: =L7+X7 -> 6 | AC7: =M7+Y7 -> 0 | AD7: =N7+Z7 -> 7 | AE7: =O7+AA7 -> 0 | AF7: 0 | AH7: 0 | AJ7: 0 | AL7: 0 | AN7: 0 | AP7: 0 | AR7: =AH7+AJ7+AL7+AN7+AP7 -> 0 | AS7: =AI7+AK7+AM7+AO7+AQ7 -> 0 | AT7: 0 | AV7: 0 | AX7: 0 | AZ7: 0 | BB7: 0 | BD7: 0 | BF7: 0 | BH7: 0 | BJ7: 0 | BL7: =AV7+AX7+AZ7+BB7+BD7+BF7+BH7+BJ7 -> 0 | BM7: =AW7+AY7+BA7+BC7+BE7+BG7+BI7+BK7 -> 0 | BN7: =AX7+AZ7+BB7+BD7+BF7+BH7+BJ7+BL7 -> 0 | BO7: =AY7+BA7+BC7+BE7+BG7+BI7+BK7+BM7 -> 0 | BP7: 0 | BR7: 0 | BT7: =BP7+BR7 -> 0 | BU7: =BQ7+BS7 -> 0 | BV7: 0 | BX7: 0 | BZ7: 0 | CB7: 0 | CD7: 6 | CF7: 7 | CH7: 0 | CJ7: 0 | CL7: =BV7+CD7 -> 6 | CM7: =BW7+CE7 -> 0 | CN7: =BX7+CF7 -> 7 | CO7: =BY7+CG7 -> 0 | CP7: =BZ7+CH7 -> 0 | CQ7: =CA7+CI7 -> 0 | CR7: =CB7+CJ7 -> 0 | CS7: =CC7+CK7 -> 0 | CT7: =CL7+CP7 -> 6 | CU7: =CM7+CQ7 -> 0 | CV7: =CN7+CR7 -> 7 | CW7: =CO7+CS7 -> 0
B8: 712TP | C8: MP | D8: 0 | F8: 0 | H8: 0 | J8: 0 | L8: =D8+H8 -> 0 | M8: =E8+I8 -> 0 | N8: =F8+J8 -> 0 | O8: =G8+K8 -> 0 | P8: 173 | R8: 11 | T8: 0 | V8: 0 | X8: =P8+T8 -> 173 | Y8: =Q8+U8 -> 0 | Z8: =R8+V8 -> 11 | AA8: =S8+W8 -> 0 | AB8: =L8+X8 -> 173 | AC8: =M8+Y8 -> 0 | AD8: =N8+Z8 -> 11 | AE8: =O8+AA8 -> 0 | AF8: 0 | AH8: 0 | AJ8: 0 | AL8: 0 | AN8: 0 | AP8: 0 | AR8: =AH8+AJ8+AL8+AN8+AP8 -> 0 | AS8: =AI8+AK8+AM8+AO8+AQ8 -> 0 | AT8: 0 | AV8: 0 | AX8: 0 | AZ8: 0 | BB8: 0 | BD8: 0 | BF8: 0 | BH8: 0 | BJ8: 0 | BL8: =AV8+AX8+AZ8+BB8+BD8+BF8+BH8+BJ8 -> 0 | BM8: =AW8+AY8+BA8+BC8+BE8+BG8+BI8+BK8 -> 0 | BN8: =AX8+AZ8+BB8+BD8+BF8+BH8+BJ8+BL8 -> 0 | BO8: =AY8+BA8+BC8+BE8+BG8+BI8+BK8+BM8 -> 0 | BP8: 0 | BR8: 0 | BT8: =BP8+BR8 -> 0 | BU8: =BQ8+BS8 -> 0 | BV8: 0 | BX8: 0 | BZ8: 0 | CB8: 0 | CD8: 173 | CF8: 11 | CH8: 0 | CJ8: 0 | CL8: =BV8+CD8 -> 173 | CM8: =BW8+CE8 -> 0 | CN8: =BX8+CF8 -> 11 | CO8: =BY8+CG8 -> 0 | CP8: =BZ8+CH8 -> 0 | CQ8: =CA8+CI8 -> 0 | CR8: =CB8+CJ8 -> 0 | CS8: =CC8+CK8 -> 0 | CT8: =CL8+CP8 -> 173 | CU8: =CM8+CQ8 -> 0 | CV8: =CN8+CR8 -> 11 | CW8: =CO8+CS8 -> 0
B9: 716AP | C9: MP | D9: 30912 | F9: 17821 | H9: 0 | J9: 15621 | L9: =D9+H9 -> 30912 | M9: =E9+I9 -> 0 | N9: =F9+J9 -> 33442 | O9: =G9+K9 -> 0 | P9: 2246 | R9: 292 | T9: 0 | V9: 23 | X9: =P9+T9 -> 2246 | Y9: =Q9+U9 -> 0 | Z9: =R9+V9 -> 315 | AA9: =S9+W9 -> 0 | AB9: =L9+X9 -> 33158 | AC9: =M9+Y9 -> 0 | AD9: =N9+Z9 -> 33757 | AE9: =O9+AA9 -> 0 | AF9: 499392 | AH9: 0 | AJ9: 260558 | AL9: 9765 | AN9: 0 | AP9: 0 | AR9: =AH9+AJ9+AL9+AN9+AP9 -> 270323 | AS9: =AI9+AK9+AM9+AO9+AQ9 -> 0 | AT9: 757675 | AV9: 0 | AX9: 0 | AZ9: 0 | BB9: 10 | BD9: 5 | BF9: 0 | BH9: 0 | BJ9: 0 | BL9: =AV9+AX9+AZ9+BB9+BD9+BF9+BH9+BJ9 -> 15 | BM9: =AW9+AY9+BA9+BC9+BE9+BG9+BI9+BK9 -> 0 | BN9: =AX9+AZ9+BB9+BD9+BF9+BH9+BJ9+BL9 -> 30 | BO9: =AY9+BA9+BC9+BE9+BG9+BI9+BK9+BM9 -> 0 | BP9: 10901 | BR9: 8366 | BT9: =BP9+BR9 -> 19267 | BU9: =BQ9+BS9 -> 0 | BV9: 33958 | BX9: 13774 | BZ9: 0 | CB9: 8103 | CD9: 3283 | CF9: 502 | CH9: 0 | CJ9: 53 | CL9: =BV9+CD9 -> 37241 | CM9: =BW9+CE9 -> 0 | CN9: =BX9+CF9 -> 14276 | CO9: =BY9+CG9 -> 0 | CP9: =BZ9+CH9 -> 0 | CQ9: =CA9+CI9 -> 0 | CR9: =CB9+CJ9 -> 8156 | CS9: =CC9+CK9 -> 0 | CT9: =CL9+CP9 -> 37241 | CU9: =CM9+CQ9 -> 0 | CV9: =CN9+CR9 -> 22432 | CW9: =CO9+CS9 -> 0
B10: 716BD | C10: R&D | D10: 0 | F10: 0 | H10: 0 | J10: 0 | L10: =D10+H10 -> 0 | M10: =E10+I10 -> 0 | N10: =F10+J10 -> 0 | O10: =G10+K10 -> 0 | P10: 69 | R10: 4 | T10: 0 | V10: 0 | X10: =P10+T10 -> 69 | Y10: =Q10+U10 -> 0 | Z10: =R10+V10 -> 4 | AA10: =S10+W10 -> 0 | AB10: =L10+X10 -> 69 | AC10: =M10+Y10 -> 0 | AD10: =N10+Z10 -> 4 | AE10: =O10+AA10 -> 0 | AF10: 0 | AH10: 0 | AJ10: 0 | AL10: 0 | AN10: 0 | AP10: 0 | AR10: =AH10+AJ10+AL10+AN10+AP10 -> 0 | AS10: =AI10+AK10+AM10+AO10+AQ10 -> 0 | AT10: 0 | AV10: 0 | AX10: 0 | AZ10: 0 | BB10: 0 | BD10: 0 | BF10: 0 | BH10: 0 | BJ10: 0 | BL10: =AV10+AX10+AZ10+BB10+BD10+BF10+BH10+BJ10 -> 0 | BM10: =AW10+AY10+BA10+BC10+BE10+BG10+BI10+BK10 -> 0 | BN10: =AX10+AZ10+BB10+BD10+BF10+BH10+BJ10+BL10 -> 0 | BO10: =AY10+BA10+BC10+BE10+BG10+BI10+BK10+BM10 -> 0 | BP10: 0 | BR10: 0 | BT10: =BP10+BR10 -> 0 | BU10: =BQ10+BS10 -> 0 | BV10: 0 | BX10: 0 | BZ10: 0 | CB10: 0 | CD10: 69 | CF10: 4 | CH10: 0 | CJ10: 0 | CL10: =BV10+CD10 -> 69 | CM10: =BW10+CE10 -> 0 | CN10: =BX10+CF10 -> 4 | CO10: =BY10+CG10 -> 0 | CP10: =BZ10+CH10 -> 0 | CQ10: =CA10+CI10 -> 0 | CR10: =CB10+CJ10 -> 0 | CS10: =CC10+CK10 -> 0 | CT10: =CL10+CP10 -> 69 | CU10: =CM10+CQ10 -> 0 | CV10: =CN10+CR10 -> 4 | CW10: =CO10+CS10 -> 0
B11: 716CD | C11: R&D | D11: 0 | F11: 0 | H11: 0 | J11: 0 | L11: =D11+H11 -> 0 | M11: =E11+I11 -> 0 | N11: =F11+J11 -> 0 | O11: =G11+K11 -> 0 | P11: 0 | R11: 1 | T11: 0 | V11: 0 | X11: =P11+T11 -> 0 | Y11: =Q11+U11 -> 0 | Z11: =R11+V11 -> 1 | AA11: =S11+W11 -> 0 | AB11: =L11+X11 -> 0 | AC11: =M11+Y11 -> 0 | AD11: =N11+Z11 -> 1 | AE11: =O11+AA11 -> 0 | AF11: 0 | AH11: 0 | AJ11: 0 | AL11: 0 | AN11: 0 | AP11: 0 | AR11: =AH11+AJ11+AL11+AN11+AP11 -> 0 | AS11: =AI11+AK11+AM11+AO11+AQ11 -> 0 | AT11: 0 | AV11: 0 | AX11: 0 | AZ11: 0 | BB11: 0 | BD11: 0 | BF11: 0 | BH11: 0 | BJ11: 0 | BL11: =AV11+AX11+AZ11+BB11+BD11+BF11+BH11+BJ11 -> 0 | BM11: =AW11+AY11+BA11+BC11+BE11+BG11+BI11+BK11 -> 0 | BN11: =AX11+AZ11+BB11+BD11+BF11+BH11+BJ11+BL11 -> 0 | BO11: =AY11+BA11+BC11+BE11+BG11+BI11+BK11+BM11 -> 0 | BP11: 0 | BR11: 0 | BT11: =BP11+BR11 -> 0 | BU11: =BQ11+BS11 -> 0 | BV11: 0 | BX11: 0 | BZ11: 0 | CB11: 0 | CD11: 0 | CF11: 1 | CH11: 0 | CJ11: 0 | CL11: =BV11+CD11 -> 0 | CM11: =BW11+CE11 -> 0 | CN11: =BX11+CF11 -> 1 | CO11: =BY11+CG11 -> 0 | CP11: =BZ11+CH11 -> 0 | CQ11: =CA11+CI11 -> 0 | CR11: =CB11+CJ11 -> 0 | CS11: =CC11+CK11 -> 0 | CT11: =CL11+CP11 -> 0 | CU11: =CM11+CQ11 -> 0 | CV11: =CN11+CR11 -> 1 | CW11: =CO11+CS11 -> 0
B12: 716DD | C12: R&D | D12: 0 | F12: 0 | H12: 0 | J12: 0 | L12: =D12+H12 -> 0 | M12: =E12+I12 -> 0 | N12: =F12+J12 -> 0 | O12: =G12+K12 -> 0 | P12: 328 | R12: 2161 | T12: 0 | V12: 144 | X12: =P12+T12 -> 328 | Y12: =Q12+U12 -> 0 | Z12: =R12+V12 -> 2305 | AA12: =S12+W12 -> 0 | AB12: =L12+X12 -> 328 | AC12: =M12+Y12 -> 0 | AD12: =N12+Z12 -> 2305 | AE12: =O12+AA12 -> 0 | AF12: 0 | AH12: 0 | AJ12: 0 | AL12: 0 | AN12: 0 | AP12: 0 | AR12: =AH12+AJ12+AL12+AN12+AP12 -> 0 | AS12: =AI12+AK12+AM12+AO12+AQ12 -> 0 | AT12: 0 | AV12: 0 | AX12: 0 | AZ12: 0 | BB12: 0 | BD12: 0 | BF12: 0 | BH12: 0 | BJ12: 0 | BL12: =AV12+AX12+AZ12+BB12+BD12+BF12+BH12+BJ12 -> 0 | BM12: =AW12+AY12+BA12+BC12+BE12+BG12+BI12+BK12 -> 0 | BN12: =AX12+AZ12+BB12+BD12+BF12+BH12+BJ12+BL12 -> 0 | BO12: =AY12+BA12+BC12+BE12+BG12+BI12+BK12+BM12 -> 0 | BP12: 0 | BR12: 2295 | BT12: =BP12+BR12 -> 2295 | BU12: =BQ12+BS12 -> 0 | BV12: 0 | BX12: 0 | BZ12: 0 | CB12: 0 | CD12: 328 | CF12: 10 | CH12: 0 | CJ12: 0 | CL12: =BV12+CD12 -> 328 | CM12: =BW12+CE12 -> 0 | CN12: =BX12+CF12 -> 10 | CO12: =BY12+CG12 -> 0 | CP12: =BZ12+CH12 -> 0 | CQ12: =CA12+CI12 -> 0 | CR12: =CB12+CJ12 -> 0 | CS12: =CC12+CK12 -> 0 | CT12: =CL12+CP12 -> 328 | CU12: =CM12+CQ12 -> 0 | CV12: =CN12+CR12 -> 10 | CW12: =CO12+CS12 -> 0
B13: 716DTT | C13: R&D | D13: 0 | F13: 0 | H13: 0 | J13: 0 | L13: =D13+H13 -> 0 | M13: =E13+I13 -> 0 | N13: =F13+J13 -> 0 | O13: =G13+K13 -> 0 | P13: 320 | R13: 0 | T13: 0 | V13: 0 | X13: =P13+T13 -> 320 | Y13: =Q13+U13 -> 0 | Z13: =R13+V13 -> 0 | AA13: =S13+W13 -> 0 | AB13: =L13+X13 -> 320 | AC13: =M13+Y13 -> 0 | AD13: =N13+Z13 -> 0 | AE13: =O13+AA13 -> 0 | AF13: 16 | AH13: 0 | AJ13: 0 | AL13: 0 | AN13: 0 | AP13: 0 | AR13: =AH13+AJ13+AL13+AN13+AP13 -> 0 | AS13: =AI13+AK13+AM13+AO13+AQ13 -> 0 | AT13: 0 | AV13: 0 | AX13: 0 | AZ13: 0 | BB13: 0 | BD13: 300 | BF13: 0 | BH13: 0 | BJ13: 0 | BL13: =AV13+AX13+AZ13+BB13+BD13+BF13+BH13+BJ13 -> 300 | BM13: =AW13+AY13+BA13+BC13+BE13+BG13+BI13+BK13 -> 0 | BN13: =AX13+AZ13+BB13+BD13+BF13+BH13+BJ13+BL13 -> 600 | BO13: =AY13+BA13+BC13+BE13+BG13+BI13+BK13+BM13 -> 0 | BP13: 36 | BR13: 0 | BT13: =BP13+BR13 -> 36 | BU13: =BQ13+BS13 -> 0 | BV13: 0 | BX13: 0 | BZ13: 0 | CB13: 0 | CD13: 0 | CF13: 0 | CH13: 0 | CJ13: 0 | CL13: =BV13+CD13 -> 0 | CM13: =BW13+CE13 -> 0 | CN13: =BX13+CF13 -> 0 | CO13: =BY13+CG13 -> 0 | CP13: =BZ13+CH13 -> 0 | CQ13: =CA13+CI13 -> 0 | CR13: =CB13+CJ13 -> 0 | CS13: =CC13+CK13 -> 0 | CT13: =CL13+CP13 -> 0 | CU13: =CM13+CQ13 -> 0 | CV13: =CN13+CR13 -> 0 | CW13: =CO13+CS13 -> 0
B14: 716ED | C14: R&D | D14: 0 | F14: 0 | H14: 0 | J14: 0 | L14: =D14+H14 -> 0 | M14: =E14+I14 -> 0 | N14: =F14+J14 -> 0 | O14: =G14+K14 -> 0 | P14: 31 | R14: 1 | T14: 0 | V14: 0 | X14: =P14+T14 -> 31 | Y14: =Q14+U14 -> 0 | Z14: =R14+V14 -> 1 | AA14: =S14+W14 -> 0 | AB14: =L14+X14 -> 31 | AC14: =M14+Y14 -> 0 | AD14: =N14+Z14 -> 1 | AE14: =O14+AA14 -> 0 | AF14: 0 | AH14: 0 | AJ14: 0 | AL14: 0 | AN14: 0 | AP14: 0 | AR14: =AH14+AJ14+AL14+AN14+AP14 -> 0 | AS14: =AI14+AK14+AM14+AO14+AQ14 -> 0 | AT14: 0 | AV14: 0 | AX14: 0 | AZ14: 0 | BB14: 0 | BD14: 0 | BF14: 0 | BH14: 0 | BJ14: 0 | BL14: =AV14+AX14+AZ14+BB14+BD14+BF14+BH14+BJ14 -> 0 | BM14: =AW14+AY14+BA14+BC14+BE14+BG14+BI14+BK14 -> 0 | BN14: =AX14+AZ14+BB14+BD14+BF14+BH14+BJ14+BL14 -> 0 | BO14: =AY14+BA14+BC14+BE14+BG14+BI14+BK14+BM14 -> 0 | BP14: 0 | BR14: 0 | BT14: =BP14+BR14 -> 0 | BU14: =BQ14+BS14 -> 0 | BV14: 0 | BX14: 0 | BZ14: 0 | CB14: 0 | CD14: 31 | CF14: 1 | CH14: 0 | CJ14: 0 | CL14: =BV14+CD14 -> 31 | CM14: =BW14+CE14 -> 0 | CN14: =BX14+CF14 -> 1 | CO14: =BY14+CG14 -> 0 | CP14: =BZ14+CH14 -> 0 | CQ14: =CA14+CI14 -> 0 | CR14: =CB14+CJ14 -> 0 | CS14: =CC14+CK14 -> 0 | CT14: =CL14+CP14 -> 31 | CU14: =CM14+CQ14 -> 0 | CV14: =CN14+CR14 -> 1 | CW14: =CO14+CS14 -> 0
B15: 716ETT | C15: R&D | D15: 0 | F15: 0 | H15: 0 | J15: 0 | L15: =D15+H15 -> 0 | M15: =E15+I15 -> 0 | N15: =F15+J15 -> 0 | O15: =G15+K15 -> 0 | P15: 576 | R15: 0 | T15: 0 | V15: 0 | X15: =P15+T15 -> 576 | Y15: =Q15+U15 -> 0 | Z15: =R15+V15 -> 0 | AA15: =S15+W15 -> 0 | AB15: =L15+X15 -> 576 | AC15: =M15+Y15 -> 0 | AD15: =N15+Z15 -> 0 | AE15: =O15+AA15 -> 0 | AF15: 256 | AH15: 0 | AJ15: 0 | AL15: 0 | AN15: 0 | AP15: 0 | AR15: =AH15+AJ15+AL15+AN15+AP15 -> 0 | AS15: =AI15+AK15+AM15+AO15+AQ15 -> 0 | AT15: 0 | AV15: 0 | AX15: 0 | AZ15: 350 | BB15: 0 | BD15: 0 | BF15: 0 | BH15: 0 | BJ15: 0 | BL15: =AV15+AX15+AZ15+BB15+BD15+BF15+BH15+BJ15 -> 350 | BM15: =AW15+AY15+BA15+BC15+BE15+BG15+BI15+BK15 -> 0 | BN15: =AX15+AZ15+BB15+BD15+BF15+BH15+BJ15+BL15 -> 700 | BO15: =AY15+BA15+BC15+BE15+BG15+BI15+BK15+BM15 -> 0 | BP15: 418 | BR15: 0 | BT15: =BP15+BR15 -> 418 | BU15: =BQ15+BS15 -> 0 | BV15: 0 | BX15: 0 | BZ15: 0 | CB15: 0 | CD15: 64 | CF15: 0 | CH15: 0 | CJ15: 0 | CL15: =BV15+CD15 -> 64 | CM15: =BW15+CE15 -> 0 | CN15: =BX15+CF15 -> 0 | CO15: =BY15+CG15 -> 0 | CP15: =BZ15+CH15 -> 0 | CQ15: =CA15+CI15 -> 0 | CR15: =CB15+CJ15 -> 0 | CS15: =CC15+CK15 -> 0 | CT15: =CL15+CP15 -> 64 | CU15: =CM15+CQ15 -> 0 | CV15: =CN15+CR15 -> 0 | CW15: =CO15+CS15 -> 0
B16: 716FD | C16: R&D | D16: 0 | F16: 0 | H16: 0 | J16: 0 | L16: =D16+H16 -> 0 | M16: =E16+I16 -> 0 | N16: =F16+J16 -> 0 | O16: =G16+K16 -> 0 | P16: 67 | R16: 1 | T16: 0 | V16: 0 | X16: =P16+T16 -> 67 | Y16: =Q16+U16 -> 0 | Z16: =R16+V16 -> 1 | AA16: =S16+W16 -> 0 | AB16: =L16+X16 -> 67 | AC16: =M16+Y16 -> 0 | AD16: =N16+Z16 -> 1 | AE16: =O16+AA16 -> 0 | AF16: 0 | AH16: 0 | AJ16: 0 | AL16: 0 | AN16: 0 | AP16: 0 | AR16: =AH16+AJ16+AL16+AN16+AP16 -> 0 | AS16: =AI16+AK16+AM16+AO16+AQ16 -> 0 | AT16: 0 | AV16: 0 | AX16: 0 | AZ16: 0 | BB16: 0 | BD16: 0 | BF16: 0 | BH16: 0 | BJ16: 0 | BL16: =AV16+AX16+AZ16+BB16+BD16+BF16+BH16+BJ16 -> 0 | BM16: =AW16+AY16+BA16+BC16+BE16+BG16+BI16+BK16 -> 0 | BN16: =AX16+AZ16+BB16+BD16+BF16+BH16+BJ16+BL16 -> 0 | BO16: =AY16+BA16+BC16+BE16+BG16+BI16+BK16+BM16 -> 0 | BP16: 0 | BR16: 0 | BT16: =BP16+BR16 -> 0 | BU16: =BQ16+BS16 -> 0 | BV16: 0 | BX16: 0 | BZ16: 0 | CB16: 0 | CD16: 67 | CF16: 1 | CH16: 0 | CJ16: 0 | CL16: =BV16+CD16 -> 67 | CM16: =BW16+CE16 -> 0 | CN16: =BX16+CF16 -> 1 | CO16: =BY16+CG16 -> 0 | CP16: =BZ16+CH16 -> 0 | CQ16: =CA16+CI16 -> 0 | CR16: =CB16+CJ16 -> 0 | CS16: =CC16+CK16 -> 0 | CT16: =CL16+CP16 -> 67 | CU16: =CM16+CQ16 -> 0 | CV16: =CN16+CR16 -> 1 | CW16: =CO16+CS16 -> 0
B17: 716GD | C17: R&D | D17: 0 | F17: 0 | H17: 0 | J17: 0 | L17: =D17+H17 -> 0 | M17: =E17+I17 -> 0 | N17: =F17+J17 -> 0 | O17: =G17+K17 -> 0 | P17: 2 | R17: 1 | T17: 0 | V17: 0 | X17: =P17+T17 -> 2 | Y17: =Q17+U17 -> 0 | Z17: =R17+V17 -> 1 | AA17: =S17+W17 -> 0 | AB17: =L17+X17 -> 2 | AC17: =M17+Y17 -> 0 | AD17: =N17+Z17 -> 1 | AE17: =O17+AA17 -> 0 | AF17: 0 | AH17: 0 | AJ17: 0 | AL17: 0 | AN17: 0 | AP17: 0 | AR17: =AH17+AJ17+AL17+AN17+AP17 -> 0 | AS17: =AI17+AK17+AM17+AO17+AQ17 -> 0 | AT17: 0 | AV17: 0 | AX17: 0 | AZ17: 0 | BB17: 0 | BD17: 0 | BF17: 0 | BH17: 0 | BJ17: 0 | BL17: =AV17+AX17+AZ17+BB17+BD17+BF17+BH17+BJ17 -> 0 | BM17: =AW17+AY17+BA17+BC17+BE17+BG17+BI17+BK17 -> 0 | BN17: =AX17+AZ17+BB17+BD17+BF17+BH17+BJ17+BL17 -> 0 | BO17: =AY17+BA17+BC17+BE17+BG17+BI17+BK17+BM17 -> 0 | BP17: 0 | BR17: 0 | BT17: =BP17+BR17 -> 0 | BU17: =BQ17+BS17 -> 0 | BV17: 0 | BX17: 0 | BZ17: 0 | CB17: 0 | CD17: 2 | CF17: 1 | CH17: 0 | CJ17: 0 | CL17: =BV17+CD17 -> 2 | CM17: =BW17+CE17 -> 0 | CN17: =BX17+CF17 -> 1 | CO17: =BY17+CG17 -> 0 | CP17: =BZ17+CH17 -> 0 | CQ17: =CA17+CI17 -> 0 | CR17: =CB17+CJ17 -> 0 | CS17: =CC17+CK17 -> 0 | CT17: =CL17+CP17 -> 2 | CU17: =CM17+CQ17 -> 0 | CV17: =CN17+CR17 -> 1 | CW17: =CO17+CS17 -> 0
B18: 716JD | C18: R&D | D18: 0 | F18: 0 | H18: 0 | J18: 0 | L18: =D18+H18 -> 0 | M18: =E18+I18 -> 0 | N18: =F18+J18 -> 0 | O18: =G18+K18 -> 0 | P18: 15 | R18: 1 | T18: 0 | V18: 0 | X18: =P18+T18 -> 15 | Y18: =Q18+U18 -> 0 | Z18: =R18+V18 -> 1 | AA18: =S18+W18 -> 0 | AB18: =L18+X18 -> 15 | AC18: =M18+Y18 -> 0 | AD18: =N18+Z18 -> 1 | AE18: =O18+AA18 -> 0 | AF18: 0 | AH18: 0 | AJ18: 0 | AL18: 0 | AN18: 0 | AP18: 0 | AR18: =AH18+AJ18+AL18+AN18+AP18 -> 0 | AS18: =AI18+AK18+AM18+AO18+AQ18 -> 0 | AT18: 0 | AV18: 0 | AX18: 0 | AZ18: 0 | BB18: 0 | BD18: 0 | BF18: 0 | BH18: 0 | BJ18: 0 | BL18: =AV18+AX18+AZ18+BB18+BD18+BF18+BH18+BJ18 -> 0 | BM18: =AW18+AY18+BA18+BC18+BE18+BG18+BI18+BK18 -> 0 | BN18: =AX18+AZ18+BB18+BD18+BF18+BH18+BJ18+BL18 -> 0 | BO18: =AY18+BA18+BC18+BE18+BG18+BI18+BK18+BM18 -> 0 | BP18: 0 | BR18: 0 | BT18: =BP18+BR18 -> 0 | BU18: =BQ18+BS18 -> 0 | BV18: 0 | BX18: 0 | BZ18: 0 | CB18: 0 | CD18: 15 | CF18: 1 | CH18: 0 | CJ18: 0 | CL18: =BV18+CD18 -> 15 | CM18: =BW18+CE18 -> 0 | CN18: =BX18+CF18 -> 1 | CO18: =BY18+CG18 -> 0 | CP18: =BZ18+CH18 -> 0 | CQ18: =CA18+CI18 -> 0 | CR18: =CB18+CJ18 -> 0 | CS18: =CC18+CK18 -> 0 | CT18: =CL18+CP18 -> 15 | CU18: =CM18+CQ18 -> 0 | CV18: =CN18+CR18 -> 1 | CW18: =CO18+CS18 -> 0
... B78: 8191D | C78: R&D | D78: 0 | F78: 0 | H78: 0 | J78: 0 | L78: =D78+H78 -> 0 | M78: =E78+I78 -> 0 | N78: =F78+J78 -> 0 | O78: =G78+K78 -> 0 | P78: 30 | R78: 1 | T78: 0 | V78: 0 | X78: =P78+T78 -> 30 | Y78: =Q78+U78 -> 0 | Z78: =R78+V78 -> 1 | AA78: =S78+W78 -> 0 | AB78: =L78+X78 -> 30 | AC78: =M78+Y78 -> 0 | AD78: =N78+Z78 -> 1 | AE78: =O78+AA78 -> 0 | AF78: 0 | AH78: 0 | AJ78: 0 | AL78: 0 | AN78: 0 | AP78: 0 | AR78: =AH78+AJ78+AL78+AN78+AP78 -> 0 | AS78: =AI78+AK78+AM78+AO78+AQ78 -> 0 | AT78: 0 | AV78: 0 | AX78: 0 | AZ78: 0 | BB78: 0 | BD78: 0 | BF78: 0 | BH78: 0 | BJ78: 0 | BL78: =AV78+AX78+AZ78+BB78+BD78+BF78+BH78+BJ78 -> 0 | BM78: =AW78+AY78+BA78+BC78+BE78+BG78+BI78+BK78 -> 0 | BN78: =AX78+AZ78+BB78+BD78+BF78+BH78+BJ78+BL78 -> 0 | BO78: =AY78+BA78+BC78+BE78+BG78+BI78+BK78+BM78 -> 0 | BP78: 0 | BR78: 0 | BT78: =BP78+BR78 -> 0 | BU78: =BQ78+BS78 -> 0 | BV78: 0 | BX78: 0 | BZ78: 0 | CB78: 0 | CD78: 30 | CF78: 1 | CH78: 0 | CJ78: 0 | CL78: =BV78+CD78 -> 30 | CM78: =BW78+CE78 -> 0 | CN78: =BX78+CF78 -> 1 | CO78: =BY78+CG78 -> 0 | CP78: =BZ78+CH78 -> 0 | CQ78: =CA78+CI78 -> 0 | CR78: =CB78+CJ78 -> 0 | CS78: =CC78+CK78 -> 0 | CT78: =CL78+CP78 -> 30 | CU78: =CM78+CQ78 -> 0 | CV78: =CN78+CR78 -> 1 | CW78: =CO78+CS78 -> 0
B79: TOTAL | D79: =SUM(D7:D78) -> 36254 | E79: =SUM(E7:E78) -> 0 | F79: =SUM(F7:F78) -> 20177 | G79: =SUM(G7:G78) -> 0 | H79: =SUM(H7:H78) -> 0 | I79: =SUM(I7:I78) -> 0 | J79: =SUM(J7:J78) -> 15624 | K79: =SUM(K7:K78) -> 0 | ... AH79: =SUM(AH7:AH78) -> 0 | AJ79: =SUM(AJ7:AJ78) -> 276489 | AL79: =SUM(AL7:AL78) -> 9997 | AN79: =SUM(AN7:AN78) -> 0 | AP79: =SUM(AP7:AP78) -> 0 | AR79: =SUM(AR7:AR78) -> 286486 | AS79: =SUM(AS7:AS78) -> 0 | AT79: =SUM(AT7:AT78) -> 989673 | AU79: =SUM(AU7:AU78) -> 0 | AV79: =SUM(AV7:AV78) -> 0 | AW79: =SUM(AW7:AW78) -> 0 | AZ79: =SUM(AZ7:AZ78) -> 503 | BA79: =SUM(BA7:BA78) -> 0 | BD79: =SUM(BD7:BD78) -> 363 | BE79: =SUM(BE7:BE78) -> 0 | BH79: =SUM(BH7:BH78) -> 0 | BI79: =SUM(BI7:BI78) -> 0 | BL79: =SUM(BL7:BL78) -> 892 | BM79: =SUM(BM7:BM78) -> 0 | BN79: =SUM(BN7:BN78) -> 1784 | BO79: =SUM(BO7:BO78) -> 0 | BP79: =SUM(BP7:BP78) -> 22357 | BQ79: =SUM(BQ7:BQ78) -> 0 | BV79: =SUM(BV7:BV78) -> 65190 | BW79: =SUM(BW7:BW78) -> 0 | BX79: =SUM(BX7:BX78) -> 19319 | BY79: =SUM(BY7:BY78) -> 0 | BZ79: =SUM(BZ7:BZ78) -> 0 | CA79: =SUM(CA7:CA78) -> 0 | CB79: =SUM(CB7:CB78) -> 8377 | CC79: =SUM(CC7:CC78) -> 0 | ... CW79: =SUM(CW7:CW78) -> 0

Sheet 제품(TP) (매출원가_제품)
V1: 열고 닫는 기능 추가 필요 (좌측으로) | AF1: 열고 닫는 기능 추가 필요 (좌측으로) | AL1: 열고 닫는 기능 추가 필요 (좌측으로) | AV1: 열고 닫는 기능 추가 필요 (좌측으로)
B2: 모델 Model | C2: 구분 Division | D2: BOH | F2: INPUT | X2: 기타입고 | AH2: OUTPUT | AN2: 기타출고 | AX2: LOSS | AZ2: EOH WH0006
F3: 1 | H3: 2 | J3: 3 | L3: 4 | N3: 5 | P3: 6 | R3: 7 | T3: 8 | V3: 9=1+…+8 | X3: 1 | Z3: 2 | AB3: 3 | AD3: 4 | AF3: 5=1+2+3+4 | AH3: 1 | AJ3: 2 | AL3: 3=1+2 | AN3: 1 | AP3: 2 | AR3: 3 | AT3: 4 | AV3: 6=1+2+3+4
F4: NORMAL FG INPUT | J4: RW FROM LINE → FG-WAREHOUSE / REWORK 생산라인 → 완제품 창고 CELL 입고 | V4: T_INPUT | X4: RMA | Z4: 반제품 (유상) | AB4: 반제품 (무상) | AD4: 기타 | AF4: 기타입고 | AH4: SHIP (A 급) | AJ4: SHIP (B 급) | AL4: T_OUTPUT | AN4: Re-Sorting (재검사) | AP4: Re-work (SI검사) | AR4: 무상매출 | AT4: 기타 | AV4: 기타출고
F5: LAST-MONTH | H5: THIS-MONTH | J5: BACK-SHIP (SORTING) | L5: BACK-SHIP (PF-RW) | N5: BACK-SHIP (PL-RW) | P5: WH RETURN (SORTING) | R5: WH RETURN (PF-RW) | T5: WH RETURN (PL-RW) | AH5: PAID | AJ5: PAID | BC5: 검증
D6: 수량 | E6: 금액 | F6: 수량 | G6: 금액 | H6: 수량 | I6: 금액 | J6: 수량 | K6: 금액 | L6: 수량 | M6: 금액 | N6: 수량 | O6: 금액 | P6: 수량 | Q6: 금액 | R6: 수량 | S6: 금액 | T6: 수량 | U6: 금액 | V6: 수량 | W6: 금액 | X6: 수량 | Y6: 금액 | Z6: 수량 | AA6: 금액 | AB6: 수량 | AC6: 금액 | AD6: 수량 | AE6: 금액 | AF6: 수량 | AG6: 금액 | AH6: 수량 | AI6: 금액 | AJ6: 수량 | AK6: 금액 | AL6: 수량 | AM6: 금액 | AN6: 수량 | AO6: 금액 | AP6: 수량 | AQ6: 금액 | AR6: 수량 | AS6: 금액 | AT6: 수량 | AU6: 금액 | AV6: 수량 | AW6: 금액 | AX6: 수량 | AY6: 금액 | AZ6: 수량 | BA6: 금액
B7: 7075P | C7: =VLOOKUP(B7,'재공품 (WIP)_생산실적'!$B$6:$C$88,2,FALSE) -> MP | D7: =IFERROR(VLOOKUP(B7,'(A) Inventory'!$A$7:$C$89,3,0),0) -> 10030 | E7: 122436.31 | F7: =IFERROR(VLOOKUP(B7,'(B) FGs'!$B$6:$D$55,3,0),0) -> 0 | H7: =IFERROR(VLOOKUP(B7,'(B) FGs'!$B$6:$E$55,4,0),0) -> 0 | J7: =IFERROR(VLOOKUP(B7,'(B) FGs'!$B$6:$G$55,6,0),0) -> 0 | L7: =IFERROR(VLOOKUP(B7,'(B) FGs'!$B$6:$H$55,7,0),0) -> 0 | N7: =IFERROR(VLOOKUP(B7,'(B) FGs'!$B$6:$I$55,8,0),0) -> 0 | P7: =IFERROR(VLOOKUP(B7,'(B) FGs'!$B$6:$J$55,9,0),0) -> 0 | R7: =IFERROR(VLOOKUP(B7,'(B) FGs'!$B$6:$K$55,10,0),0) -> 0 | T7: =IFERROR(VLOOKUP(B7,'(B) FGs'!$B$6:$L$55,11,0),0) -> 0 | V7: =F7+H7+J7+L7+N7+P7+R7+T7 -> 0 | W7: =G7+I7+K7+M7+O7+Q7+S7+U7 -> 0 | X7: =IFERROR(VLOOKUP(B7,'(B) FGs'!$B$6:$R$55,13,0),0) -> 0 | Z7: =IFERROR(VLOOKUP(B7,'(A) Inventory'!$A$7:$R$89,18,0),0) -> 0 | AB7: =IFERROR(VLOOKUP(B7,'(A) Inventory'!$A$7:$S$89,19,0),0) -> 0 | AD7: 0 | AF7: =X7+Z7+AB7+AD7 -> 0 | AG7: =Y7+AA7+AC7+AE7 -> 0 | AH7: =IFERROR(VLOOKUP(B7,'(A) Inventory'!$A$7:$P$89,16,0),0) -> 0 | AJ7: =IFERROR(VLOOKUP(B7,'(A) Inventory'!$A$7:$R$89,18,0),0) -> 0 | AL7: =AH7+AJ7 -> 0 | AM7: =AI7+AK7 -> 0 | AN7: =IFERROR(VLOOKUP(B7,'(B) FGs'!$B$6:$S$55,18,0),0)-IFERROR(VLOOKUP(B7,'(B) FGs'!$B$6:$M$55,12,0),0) -> 0 | AP7: =IFERROR(VLOOKUP(B7,'(B) FGs'!$B$6:$M$55,12,0),0) -> 0 | AR7: =IFERROR(VLOOKUP(B7,'(A) Inventory'!$A$7:$S$89,19,0),0) -> 0 | AT7: 0 | AV7: =AN7+AP7+AR7+AT7 -> 0 | AW7: =AO7+AQ7+AS7+AU7 -> 0 | AX7: 0 | AZ7: =D7+V7+AF7-AL7-AV7-AX7 -> 10030 | BA7: =E7+W7+AG7-AM7-AW7-AY7 -> 122436.31 | BC7: =D7+V7+AF7-AL7-AV7-AX7=AZ7 -> TRUE | BD7: =D7+V7+AF7-AL7-AV7-AX7-AZ7 -> 0
B8: 712TP | C8: =VLOOKUP(B8,'재공품 (WIP)_생산실적'!$B$6:$C$88,2,FALSE) -> MP | D8: =IFERROR(VLOOKUP(B8,'(A) Inventory'!$A$7:$C$89,3,0),0) -> 0 | E8: 0 | F8: =IFERROR(VLOOKUP(B8,'(B) FGs'!$B$6:$D$55,3,0),0) -> 0 | H8: =IFERROR(VLOOKUP(B8,'(B) FGs'!$B$6:$E$55,4,0),0) -> 0 | J8: =IFERROR(VLOOKUP(B8,'(B) FGs'!$B$6:$G$55,6,0),0) -> 0 | L8: =IFERROR(VLOOKUP(B8,'(B) FGs'!$B$6:$H$55,7,0),0) -> 0 | N8: =IFERROR(VLOOKUP(B8,'(B) FGs'!$B$6:$I$55,8,0),0) -> 0 | P8: =IFERROR(VLOOKUP(B8,'(B) FGs'!$B$6:$J$55,9,0),0) -> 0 | R8: 0 | T8: =IFERROR(VLOOKUP(B8,'(B) FGs'!$B$6:$L$55,11,0),0) -> 0 | V8: =F8+H8+J8+L8+N8+P8+R8+T8 -> 0 | W8: =G8+I8+K8+M8+O8+Q8+S8+U8 -> 0 | X8: =IFERROR(VLOOKUP(B8,'(B) FGs'!$B$6:$R$55,13,0),0) -> 0 | Z8: =IFERROR(VLOOKUP(B8,'(A) Inventory'!$A$7:$R$89,18,0),0) -> 0 | AB8: =IFERROR(VLOOKUP(B8,'(A) Inventory'!$A$7:$S$89,19,0),0) -> 0 | AD8: 0 | AF8: =X8+Z8+AB8+AD8 -> 0 | AG8: =Y8+AA8+AC8+AE8 -> 0 | AH8: =IFERROR(VLOOKUP(B8,'(A) Inventory'!$A$7:$P$89,16,0),0) -> 0 | AJ8: =IFERROR(VLOOKUP(B8,'(A) Inventory'!$A$7:$R$89,18,0),0) -> 0 | AL8: =AH8+AJ8 -> 0 | AM8: =AI8+AK8 -> 0 | AN8: =IFERROR(VLOOKUP(B8,'(B) FGs'!$B$6:$S$55,18,0),0)-IFERROR(VLOOKUP(B8,'(B) FGs'!$B$6:$M$55,12,0),0) -> 0 | AP8: =IFERROR(VLOOKUP(B8,'(B) FGs'!$B$6:$M$55,12,0),0) -> 0 | AR8: =IFERROR(VLOOKUP(B8,'(A) Inventory'!$A$7:$S$89,19,0),0) -> 0 | AT8: 0 | AV8: =AN8+AP8+AR8+AT8 -> 0 | AW8: =AO8+AQ8+AS8+AU8 -> 0 | AX8: 0 | AZ8: =D8+V8+AF8-AL8-AV8-AX8 -> 0 | BA8: =E8+W8+AG8-AM8-AW8-AY8 -> 0 | BC8: =D8+V8+AF8-AL8-AV8-AX8=AZ8 -> TRUE | BD8: =D8+V8+AF8-AL8-AV8-AX8-AZ8 -> 0
B9: 716AP | C9: =VLOOKUP(B9,'재공품 (WIP)_생산실적'!$B$6:$C$88,2,FALSE) -> MP | D9: =IFERROR(VLOOKUP(B9,'(A) Inventory'!$A$7:$C$89,3,0),0) -> 387259 | E9: 4200575.1 | F9: =IFERROR(VLOOKUP(B9,'(B) FGs'!$B$6:$D$55,3,0),0) -> 39672 | H9: =IFERROR(VLOOKUP(B9,'(B) FGs'!$B$6:$E$55,4,0),0) -> 441648 | J9: =IFERROR(VLOOKUP(B9,'(B) FGs'!$B$6:$G$55,6,0),0) -> 23934 | L9: =IFERROR(VLOOKUP(B9,'(B) FGs'!$B$6:$H$55,7,0),0) -> 0 | N9: =IFERROR(VLOOKUP(B9,'(B) FGs'!$B$6:$I$55,8,0),0) -> 0 | P9: =IFERROR(VLOOKUP(B9,'(B) FGs'!$B$6:$J$55,9,0),0) -> 242656 | R9: 9765 | T9: =IFERROR(VLOOKUP(B9,'(B) FGs'!$B$6:$L$55,11,0),0) -> 0 | V9: =F9+H9+J9+L9+N9+P9+R9+T9 -> 757675 | W9: =G9+I9+K9+M9+O9+Q9+S9+U9 -> 0 | X9: =IFERROR(VLOOKUP(B9,'(B) FGs'!$B$6:$R$55,13,0),0) -> 0 | Z9: =IFERROR(VLOOKUP(B9,'(A) Inventory'!$A$7:$R$89,18,0),0) -> 10 | AB9: =IFERROR(VLOOKUP(B9,'(A) Inventory'!$A$7:$S$89,19,0),0) -> 5 | AD9: 0 | AF9: =X9+Z9+AB9+AD9 -> 15 | AG9: =Y9+AA9+AC9+AE9 -> 0 | AH9: =IFERROR(VLOOKUP(B9,'(A) Inventory'!$A$7:$P$89,16,0),0) -> 594080 | AJ9: =IFERROR(VLOOKUP(B9,'(A) Inventory'!$A$7:$R$89,18,0),0) -> 10 | AL9: =AH9+AJ9 -> 594090 | AM9: =AI9+AK9 -> 0 | AN9: =IFERROR(VLOOKUP(B9,'(B) FGs'!$B$6:$S$55,18,0),0)-IFERROR(VLOOKUP(B9,'(B) FGs'!$B$6:$M$55,12,0),0) -> 260558 | AP9: =IFERROR(VLOOKUP(B9,'(B) FGs'!$B$6:$M$55,12,0),0) -> 9765 | AR9: =IFERROR(VLOOKUP(B9,'(A) Inventory'!$A$7:$S$89,19,0),0) -> 5 | AT9: 0 | AV9: =AN9+AP9+AR9+AT9 -> 270328 | AW9: =AO9+AQ9+AS9+AU9 -> 0 | AX9: 0 | AZ9: =D9+V9+AF9-AL9-AV9-AX9 -> 280531 | BA9: =E9+W9+AG9-AM9-AW9-AY9 -> 4200575.1 | BC9: =D9+V9+AF9-AL9-AV9-AX9=AZ9 -> TRUE | BD9: =D9+V9+AF9-AL9-AV9-AX9-AZ9 -> 0
B10: 716BD | C10: =VLOOKUP(B10,'재공품 (WIP)_생산실적'!$B$6:$C$88,2,FALSE) -> R&D | D10: =IFERROR(VLOOKUP(B10,'(A) Inventory'!$A$7:$C$89,3,0),0) -> 987 | E10: 21037.24 | F10: =IFERROR(VLOOKUP(B10,'(B) FGs'!$B$6:$D$55,3,0),0) -> 0 | H10: =IFERROR(VLOOKUP(B10,'(B) FGs'!$B$6:$E$55,4,0),0) -> 0 | J10: =IFERROR(VLOOKUP(B10,'(B) FGs'!$B$6:$G$55,6,0),0) -> 0 | L10: =IFERROR(VLOOKUP(B10,'(B) FGs'!$B$6:$H$55,7,0),0) -> 0 | N10: =IFERROR(VLOOKUP(B10,'(B) FGs'!$B$6:$I$55,8,0),0) -> 0 | P10: =IFERROR(VLOOKUP(B10,'(B) FGs'!$B$6:$J$55,9,0),0) -> 0 | R10: 0 | T10: =IFERROR(VLOOKUP(B10,'(B) FGs'!$B$6:$L$55,11,0),0) -> 0 | V10: =F10+H10+J10+L10+N10+P10+R10+T10 -> 0 | W10: =G10+I10+K10+M10+O10+Q10+S10+U10 -> 0 | X10: =IFERROR(VLOOKUP(B10,'(B) FGs'!$B$6:$R$55,13,0),0) -> 0 | Z10: =IFERROR(VLOOKUP(B10,'(A) Inventory'!$A$7:$R$89,18,0),0) -> 0 | AB10: =IFERROR(VLOOKUP(B10,'(A) Inventory'!$A$7:$S$89,19,0),0) -> 0 | AD10: 0 | AF10: =X10+Z10+AB10+AD10 -> 0 | AG10: =Y10+AA10+AC10+AE10 -> 0 | AH10: =IFERROR(VLOOKUP(B10,'(A) Inventory'!$A$7:$P$89,16,0),0) -> 0 | AJ10: =IFERROR(VLOOKUP(B10,'(A) Inventory'!$A$7:$R$89,18,0),0) -> 0 | AL10: =AH10+AJ10 -> 0 | AM10: =AI10+AK10 -> 0 | AN10: =IFERROR(VLOOKUP(B10,'(B) FGs'!$B$6:$S$55,18,0),0)-IFERROR(VLOOKUP(B10,'(B) FGs'!$B$6:$M$55,12,0),0) -> 0 | AP10: =IFERROR(VLOOKUP(B10,'(B) FGs'!$B$6:$M$55,12,0),0) -> 0 | AR10: =IFERROR(VLOOKUP(B10,'(A) Inventory'!$A$7:$S$89,19,0),0) -> 0 | AT10: 0 | AV10: =AN10+AP10+AR10+AT10 -> 0 | AW10: =AO10+AQ10+AS10+AU10 -> 0 | AX10: 0 | AZ10: =D10+V10+AF10-AL10-AV10-AX10 -> 987 | BA10: =E10+W10+AG10-AM10-AW10-AY10 -> 21037.24 | BC10: =D10+V10+AF10-AL10-AV10-AX10=AZ10 -> TRUE | BD10: =D10+V10+AF10-AL10-AV10-AX10-AZ10 -> 0
B11: 716CD | C11: =VLOOKUP(B11,'재공품 (WIP)_생산실적'!$B$6:$C$88,2,FALSE) -> R&D | D11: =IFERROR(VLOOKUP(B11,'(A) Inventory'!$A$7:$C$89,3,0),0) -> 38 | E11: 750.22 | F11: =IFERROR(VLOOKUP(B11,'(B) FGs'!$B$6:$D$55,3,0),0) -> 0 | H11: =IFERROR(VLOOKUP(B11,'(B) FGs'!$B$6:$E$55,4,0),0) -> 0 | J11: =IFERROR(VLOOKUP(B11,'(B) FGs'!$B$6:$G$55,6,0),0) -> 0 | L11: =IFERROR(VLOOKUP(B11,'(B) FGs'!$B$6:$H$55,7,0),0) -> 0 | N11: =IFERROR(VLOOKUP(B11,'(B) FGs'!$B$6:$I$55,8,0),0) -> 0 | P11: =IFERROR(VLOOKUP(B11,'(B) FGs'!$B$6:$J$55,9,0),0) -> 0 | R11: 0 | T11: =IFERROR(VLOOKUP(B11,'(B) FGs'!$B$6:$L$55,11,0),0) -> 0 | V11: =F11+H11+J11+L11+N11+P11+R11+T11 -> 0 | W11: =G11+I11+K11+M11+O11+Q11+S11+U11 -> 0 | X11: =IFERROR(VLOOKUP(B11,'(B) FGs'!$B$6:$R$55,13,0),0) -> 0 | Z11: =IFERROR(VLOOKUP(B11,'(A) Inventory'!$A$7:$R$89,18,0),0) -> 0 | AB11: =IFERROR(VLOOKUP(B11,'(A) Inventory'!$A$7:$S$89,19,0),0) -> 0 | AD11: 0 | AF11: =X11+Z11+AB11+AD11 -> 0 | AG11: =Y11+AA11+AC11+AE11 -> 0 | AH11: =IFERROR(VLOOKUP(B11,'(A) Inventory'!$A$7:$P$89,16,0),0) -> 0 | AJ11: =IFERROR(VLOOKUP(B11,'(A) Inventory'!$A$7:$R$89,18,0),0) -> 0 | AL11: =AH11+AJ11 -> 0 | AM11: =AI11+AK11 -> 0 | AN11: =IFERROR(VLOOKUP(B11,'(B) FGs'!$B$6:$S$55,18,0),0)-IFERROR(VLOOKUP(B11,'(B) FGs'!$B$6:$M$55,12,0),0) -> 0 | AP11: =IFERROR(VLOOKUP(B11,'(B) FGs'!$B$6:$M$55,12,0),0) -> 0 | AR11: =IFERROR(VLOOKUP(B11,'(A) Inventory'!$A$7:$S$89,19,0),0) -> 0 | AT11: 0 | AV11: =AN11+AP11+AR11+AT11 -> 0 | AW11: =AO11+AQ11+AS11+AU11 -> 0 | AX11: 0 | AZ11: =D11+V11+AF11-AL11-AV11-AX11 -> 38 | BA11: =E11+W11+AG11-AM11-AW11-AY11 -> 750.22 | BC11: =D11+V11+AF11-AL11-AV11-AX11=AZ11 -> TRUE | BD11: =D11+V11+AF11-AL11-AV11-AX11-AZ11 -> 0
B12: 716DD | C12: =VLOOKUP(B12,'재공품 (WIP)_생산실적'!$B$6:$C$88,2,FALSE) -> R&D | D12: =IFERROR(VLOOKUP(B12,'(A) Inventory'!$A$7:$C$89,3,0),0) -> 14976 | E12: 217019.46 | F12: =IFERROR(VLOOKUP(B12,'(B) FGs'!$B$6:$D$55,3,0),0) -> 0 | H12: =IFERROR(VLOOKUP(B12,'(B) FGs'!$B$6:$E$55,4,0),0) -> 0 | J12: =IFERROR(VLOOKUP(B12,'(B) FGs'!$B$6:$G$55,6,0),0) -> 0 | L12: =IFERROR(VLOOKUP(B12,'(B) FGs'!$B$6:$H$55,7,0),0) -> 0 | N12: =IFERROR(VLOOKUP(B12,'(B) FGs'!$B$6:$I$55,8,0),0) -> 0 | P12: =IFERROR(VLOOKUP(B12,'(B) FGs'!$B$6:$J$55,9,0),0) -> 0 | R12: 0 | T12: =IFERROR(VLOOKUP(B12,'(B) FGs'!$B$6:$L$55,11,0),0) -> 0 | V12: =F12+H12+J12+L12+N12+P12+R12+T12 -> 0 | W12: =G12+I12+K12+M12+O12+Q12+S12+U12 -> 0 | X12: =IFERROR(VLOOKUP(B12,'(B) FGs'!$B$6:$R$55,13,0),0) -> 0 | Z12: =IFERROR(VLOOKUP(B12,'(A) Inventory'!$A$7:$R$89,18,0),0) -> 0 | AB12: =IFERROR(VLOOKUP(B12,'(A) Inventory'!$A$7:$S$89,19,0),0) -> 0 | AD12: 0 | AF12: =X12+Z12+AB12+AD12 -> 0 | AG12: =Y12+AA12+AC12+AE12 -> 0 | AH12: =IFERROR(VLOOKUP(B12,'(A) Inventory'!$A$7:$P$89,16,0),0) -> 0 | AJ12: =IFERROR(VLOOKUP(B12,'(A) Inventory'!$A$7:$R$89,18,0),0) -> 0 | AL12: =AH12+AJ12 -> 0 | AM12: =AI12+AK12 -> 0 | AN12: =IFERROR(VLOOKUP(B12,'(B) FGs'!$B$6:$S$55,18,0),0)-IFERROR(VLOOKUP(B12,'(B) FGs'!$B$6:$M$55,12,0),0) -> 0 | AP12: =IFERROR(VLOOKUP(B12,'(B) FGs'!$B$6:$M$55,12,0),0) -> 0 | AR12: =IFERROR(VLOOKUP(B12,'(A) Inventory'!$A$7:$S$89,19,0),0) -> 0 | AT12: 0 | AV12: =AN12+AP12+AR12+AT12 -> 0 | AW12: =AO12+AQ12+AS12+AU12 -> 0 | AX12: 0 | AZ12: =D12+V12+AF12-AL12-AV12-AX12 -> 14976 | BA12: =E12+W12+AG12-AM12-AW12-AY12 -> 217019.46 | BC12: =D12+V12+AF12-AL12-AV12-AX12=AZ12 -> TRUE | BD12: =D12+V12+AF12-AL12-AV12-AX12-AZ12 -> 0
B13: 716DTT | C13: =VLOOKUP(B13,'재공품 (WIP)_생산실적'!$B$6:$C$88,2,FALSE) -> R&D | D13: =IFERROR(VLOOKUP(B13,'(A) Inventory'!$A$7:$C$89,3,0),0) -> 0 | E13: 0 | F13: =IFERROR(VLOOKUP(B13,'(B) FGs'!$B$6:$D$55,3,0),0) -> 0 | H13: =IFERROR(VLOOKUP(B13,'(B) FGs'!$B$6:$E$55,4,0),0) -> 0 | J13: =IFERROR(VLOOKUP(B13,'(B) FGs'!$B$6:$G$55,6,0),0) -> 0 | L13: =IFERROR(VLOOKUP(B13,'(B) FGs'!$B$6:$H$55,7,0),0) -> 0 | N13: =IFERROR(VLOOKUP(B13,'(B) FGs'!$B$6:$I$55,8,0),0) -> 0 | P13: =IFERROR(VLOOKUP(B13,'(B) FGs'!$B$6:$J$55,9,0),0) -> 0 | R13: 0 | T13: =IFERROR(VLOOKUP(B13,'(B) FGs'!$B$6:$L$55,11,0),0) -> 0 | V13: =F13+H13+J13+L13+N13+P13+R13+T13 -> 0 | W13: =G13+I13+K13+M13+O13+Q13+S13+U13 -> 0 | X13: =IFERROR(VLOOKUP(B13,'(B) FGs'!$B$6:$R$55,13,0),0) -> 0 | Z13: =IFERROR(VLOOKUP(B13,'(A) Inventory'!$A$7:$R$89,18,0),0) -> 0 | AB13: =IFERROR(VLOOKUP(B13,'(A) Inventory'!$A$7:$S$89,19,0),0) -> 300 | AD13: 0 | AF13: =X13+Z13+AB13+AD13 -> 300 | AG13: =Y13+AA13+AC13+AE13 -> 0 | AH13: =IFERROR(VLOOKUP(B13,'(A) Inventory'!$A$7:$P$89,16,0),0) -> 0 | AJ13: =IFERROR(VLOOKUP(B13,'(A) Inventory'!$A$7:$R$89,18,0),0) -> 0 | AL13: =AH13+AJ13 -> 0 | AM13: =AI13+AK13 -> 0 | AN13: =IFERROR(VLOOKUP(B13,'(B) FGs'!$B$6:$S$55,18,0),0)-IFERROR(VLOOKUP(B13,'(B) FGs'!$B$6:$M$55,12,0),0) -> 0 | AP13: =IFERROR(VLOOKUP(B13,'(B) FGs'!$B$6:$M$55,12,0),0) -> 0 | AR13: =IFERROR(VLOOKUP(B13,'(A) Inventory'!$A$7:$S$89,19,0),0) -> 300 | AT13: 0 | AV13: =AN13+AP13+AR13+AT13 -> 300 | AW13: =AO13+AQ13+AS13+AU13 -> 0 | AX13: 0 | AZ13: =D13+V13+AF13-AL13-AV13-AX13 -> 0 | BA13: =E13+W13+AG13-AM13-AW13-AY13 -> 0 | BC13: =D13+V13+AF13-AL13-AV13-AX13=AZ13 -> TRUE | BD13: =D13+V13+AF13-AL13-AV13-AX13-AZ13 -> 0
B14: 716ED | C14: =VLOOKUP(B14,'재공품 (WIP)_생산실적'!$B$6:$C$88,2,FALSE) -> R&D | D14: =IFERROR(VLOOKUP(B14,'(A) Inventory'!$A$7:$C$89,3,0),0) -> 0 | E14: 0 | F14: =IFERROR(VLOOKUP(B14,'(B) FGs'!$B$6:$D$55,3,0),0) -> 0 | H14: =IFERROR(VLOOKUP(B14,'(B) FGs'!$B$6:$E$55,4,0),0) -> 0 | J14: =IFERROR(VLOOKUP(B14,'(B) FGs'!$B$6:$G$55,6,0),0) -> 0 | L14: =IFERROR(VLOOKUP(B14,'(B) FGs'!$B$6:$H$55,7,0),0) -> 0 | N14: =IFERROR(VLOOKUP(B14,'(B) FGs'!$B$6:$I$55,8,0),0) -> 0 | P14: =IFERROR(VLOOKUP(B14,'(B) FGs'!$B$6:$J$55,9,0),0) -> 0 | R14: 0 | T14: =IFERROR(VLOOKUP(B14,'(B) FGs'!$B$6:$L$55,11,0),0) -> 0 | V14: =F14+H14+J14+L14+N14+P14+R14+T14 -> 0 | W14: =G14+I14+K14+M14+O14+Q14+S14+U14 -> 0 | X14: =IFERROR(VLOOKUP(B14,'(B) FGs'!$B$6:$R$55,13,0),0) -> 0 | Z14: =IFERROR(VLOOKUP(B14,'(A) Inventory'!$A$7:$R$89,18,0),0) -> 0 | AB14: =IFERROR(VLOOKUP(B14,'(A) Inventory'!$A$7:$S$89,19,0),0) -> 0 | AD14: 0 | AF14: =X14+Z14+AB14+AD14 -> 0 | AG14: =Y14+AA14+AC14+AE14 -> 0 | AH14: =IFERROR(VLOOKUP(B14,'(A) Inventory'!$A$7:$P$89,16,0),0) -> 0 | AJ14: =IFERROR(VLOOKUP(B14,'(A) Inventory'!$A$7:$R$89,18,0),0) -> 0 | AL14: =AH14+AJ14 -> 0 | AM14: =AI14+AK14 -> 0 | AN14: =IFERROR(VLOOKUP(B14,'(B) FGs'!$B$6:$S$55,18,0),0)-IFERROR(VLOOKUP(B14,'(B) FGs'!$B$6:$M$55,12,0),0) -> 0 | AP14: =IFERROR(VLOOKUP(B14,'(B) FGs'!$B$6:$M$55,12,0),0) -> 0 | AR14: =IFERROR(VLOOKUP(B14,'(A) Inventory'!$A$7:$S$89,19,0),0) -> 0 | AT14: 0 | AV14: =AN14+AP14+AR14+AT14 -> 0 | AW14: =AO14+AQ14+AS14+AU14 -> 0 | AX14: 0 | AZ14: =D14+V14+AF14-AL14-AV14-AX14 -> 0 | BA14: =E14+W14+AG14-AM14-AW14-AY14 -> 0 | BC14: =D14+V14+AF14-AL14-AV14-AX14=AZ14 -> TRUE | BD14: =D14+V14+AF14-AL14-AV14-AX14-AZ14 -> 0
B15: 716ETT | C15: =VLOOKUP(B15,'재공품 (WIP)_생산실적'!$B$6:$C$88,2,FALSE) -> R&D | D15: =IFERROR(VLOOKUP(B15,'(A) Inventory'!$A$7:$C$89,3,0),0) -> 0 | E15: 0 | F15: =IFERROR(VLOOKUP(B15,'(B) FGs'!$B$6:$D$55,3,0),0) -> 0 | H15: =IFERROR(VLOOKUP(B15,'(B) FGs'!$B$6:$E$55,4,0),0) -> 0 | J15: =IFERROR(VLOOKUP(B15,'(B) FGs'!$B$6:$G$55,6,0),0) -> 0 | L15: =IFERROR(VLOOKUP(B15,'(B) FGs'!$B$6:$H$55,7,0),0) -> 0 | N15: =IFERROR(VLOOKUP(B15,'(B) FGs'!$B$6:$I$55,8,0),0) -> 0 | P15: =IFERROR(VLOOKUP(B15,'(B) FGs'!$B$6:$J$55,9,0),0) -> 0 | R15: 0 | T15: =IFERROR(VLOOKUP(B15,'(B) FGs'!$B$6:$L$55,11,0),0) -> 0 | V15: =F15+H15+J15+L15+N15+P15+R15+T15 -> 0 | W15: =G15+I15+K15+M15+O15+Q15+S15+U15 -> 0 | X15: =IFERROR(VLOOKUP(B15,'(B) FGs'!$B$6:$R$55,13,0),0) -> 0 | Z15: =IFERROR(VLOOKUP(B15,'(A) Inventory'!$A$7:$R$89,18,0),0) -> 350 | AB15: =IFERROR(VLOOKUP(B15,'(A) Inventory'!$A$7:$S$89,19,0),0) -> 0 | AD15: 0 | AF15: =X15+Z15+AB15+AD15 -> 350 | AG15: =Y15+AA15+AC15+AE15 -> 0 | AH15: =IFERROR(VLOOKUP(B15,'(A) Inventory'!$A$7:$P$89,16,0),0) -> 0 | AJ15: =IFERROR(VLOOKUP(B15,'(A) Inventory'!$A$7:$R$89,18,0),0) -> 350 | AL15: =AH15+AJ15 -> 350 | AM15: =AI15+AK15 -> 0 | AN15: =IFERROR(VLOOKUP(B15,'(B) FGs'!$B$6:$S$55,18,0),0)-IFERROR(VLOOKUP(B15,'(B) FGs'!$B$6:$M$55,12,0),0) -> 0 | AP15: =IFERROR(VLOOKUP(B15,'(B) FGs'!$B$6:$M$55,12,0),0) -> 0 | AR15: =IFERROR(VLOOKUP(B15,'(A) Inventory'!$A$7:$S$89,19,0),0) -> 0 | AT15: 0 | AV15: =AN15+AP15+AR15+AT15 -> 0 | AW15: =AO15+AQ15+AS15+AU15 -> 0 | AX15: 0 | AZ15: =D15+V15+AF15-AL15-AV15-AX15 -> 0 | BA15: =E15+W15+AG15-AM15-AW15-AY15 -> 0 | BC15: =D15+V15+AF15-AL15-AV15-AX15=AZ15 -> TRUE | BD15: =D15+V15+AF15-AL15-AV15-AX15-AZ15 -> 0
B16: 716FD | C16: =VLOOKUP(B16,'재공품 (WIP)_생산실적'!$B$6:$C$88,2,FALSE) -> R&D | D16: =IFERROR(VLOOKUP(B16,'(A) Inventory'!$A$7:$C$89,3,0),0) -> 0 | E16: 0 | F16: =IFERROR(VLOOKUP(B16,'(B) FGs'!$B$6:$D$55,3,0),0) -> 0 | H16: =IFERROR(VLOOKUP(B16,'(B) FGs'!$B$6:$E$55,4,0),0) -> 0 | J16: =IFERROR(VLOOKUP(B16,'(B) FGs'!$B$6:$G$55,6,0),0) -> 0 | L16: =IFERROR(VLOOKUP(B16,'(B) FGs'!$B$6:$H$55,7,0),0) -> 0 | N16: =IFERROR(VLOOKUP(B16,'(B) FGs'!$B$6:$I$55,8,0),0) -> 0 | P16: =IFERROR(VLOOKUP(B16,'(B) FGs'!$B$6:$J$55,9,0),0) -> 0 | R16: 0 | T16: =IFERROR(VLOOKUP(B16,'(B) FGs'!$B$6:$L$55,11,0),0) -> 0 | V16: =F16+H16+J16+L16+N16+P16+R16+T16 -> 0 | W16: =G16+I16+K16+M16+O16+Q16+S16+U16 -> 0 | X16: =IFERROR(VLOOKUP(B16,'(B) FGs'!$B$6:$R$55,13,0),0) -> 0 | Z16: =IFERROR(VLOOKUP(B16,'(A) Inventory'!$A$7:$R$89,18,0),0) -> 0 | AB16: =IFERROR(VLOOKUP(B16,'(A) Inventory'!$A$7:$S$89,19,0),0) -> 0 | AD16: 0 | AF16: =X16+Z16+AB16+AD16 -> 0 | AG16: =Y16+AA16+AC16+AE16 -> 0 | AH16: =IFERROR(VLOOKUP(B16,'(A) Inventory'!$A$7:$P$89,16,0),0) -> 0 | AJ16: =IFERROR(VLOOKUP(B16,'(A) Inventory'!$A$7:$R$89,18,0),0) -> 0 | AL16: =AH16+AJ16 -> 0 | AM16: =AI16+AK16 -> 0 | AN16: =IFERROR(VLOOKUP(B16,'(B) FGs'!$B$6:$S$55,18,0),0)-IFERROR(VLOOKUP(B16,'(B) FGs'!$B$6:$M$55,12,0),0) -> 0 | AP16: =IFERROR(VLOOKUP(B16,'(B) FGs'!$B$6:$M$55,12,0),0) -> 0 | AR16: =IFERROR(VLOOKUP(B16,'(A) Inventory'!$A$7:$S$89,19,0),0) -> 0 | AT16: 0 | AV16: =AN16+AP16+AR16+AT16 -> 0 | AW16: =AO16+AQ16+AS16+AU16 -> 0 | AX16: 0 | AZ16: =D16+V16+AF16-AL16-AV16-AX16 -> 0 | BA16: =E16+W16+AG16-AM16-AW16-AY16 -> 0 | BC16: =D16+V16+AF16-AL16-AV16-AX16=AZ16 -> TRUE | BD16: =D16+V16+AF16-AL16-AV16-AX16-AZ16 -> 0
B17: 716GD | C17: =VLOOKUP(B17,'재공품 (WIP)_생산실적'!$B$6:$C$88,2,FALSE) -> R&D | D17: =IFERROR(VLOOKUP(B17,'(A) Inventory'!$A$7:$C$89,3,0),0) -> 0 | E17: 0 | F17: =IFERROR(VLOOKUP(B17,'(B) FGs'!$B$6:$D$55,3,0),0) -> 0 | H17: =IFERROR(VLOOKUP(B17,'(B) FGs'!$B$6:$E$55,4,0),0) -> 0 | J17: =IFERROR(VLOOKUP(B17,'(B) FGs'!$B$6:$G$55,6,0),0) -> 0 | L17: =IFERROR(VLOOKUP(B17,'(B) FGs'!$B$6:$H$55,7,0),0) -> 0 | N17: =IFERROR(VLOOKUP(B17,'(B) FGs'!$B$6:$I$55,8,0),0) -> 0 | P17: =IFERROR(VLOOKUP(B17,'(B) FGs'!$B$6:$J$55,9,0),0) -> 0 | R17: 0 | T17: =IFERROR(VLOOKUP(B17,'(B) FGs'!$B$6:$L$55,11,0),0) -> 0 | V17: =F17+H17+J17+L17+N17+P17+R17+T17 -> 0 | W17: =G17+I17+K17+M17+O17+Q17+S17+U17 -> 0 | X17: =IFERROR(VLOOKUP(B17,'(B) FGs'!$B$6:$R$55,13,0),0) -> 0 | Z17: =IFERROR(VLOOKUP(B17,'(A) Inventory'!$A$7:$R$89,18,0),0) -> 0 | AB17: =IFERROR(VLOOKUP(B17,'(A) Inventory'!$A$7:$S$89,19,0),0) -> 0 | AD17: 0 | AF17: =X17+Z17+AB17+AD17 -> 0 | AG17: =Y17+AA17+AC17+AE17 -> 0 | AH17: =IFERROR(VLOOKUP(B17,'(A) Inventory'!$A$7:$P$89,16,0),0) -> 0 | AJ17: =IFERROR(VLOOKUP(B17,'(A) Inventory'!$A$7:$R$89,18,0),0) -> 0 | AL17: =AH17+AJ17 -> 0 | AM17: =AI17+AK17 -> 0 | AN17: =IFERROR(VLOOKUP(B17,'(B) FGs'!$B$6:$S$55,18,0),0)-IFERROR(VLOOKUP(B17,'(B) FGs'!$B$6:$M$55,12,0),0) -> 0 | AP17: =IFERROR(VLOOKUP(B17,'(B) FGs'!$B$6:$M$55,12,0),0) -> 0 | AR17: =IFERROR(VLOOKUP(B17,'(A) Inventory'!$A$7:$S$89,19,0),0) -> 0 | AT17: 0 | AV17: =AN17+AP17+AR17+AT17 -> 0 | AW17: =AO17+AQ17+AS17+AU17 -> 0 | AX17: 0 | AZ17: =D17+V17+AF17-AL17-AV17-AX17 -> 0 | BA17: =E17+W17+AG17-AM17-AW17-AY17 -> 0 | BC17: =D17+V17+AF17-AL17-AV17-AX17=AZ17 -> TRUE | BD17: =D17+V17+AF17-AL17-AV17-AX17-AZ17 -> 0
B18: 716JD | C18: =VLOOKUP(B18,'재공품 (WIP)_생산실적'!$B$6:$C$88,2,FALSE) -> R&D | D18: =IFERROR(VLOOKUP(B18,'(A) Inventory'!$A$7:$C$89,3,0),0) -> 3773 | E18: 77411.06 | F18: =IFERROR(VLOOKUP(B18,'(B) FGs'!$B$6:$D$55,3,0),0) -> 0 | H18: =IFERROR(VLOOKUP(B18,'(B) FGs'!$B$6:$E$55,4,0),0) -> 0 | J18: =IFERROR(VLOOKUP(B18,'(B) FGs'!$B$6:$G$55,6,0),0) -> 0 | L18: =IFERROR(VLOOKUP(B18,'(B) FGs'!$B$6:$H$55,7,0),0) -> 0 | N18: =IFERROR(VLOOKUP(B18,'(B) FGs'!$B$6:$I$55,8,0),0) -> 0 | P18: =IFERROR(VLOOKUP(B18,'(B) FGs'!$B$6:$J$55,9,0),0) -> 0 | R18: 0 | T18: =IFERROR(VLOOKUP(B18,'(B) FGs'!$B$6:$L$55,11,0),0) -> 0 | V18: =F18+H18+J18+L18+N18+P18+R18+T18 -> 0 | W18: =G18+I18+K18+M18+O18+Q18+S18+U18 -> 0 | X18: =IFERROR(VLOOKUP(B18,'(B) FGs'!$B$6:$R$55,13,0),0) -> 0 | Z18: =IFERROR(VLOOKUP(B18,'(A) Inventory'!$A$7:$R$89,18,0),0) -> 0 | AB18: =IFERROR(VLOOKUP(B18,'(A) Inventory'!$A$7:$S$89,19,0),0) -> 0 | AD18: 0 | AF18: =X18+Z18+AB18+AD18 -> 0 | AG18: =Y18+AA18+AC18+AE18 -> 0 | AH18: =IFERROR(VLOOKUP(B18,'(A) Inventory'!$A$7:$P$89,16,0),0) -> 0 | AJ18: =IFERROR(VLOOKUP(B18,'(A) Inventory'!$A$7:$R$89,18,0),0) -> 0 | AL18: =AH18+AJ18 -> 0 | AM18: =AI18+AK18 -> 0 | AN18: =IFERROR(VLOOKUP(B18,'(B) FGs'!$B$6:$S$55,18,0),0)-IFERROR(VLOOKUP(B18,'(B) FGs'!$B$6:$M$55,12,0),0) -> 0 | AP18: =IFERROR(VLOOKUP(B18,'(B) FGs'!$B$6:$M$55,12,0),0) -> 0 | AR18: =IFERROR(VLOOKUP(B18,'(A) Inventory'!$A$7:$S$89,19,0),0) -> 0 | AT18: 0 | AV18: =AN18+AP18+AR18+AT18 -> 0 | AW18: =AO18+AQ18+AS18+AU18 -> 0 | AX18: 0 | AZ18: =D18+V18+AF18-AL18-AV18-AX18 -> 3773 | BA18: =E18+W18+AG18-AM18-AW18-AY18 -> 77411.06 | BC18: =D18+V18+AF18-AL18-AV18-AX18=AZ18 -> TRUE | BD18: =D18+V18+AF18-AL18-AV18-AX18-AZ18 -> 0
B19: 716KD | C19: =VLOOKUP(B19,'재공품 (WIP)_생산실적'!$B$6:$C$88,2,FALSE) -> R&D | D19: =IFERROR(VLOOKUP(B19,'(A) Inventory'!$A$7:$C$89,3,0),0) -> 1943 | E19: 51949.23 | F19: =IFERROR(VLOOKUP(B19,'(B) FGs'!$B$6:$D$55,3,0),0) -> 393 | H19: =IFERROR(VLOOKUP(B19,'(B) FGs'!$B$6:$E$55,4,0),0) -> 0 | J19: =IFERROR(VLOOKUP(B19,'(B) FGs'!$B$6:$G$55,6,0),0) -> 0 | L19: =IFERROR(VLOOKUP(B19,'(B) FGs'!$B$6:$H$55,7,0),0) -> 0 | N19: =IFERROR(VLOOKUP(B19,'(B) FGs'!$B$6:$I$55,8,0),0) -> 0 | P19: =IFERROR(VLOOKUP(B19,'(B) FGs'!$B$6:$J$55,9,0),0) -> 0 | R19: 0 | T19: =IFERROR(VLOOKUP(B19,'(B) FGs'!$B$6:$L$55,11,0),0) -> 0 | V19: =F19+H19+J19+L19+N19+P19+R19+T19 -> 393 | W19: =G19+I19+K19+M19+O19+Q19+S19+U19 -> 0 | X19: =IFERROR(VLOOKUP(B19,'(B) FGs'!$B$6:$R$55,13,0),0) -> 0 | Z19: =IFERROR(VLOOKUP(B19,'(A) Inventory'!$A$7:$R$89,18,0),0) -> 0 | AB19: =IFERROR(VLOOKUP(B19,'(A) Inventory'!$A$7:$S$89,19,0),0) -> 0 | AD19: 0 | AF19: =X19+Z19+AB19+AD19 -> 0 | AG19: =Y19+AA19+AC19+AE19 -> 0 | AH19: =IFERROR(VLOOKUP(B19,'(A) Inventory'!$A$7:$P$89,16,0),0) -> 0 | AJ19: =IFERROR(VLOOKUP(B19,'(A) Inventory'!$A$7:$R$89,18,0),0) -> 0 | AL19: =AH19+AJ19 -> 0 | AM19: =AI19+AK19 -> 0 | AN19: =IFERROR(VLOOKUP(B19,'(B) FGs'!$B$6:$S$55,18,0),0)-IFERROR(VLOOKUP(B19,'(B) FGs'!$B$6:$M$55,12,0),0) -> 0 | AP19: =IFERROR(VLOOKUP(B19,'(B) FGs'!$B$6:$M$55,12,0),0) -> 0 | AR19: =IFERROR(VLOOKUP(B19,'(A) Inventory'!$A$7:$S$89,19,0),0) -> 0 | AT19: 0 | AV19: =AN19+AP19+AR19+AT19 -> 0 | AW19: =AO19+AQ19+AS19+AU19 -> 0 | AX19: 0 | AZ19: =D19+V19+AF19-AL19-AV19-AX19 -> 2336 | BA19: =E19+W19+AG19-AM19-AW19-AY19 -> 51949.23 | BC19: =D19+V19+AF19-AL19-AV19-AX19=AZ19 -> TRUE | BD19: =D19+V19+AF19-AL19-AV19-AX19-AZ19 -> 0
... B89: 8191D | C89: =VLOOKUP(B89,'재공품 (WIP)_생산실적'!$B$6:$C$88,2,FALSE) -> R&D | D89: =IFERROR(VLOOKUP(B89,'(A) Inventory'!$A$7:$C$89,3,0),0) -> 120 | E89: 2438.58 | F89: =IFERROR(VLOOKUP(B89,'(B) FGs'!$B$6:$D$55,3,0),0) -> 0 | H89: =IFERROR(VLOOKUP(B89,'(B) FGs'!$B$6:$E$55,4,0),0) -> 0 | J89: =IFERROR(VLOOKUP(B89,'(B) FGs'!$B$6:$G$55,6,0),0) -> 0 | L89: =IFERROR(VLOOKUP(B89,'(B) FGs'!$B$6:$H$55,7,0),0) -> 0 | N89: =IFERROR(VLOOKUP(B89,'(B) FGs'!$B$6:$I$55,8,0),0) -> 0 | P89: =IFERROR(VLOOKUP(B89,'(B) FGs'!$B$6:$J$55,9,0),0) -> 0 | R89: 0 | T89: =IFERROR(VLOOKUP(B89,'(B) FGs'!$B$6:$L$55,11,0),0) -> 0 | V89: =F89+H89+J89+L89+N89+P89+R89+T89 -> 0 | W89: =G89+I89+K89+M89+O89+Q89+S89+U89 -> 0 | X89: =IFERROR(VLOOKUP(B89,'(B) FGs'!$B$6:$R$55,13,0),0) -> 0 | Z89: =IFERROR(VLOOKUP(B89,'(A) Inventory'!$A$7:$R$89,18,0),0) -> 0 | AB89: =IFERROR(VLOOKUP(B89,'(A) Inventory'!$A$7:$S$89,19,0),0) -> 0 | AD89: 0 | AF89: =X89+Z89+AB89+AD89 -> 0 | AG89: =Y89+AA89+AC89+AE89 -> 0 | AH89: =IFERROR(VLOOKUP(B89,'(A) Inventory'!$A$7:$P$89,16,0),0) -> 0 | AJ89: =IFERROR(VLOOKUP(B89,'(A) Inventory'!$A$7:$R$89,18,0),0) -> 0 | AL89: =AH89+AJ89 -> 0 | AM89: =AI89+AK89 -> 0 | AN89: =IFERROR(VLOOKUP(B89,'(B) FGs'!$B$6:$S$55,18,0),0)-IFERROR(VLOOKUP(B89,'(B) FGs'!$B$6:$M$55,12,0),0) -> 0 | AP89: =IFERROR(VLOOKUP(B89,'(B) FGs'!$B$6:$M$55,12,0),0) -> 0 | AR89: =IFERROR(VLOOKUP(B89,'(A) Inventory'!$A$7:$S$89,19,0),0) -> 0 | AT89: 0 | AV89: =AN89+AP89+AR89+AT89 -> 0 | AW89: =AO89+AQ89+AS89+AU89 -> 0 | AX89: 0 | AZ89: =D89+V89+AF89-AL89-AV89-AX89 -> 120 | BA89: =E89+W89+AG89-AM89-AW89-AY89 -> 2438.58 | BC89: =D89+V89+AF89-AL89-AV89-AX89=AZ89 -> TRUE | BD89: =D89+V89+AF89-AL89-AV89-AX89-AZ89 -> 0
B90: TOTAL | D90: =SUM(D7:D89) -> 679860 | E90: =SUM(E7:E89) -> 7772801.3 | F90: =SUM(F7:F89) -> 50800 | G90: =SUM(G7:G89) -> 0 | H90: =SUM(H7:H89) -> 646966 | I90: =SUM(I7:I89) -> 0 | J90: =SUM(J7:J89) -> 23934 | K90: =SUM(K7:K89) -> 0 | ... BA90: =SUM(BA7:BA89) -> 7772801.3 | BC90: =D90+V90+AF90-AL90-AV90-AX90=AZ90 -> TRUE | BD90: =D90+V90+AF90-AL90-AV90-AX90-AZ90 -> 0

Sheet (A) Inventory
A1: Nexplant EMI
A2: MAT ID | B2: TOTAL BOH | L2: INPUT QTY | P2: OUTPUT QTY | V2: SCRAP INFORMATION | Y2: TOTAL EOH | AQ2: GAP
Y3: EOH (A 급) | AG3: EOH (B 급) | AP3: TOTAL
B4: BOH (A 급) | D4: BOH (B 급) | K4: TOTAL | P4: SHIP (A 급) | R4: SHIP (B 급) | U4: TOTAL | Y4: S-FGs | AF4: SUB_TOTAL | AG4: PROD_WH | AH4: DEV_WH | AI4: EQM_WH | AJ4: PE_WH | AK4: WAIT_SHIP | AL4: QC_WH | AM4: SUB_TOTAL | AN4: WIP OR FGs
B5: Line(A) | C5: FG's(B) | D5: QC(C) | E5: R&D(D) | F5: TECH(E) | G5: WH#3(F) | H5: EQM(G) | I5: PROD_WH | J5: T_B_BOH | L5: INPUT USC | M5: LOCAL & ETC_IN | N5: BACK SHIP | O5: TOTAL | P5: PAID | Q5: FREE | R5: PAID | S5: FREE | T5: T_B_SHIP | V5: WIP | W5: FGs | X5: TOTAL | Y5: LINE(A) | Z5: LINE(A)-WH20(ERP) | AA5: WAIT_CF | AB5: FGs | AC5: CELL | AD5: CELL_PF | AE5: CELL_PF_PL | AN5: NG_WIP | AO5: NG_FGs
B6: 72055 | C6: 679860 | D6: 7196 | E6: 16471 | F6: 0 | G6: 300 | H6: 7 | I6: 0 | J6: =SUM(D6:I6) -> 23974 | K6: =B6+SUM(D6:I6) -> 96029 | L6: 762360 | M6: 0 | N6: 21600 | O6: 783960 | P6: 968912 | Q6: 21600 | R6: 513 | S6: 379 | T6: =R6+S6 -> 892 | U6: 991404 | V6: 44651 | W6: 1527 | X6: 46250 | Y6: 84509 | Z6: 8377 | AA6: 19633 | AB6: 414135 | AC6: 65049 | AD6: 0 | AE6: 8204 | AF6: 507021 | AG6: 0 | AH6: 6002 | AI6: 60 | AJ6: 0 | AK6: 0 | AL6: 9112 | AM6: 15174 | AN6: 14785 | AO6: 389 | AP6: 522195 | AQ6: 0
A7: 7075P | B7: 0 | C7: 10030 | D7: 13 | E7: 0 | F7: 0 | G7: 0 | H7: 0 | I7: 0 | J7: =SUM(D7:I7) -> 13 | K7: =B7+SUM(D7:I7) -> 13 | L7: 0 | M7: 0 | N7: 0 | O7: 0 | P7: 0 | Q7: 0 | R7: 0 | S7: 0 | T7: =R7+S7 -> 0 | U7: 0 | V7: 0 | W7: 0 | X7: 0 | Y7: 0 | Z7: 0 | AA7: 0 | AB7: 10030 | AC7: 0 | AD7: 0 | AE7: 0 | AF7: 10030 | AG7: 0 | AH7: 0 | AI7: 0 | AJ7: 0 | AK7: 0 | AL7: 13 | AM7: 13 | AN7: 13 | AO7: 0 | AP7: 10043 | AQ7: OK
A8: 712TP | B8: 0 | C8: 0 | D8: 184 | E8: 0 | F8: 0 | G8: 0 | H8: 0 | I8: 0 | J8: =SUM(D8:I8) -> 184 | K8: =B8+SUM(D8:I8) -> 184 | L8: 0 | M8: 0 | N8: 0 | O8: 0 | P8: 0 | Q8: 0 | R8: 0 | S8: 0 | T8: =R8+S8 -> 0 | U8: 0 | V8: 0 | W8: 0 | X8: 0 | Y8: 0 | Z8: 0 | AA8: 0 | AB8: 0 | AC8: 0 | AD8: 0 | AE8: 0 | AF8: 0 | AG8: 0 | AH8: 0 | AI8: 0 | AJ8: 0 | AK8: 0 | AL8: 184 | AM8: 184 | AN8: 184 | AO8: 0 | AP8: 184 | AQ8: OK
A9: 716AP | B9: 64354 | C9: 387259 | D9: 2554 | E9: 0 | F9: 0 | G9: 0 | H9: 7 | I9: 0 | J9: =SUM(D9:I9) -> 2561 | K9: =B9+SUM(D9:I9) -> 66915 | L9: 499392 | M9: 0 | N9: 21600 | O9: 520992 | P9: 594080 | Q9: 21600 | R9: 10 | S9: 5 | T9: =R9+S9 -> 15 | U9: 615695 | V9: 17731 | W9: 1523 | X9: 19267 | Y9: 47732 | Z9: 8103 | AA9: 17665 | AB9: 280531 | AC9: 33887 | AD9: 0 | AE9: 4283 | AF9: 336366 | AG9: 0 | AH9: 0 | AI9: 60 | AJ9: 0 | AK9: 0 | AL9: 3778 | AM9: 3838 | AN9: 3785 | AO9: 53 | AP9: 340204 | AQ9: OK
A10: 716BD | B10: 0 | C10: 987 | D10: 73 | E10: 0 | F10: 0 | G10: 0 | H10: 0 | I10: 0 | J10: =SUM(D10:I10) -> 73 | K10: =B10+SUM(D10:I10) -> 73 | L10: 0 | M10: 0 | N10: 0 | O10: 0 | P10: 0 | Q10: 0 | R10: 0 | S10: 0 | T10: =R10+S10 -> 0 | U10: 0 | V10: 0 | W10: 0 | X10: 0 | Y10: 0 | Z10: 0 | AA10: 0 | AB10: 987 | AC10: 0 | AD10: 0 | AE10: 0 | AF10: 987 | AG10: 0 | AH10: 0 | AI10: 0 | AJ10: 0 | AK10: 0 | AL10: 73 | AM10: 73 | AN10: 73 | AO10: 0 | AP10: 1060 | AQ10: OK
A11: 716CD | B11: 0 | C11: 38 | D11: 1 | E11: 0 | F11: 0 | G11: 0 | H11: 0 | I11: 0 | J11: =SUM(D11:I11) -> 1 | K11: =B11+SUM(D11:I11) -> 1 | L11: 0 | M11: 0 | N11: 0 | O11: 0 | P11: 0 | Q11: 0 | R11: 0 | S11: 0 | T11: =R11+S11 -> 0 | U11: 0 | V11: 0 | W11: 0 | X11: 0 | Y11: 0 | Z11: 0 | AA11: 0 | AB11: 38 | AC11: 0 | AD11: 0 | AE11: 0 | AF11: 38 | AG11: 0 | AH11: 0 | AI11: 0 | AJ11: 0 | AK11: 0 | AL11: 1 | AM11: 1 | AN11: 1 | AO11: 0 | AP11: 39 | AQ11: OK
A12: 716DD | B12: 0 | C12: 14976 | D12: 338 | E12: 2295 | F12: 0 | G12: 0 | H12: 0 | I12: 0 | J12: =SUM(D12:I12) -> 2633 | K12: =B12+SUM(D12:I12) -> 2633 | L12: 0 | M12: 0 | N12: 0 | O12: 0 | P12: 0 | Q12: 0 | R12: 0 | S12: 0 | T12: =R12+S12 -> 0 | U12: 0 | V12: 2295 | W12: 0 | X12: 2295 | Y12: 0 | Z12: 0 | AA12: 0 | AB12: 14976 | AC12: 0 | AD12: 0 | AE12: 0 | AF12: 14976 | AG12: 0 | AH12: 0 | AI12: 0 | AJ12: 0 | AK12: 0 | AL12: 338 | AM12: 338 | AN12: 338 | AO12: 0 | AP12: 15314 | AQ12: OK
A13: 716DTT | B13: 0 | C13: 0 | D13: 0 | E13: 20 | F13: 0 | G13: 300 | H13: 0 | I13: 0 | J13: =SUM(D13:I13) -> 320 | K13: =B13+SUM(D13:I13) -> 320 | L13: 16 | M13: 0 | N13: 0 | O13: 16 | P13: 0 | Q13: 0 | R13: 0 | S13: 300 | T13: =R13+S13 -> 300 | U13: 300 | V13: 36 | W13: 0 | X13: 36 | Y13: 0 | Z13: 0 | AA13: 0 | AB13: 0 | AC13: 0 | AD13: 0 | AE13: 0 | AF13: 0 | AG13: 0 | AH13: 0 | AI13: 0 | AJ13: 0 | AK13: 0 | AL13: 0 | AM13: 0 | AN13: 0 | AO13: 0 | AP13: 0 | AQ13: OK
A14: 716ED | B14: 0 | C14: 0 | D14: 32 | E14: 0 | F14: 0 | G14: 0 | H14: 0 | I14: 0 | J14: =SUM(D14:I14) -> 32 | K14: =B14+SUM(D14:I14) -> 32 | L14: 0 | M14: 0 | N14: 0 | O14: 0 | P14: 0 | Q14: 0 | R14: 0 | S14: 0 | T14: =R14+S14 -> 0 | U14: 0 | V14: 0 | W14: 0 | X14: 0 | Y14: 0 | Z14: 0 | AA14: 0 | AB14: 0 | AC14: 0 | AD14: 0 | AE14: 0 | AF14: 0 | AG14: 0 | AH14: 0 | AI14: 0 | AJ14: 0 | AK14: 0 | AL14: 32 | AM14: 32 | AN14: 32 | AO14: 0 | AP14: 32 | AQ14: OK
A15: 716ETT | B15: 0 | C15: 0 | D15: 0 | E15: 576 | F15: 0 | G15: 0 | H15: 0 | I15: 0 | J15: =SUM(D15:I15) -> 576 | K15: =B15+SUM(D15:I15) -> 576 | L15: 256 | M15: 0 | N15: 0 | O15: 256 | P15: 0 | Q15: 0 | R15: 350 | S15: 0 | T15: =R15+S15 -> 350 | U15: 350 | V15: 418 | W15: 0 | X15: 418 | Y15: 0 | Z15: 0 | AA15: 0 | AB15: 0 | AC15: 0 | AD15: 0 | AE15: 0 | AF15: 0 | AG15: 0 | AH15: 64 | AI15: 0 | AJ15: 0 | AK15: 0 | AL15: 0 | AM15: 64 | AN15: 64 | AO15: 0 | AP15: 64 | AQ15: OK
A16: 716FD | B16: 0 | C16: 0 | D16: 68 | E16: 0 | F16: 0 | G16: 0 | H16: 0 | I16: 0 | J16: =SUM(D16:I16) -> 68 | K16: =B16+SUM(D16:I16) -> 68 | L16: 0 | M16: 0 | N16: 0 | O16: 0 | P16: 0 | Q16: 0 | R16: 0 | S16: 0 | T16: =R16+S16 -> 0 | U16: 0 | V16: 0 | W16: 0 | X16: 0 | Y16: 0 | Z16: 0 | AA16: 0 | AB16: 0 | AC16: 0 | AD16: 0 | AE16: 0 | AF16: 0 | AG16: 0 | AH16: 0 | AI16: 0 | AJ16: 0 | AK16: 0 | AL16: 68 | AM16: 68 | AN16: 68 | AO16: 0 | AP16: 68 | AQ16: OK
A17: 716GD | B17: 0 | C17: 0 | D17: 3 | E17: 0 | F17: 0 | G17: 0 | H17: 0 | I17: 0 | J17: =SUM(D17:I17) -> 3 | K17: =B17+SUM(D17:I17) -> 3 | L17: 0 | M17: 0 | N17: 0 | O17: 0 | P17: 0 | Q17: 0 | R17: 0 | S17: 0 | T17: =R17+S17 -> 0 | U17: 0 | V17: 0 | W17: 0 | X17: 0 | Y17: 0 | Z17: 0 | AA17: 0 | AB17: 0 | AC17: 0 | AD17: 0 | AE17: 0 | AF17: 0 | AG17: 0 | AH17: 0 | AI17: 0 | AJ17: 0 | AK17: 0 | AL17: 3 | AM17: 3 | AN17: 3 | AO17: 0 | AP17: 3 | AQ17: OK
A18: 716JD | B18: 0 | C18: 3773 | D18: 16 | E18: 0 | F18: 0 | G18: 0 | H18: 0 | I18: 0 | J18: =SUM(D18:I18) -> 16 | K18: =B18+SUM(D18:I18) -> 16 | L18: 0 | M18: 0 | N18: 0 | O18: 0 | P18: 0 | Q18: 0 | R18: 0 | S18: 0 | T18: =R18+S18 -> 0 | U18: 0 | V18: 0 | W18: 0 | X18: 0 | Y18: 0 | Z18: 0 | AA18: 0 | AB18: 3773 | AC18: 0 | AD18: 0 | AE18: 0 | AF18: 3773 | AG18: 0 | AH18: 0 | AI18: 0 | AJ18: 0 | AK18: 0 | AL18: 16 | AM18: 16 | AN18: 16 | AO18: 0 | AP18: 3789 | AQ18: OK
... A89: 8191D | B89: 0 | C89: 120 | D89: 31 | E89: 0 | F89: 0 | G89: 0 | H89: 0 | I89: 0 | J89: =SUM(D89:I89) -> 31 | K89: =B89+SUM(D89:I89) -> 31 | L89: 0 | M89: 0 | N89: 0 | O89: 0 | P89: 0 | Q89: 0 | R89: 0 | S89: 0 | T89: =R89+S89 -> 0 | U89: 0 | V89: 0 | W89: 0 | X89: 0 | Y89: 0 | Z89: 0 | AA89: 0 | AB89: 120 | AC89: 0 | AD89: 0 | AE89: 0 | AF89: 120 | AG89: 0 | AH89: 0 | AI89: 0 | AJ89: 0 | AK89: 0 | AL89: 31 | AM89: 31 | AN89: 31 | AO89: 0 | AP89: 151 | AQ89: OK

Sheet (B) FGs
A1: Nexplant EMI
A2: WORK DATE | B2: MAT ID | C2: BOH | D2: INPUT (VPM OUT) | P2: OUTPUT QTY | U2: ACTUAL WH IN/OUT | V2: EOH | W2: GAP QTY
D3: NORMAL FG INPUT | G3: FROM LINE → FG-WAREHOUSE / 생산라인 → 완제품 창고 CELL 입고 | O3: INPUT TOTAL
D4: LAST-MONTH | E4: THIS-MONTH | F4: SUB TOTAL | G4: BACK-SHIP (SORTING) | H4: BACK-SHIP (PF-RW) | I4: BACK-SHIP (PL-RW) | J4: WH RETURN (SORTING) | K4: WH RETURN (PF-RW) | L4: WH RETURN (PL-RW) | M4: SUM REWORK | N4: BACK-SHIP (NG-QTY) | P4: Shipping (A 급) | Q4: Shiping B | R4: BACK SHIP | S4: TRANSFER TO LINE | T4: OUTPUT TOTAL
C5: 679860 | D5: 50800 | E5: 646966 | F5: 697766 | G5: 23934 | H5: 0 | I5: 0 | J5: 257976 | K5: 9997 | L5: 0 | M5: =H5+I5+K5+L5 -> 9997 | N5: 21600 | O5: 1011273 | P5: 968912 | Q5: 892 | R5: 21600 | S5: 286486 | T5: 1276998 | U5: 703187 | V5: 414135 | W5: 8766
A6: 20260630 | B6: 7075P | C6: 10030 | D6: 0 | E6: 0 | F6: 0 | G6: 0 | H6: 0 | I6: 0 | J6: 0 | K6: 0 | L6: 0 | M6: =H6+I6+K6+L6 -> 0 | N6: 0 | O6: 0 | P6: 0 | Q6: 0 | R6: 0 | S6: 0 | T6: 0 | U6: 0 | V6: 10030 | W6: 0
A7: 20260630 | B7: 716AP | C7: 387259 | D7: 39672 | E7: 441648 | F7: 481320 | G7: 23934 | H7: 0 | I7: 0 | J7: 242656 | K7: 9765 | L7: 0 | M7: =H7+I7+K7+L7 -> 9765 | O7: 779275 | P7: 594080 | Q7: 15 | R7: 21600 | S7: 270323 | T7: 886003 | U7: 487352 | V7: 280531 | W7: 0
A8: 20260630 | B8: 716BD | C8: 987 | D8: 0 | E8: 0 | F8: 0 | G8: 0 | H8: 0 | I8: 0 | J8: 0 | K8: 0 | L8: 0 | M8: =H8+I8+K8+L8 -> 0 | N8: 0 | O8: 0 | P8: 0 | Q8: 0 | R8: 0 | S8: 0 | T8: 0 | U8: 0 | V8: 987 | W8: 0
A9: 20260630 | B9: 716CD | C9: 38 | D9: 0 | E9: 0 | F9: 0 | G9: 0 | H9: 0 | I9: 0 | J9: 0 | K9: 0 | L9: 0 | M9: =H9+I9+K9+L9 -> 0 | N9: 0 | O9: 0 | P9: 0 | Q9: 0 | R9: 0 | S9: 0 | T9: 0 | U9: 0 | V9: 38 | W9: 0
A10: 20260630 | B10: 716DD | C10: 14976 | D10: 0 | E10: 0 | F10: 0 | G10: 0 | H10: 0 | I10: 0 | J10: 0 | K10: 0 | L10: 0 | M10: =H10+I10+K10+L10 -> 0 | N10: 0 | O10: 0 | P10: 0 | Q10: 0 | R10: 0 | S10: 0 | T10: 0 | U10: 0 | V10: 14976 | W10: 0
A11: 20260630 | B11: 716JD | C11: 3773 | D11: 0 | E11: 0 | F11: 0 | G11: 0 | H11: 0 | I11: 0 | J11: 0 | K11: 0 | L11: 0 | M11: =H11+I11+K11+L11 -> 0 | N11: 0 | O11: 0 | P11: 0 | Q11: 0 | R11: 0 | S11: 0 | T11: 0 | U11: 0 | V11: 3773 | W11: 0
A12: 20260630 | B12: 716KD | C12: 1943 | D12: 393 | E12: 0 | F12: 393 | G12: 0 | H12: 0 | I12: 0 | J12: 0 | K12: 0 | L12: 0 | M12: =H12+I12+K12+L12 -> 0 | N12: 0 | O12: 393 | P12: 0 | Q12: 0 | R12: 0 | S12: 0 | T12: 0 | U12: 393 | V12: 2336 | W12: 0
A13: 20260630 | B13: 716LD | C13: 55 | D13: 0 | E13: 0 | F13: 0 | G13: 0 | H13: 0 | I13: 0 | J13: 0 | K13: 0 | L13: 0 | M13: =H13+I13+K13+L13 -> 0 | N13: 0 | O13: 0 | P13: 0 | Q13: 0 | R13: 0 | S13: 0 | T13: 0 | U13: 0 | V13: 55 | W13: 0
A14: 20260630 | B14: 716ND | C14: 0 | D14: 0 | E14: 334 | F14: 334 | G14: 0 | H14: 0 | I14: 0 | J14: 0 | K14: 0 | L14: 0 | M14: =H14+I14+K14+L14 -> 0 | N14: 0 | O14: 334 | P14: 310 | Q14: 0 | R14: 0 | S14: 0 | T14: 310 | U14: 334 | V14: 24 | W14: 0
A15: 20260630 | B15: 716OD | C15: 0 | D15: 0 | E15: 97 | F15: 97 | G15: 0 | H15: 0 | I15: 0 | J15: 70 | K15: 0 | L15: 0 | M15: =H15+I15+K15+L15 -> 0 | N15: 0 | O15: 167 | P15: 70 | Q15: 0 | R15: 0 | S15: 97 | T15: 167 | U15: 70 | V15: 0 | W15: 0
A16: 20260630 | B16: 716T6 | C16: 25 | D16: 0 | E16: 0 | F16: 0 | G16: 0 | H16: 0 | I16: 0 | J16: 0 | K16: 0 | L16: 0 | M16: =H16+I16+K16+L16 -> 0 | N16: 0 | O16: 0 | P16: 0 | Q16: 0 | R16: 0 | S16: 0 | T16: 0 | U16: 0 | V16: 25 | W16: 0
A17: 20260630 | B17: 7171D | C17: 61 | D17: 0 | E17: 0 | F17: 0 | G17: 0 | H17: 0 | I17: 0 | J17: 0 | K17: 0 | L17: 0 | M17: =H17+I17+K17+L17 -> 0 | N17: 0 | O17: 0 | P17: 0 | Q17: 0 | R17: 0 | S17: 0 | T17: 0 | U17: 0 | V17: 61 | W17: 0
A18: 20260630 | B18: 7172D | C18: 27 | D18: 0 | E18: 0 | F18: 0 | G18: 0 | H18: 0 | I18: 0 | J18: 0 | K18: 0 | L18: 0 | M18: =H18+I18+K18+L18 -> 0 | N18: 0 | O18: 0 | P18: 0 | Q18: 0 | R18: 0 | S18: 0 | T18: 0 | U18: 0 | V18: 27 | W18: 0
A19: 20260630 | B19: 7173D | C19: 107 | D19: 0 | E19: 0 | F19: 0 | G19: 0 | H19: 0 | I19: 0 | J19: 0 | K19: 0 | L19: 0 | M19: =H19+I19+K19+L19 -> 0 | N19: 0 | O19: 0 | P19: 0 | Q19: 0 | R19: 0 | S19: 0 | T19: 0 | U19: 0 | V19: 107 | W19: 0
... A55: 20260630 | B55: 8191D | C55: 120 | D55: 0 | E55: 0 | F55: 0 | G55: 0 | H55: 0 | I55: 0 | J55: 0 | K55: 0 | L55: 0 | M55: =H55+I55+K55+L55 -> 0 | N55: 0 | O55: 0 | P55: 0 | Q55: 0 | R55: 0 | S55: 0 | T55: 0 | U55: 0 | V55: 120 | W55: 0

Sheet (C) S-FGs
A1: Nexplant EMI
A2: WORK DATE | B2: MAT ID | C2: BOH | F2: INPUT | J2: OUTPUT | S2: LOSS | V2: EOH | Y2: GAP
J3: NORMAL | L3: BACK SHIP (SORTING) | M3: BACK SHIP (PF-RW) | N3: BACK SHIP (PL-RW) | O3: WH RETURN (SORTING) | P3: WH RETURN (PF-RW) | Q3: WH RETURN (PL-RW) | R3: SUB TOTAL
C4: BOH | D4: BOH WAIT-CF | E4: SUB TOTAL | F4: USC CUTTING | G4: BACK SHIP | H4: RE SORTING | I4: SUB TOTAL | J4: THIS MONTH | K4: LAST MONTH | S4: THIS MONTH | T4: LAST MONTH | U4: SUB TOTAL | V4: EOH | W4: EOH WAIT-CF | X4: SUB TOTAL
A5: TOTAL | C5: 53699 | D5: 18356 | E5: 72055 | F5: 762360 | G5: 23934 | H5: 286486 | I5: 1048846 | J5: 646966 | K5: 50800 | L5: 23934 | M5: 0 | N5: 0 | O5: 257976 | P5: 9997 | Q5: 0 | R5: 989673 | S5: 33833 | T5: 4509 | U5: 38342 | V5: 73253 | W5: 19633 | X5: 92886 | Y5: 0
A6: 20260630 | B6: 716AP | C6: 46671 | D6: 17683 | E6: 64354 | F6: 499392 | G6: 23934 | H6: 270323 | I6: 769715 | J6: 441648 | K6: 39672 | L6: 23934 | M6: 0 | N6: 0 | O6: 242656 | P6: 9765 | Q6: 0 | R6: 757675 | S6: 17386 | T6: 3173 | U6: 20559 | V6: 38170 | W6: 17665 | X6: 55835 | Y6: 0
A7: 20260630 | B7: 716DTT | C7: 0 | D7: 0 | E7: 0 | F7: 16 | G7: 0 | H7: 0 | I7: 16 | J7: 0 | K7: 0 | L7: 0 | M7: 0 | N7: 0 | O7: 0 | P7: 0 | Q7: 0 | R7: 0 | S7: 16 | T7: 0 | U7: 16 | V7: 0 | W7: 0 | X7: 0 | Y7: 0
A8: 20260630 | B8: 716ETT | C8: 0 | D8: 0 | E8: 0 | F8: 256 | G8: 0 | H8: 0 | I8: 256 | J8: 0 | K8: 0 | L8: 0 | M8: 0 | N8: 0 | O8: 0 | P8: 0 | Q8: 0 | R8: 0 | S8: 256 | T8: 0 | U8: 256 | V8: 0 | W8: 0 | X8: 0 | Y8: 0
A9: 20260630 | B9: 716KD | C9: 452 | D9: 0 | E9: 452 | F9: 0 | G9: 0 | H9: 0 | I9: 0 | J9: 0 | K9: 393 | L9: 0 | M9: 0 | N9: 0 | O9: 0 | P9: 0 | Q9: 0 | R9: 393 | S9: 0 | T9: 59 | U9: 59 | V9: 0 | W9: 0 | X9: 0 | Y9: 0
A10: 20260630 | B10: 716ND | C10: 0 | D10: 0 | E10: 0 | F10: 496 | G10: 0 | H10: 0 | I10: 496 | J10: 334 | K10: 0 | L10: 0 | M10: 0 | N10: 0 | O10: 0 | P10: 0 | Q10: 0 | R10: 334 | S10: 162 | T10: 0 | U10: 162 | V10: 0 | W10: 0 | X10: 0 | Y10: 0
A11: 20260630 | B11: 716OD | C11: 0 | D11: 0 | E11: 0 | F11: 224 | G11: 0 | H11: 97 | I11: 321 | J11: 97 | K11: 0 | L11: 0 | M11: 0 | N11: 0 | O11: 70 | P11: 0 | Q11: 0 | R11: 167 | S11: 154 | T11: 0 | U11: 154 | V11: 0 | W11: 0 | X11: 0 | Y11: 0
A12: 20260630 | B12: 7175D | C12: 0 | D12: 3 | E12: 3 | F12: 0 | G12: 0 | H12: 0 | I12: 0 | J12: 0 | K12: 0 | L12: 0 | M12: 0 | N12: 0 | O12: 0 | P12: 0 | Q12: 0 | R12: 0 | S12: 0 | T12: 3 | U12: 3 | V12: 0 | W12: 0 | X12: 0 | Y12: 0
A13: 20260630 | B13: 7178D | C13: 4886 | D13: 377 | E13: 5263 | F13: 0 | G13: 0 | H13: 4429 | I13: 4429 | J13: 0 | K13: 4696 | L13: 0 | M13: 0 | N13: 0 | O13: 4247 | P13: 0 | Q13: 0 | R13: 8943 | S13: 0 | T13: 749 | U13: 749 | V13: 0 | W13: 0 | X13: 0 | Y13: 0
A14: 20260630 | B14: 7179D | C14: 879 | D14: 0 | E14: 879 | F14: 0 | G14: 0 | H14: 748 | I14: 748 | J14: 0 | K14: 725 | L14: 0 | M14: 0 | N14: 0 | O14: 701 | P14: 0 | Q14: 0 | R14: 1426 | S14: 0 | T14: 201 | U14: 201 | V14: 0 | W14: 0 | X14: 0 | Y14: 0
A15: 20260630 | B15: 717AD | C15: 549 | D15: 0 | E15: 549 | F15: 0 | G15: 0 | H15: 462 | I15: 462 | J15: 0 | K15: 445 | L15: 0 | M15: 0 | N15: 0 | O15: 404 | P15: 0 | Q15: 0 | R15: 849 | S15: 0 | T15: 162 | U15: 162 | V15: 0 | W15: 0 | X15: 0 | Y15: 0
A16: 20260630 | B16: 717BD | C16: 262 | D16: 0 | E16: 262 | F16: 0 | G16: 0 | H16: 152 | I16: 152 | J16: 0 | K16: 152 | L16: 0 | M16: 0 | N16: 0 | O16: 131 | P16: 0 | Q16: 0 | R16: 283 | S16: 0 | T16: 131 | U16: 131 | V16: 0 | W16: 0 | X16: 0 | Y16: 0
A17: 20260630 | B17: 7187D | C17: 0 | D17: 1 | E17: 1 | F17: 12930 | G17: 0 | H17: 0 | I17: 12930 | J17: 11305 | K17: 0 | L17: 0 | M17: 0 | N17: 0 | O17: 0 | P17: 0 | Q17: 0 | R17: 11305 | S17: 763 | T17: 1 | U17: 764 | V17: 0 | W17: 862 | X17: 862 | Y17: 0
... A20: 20260630 | B20: 818ETT | C20: 0 | D20: 0 | E20: 0 | F20: 688 | G20: 0 | H20: 0 | I20: 688 | J20: 0 | K20: 0 | L20: 0 | M20: 0 | N20: 0 | O20: 0 | P20: 0 | Q20: 0 | R20: 0 | S20: 688 | T20: 0 | U20: 688 | V20: 0 | W20: 0 | X20: 0 | Y20: 0

Sheet BOH
E1: LINE_WIP | G1: LINE_FGS | I1: BOH A_LEVEL SUB TOTAL | K1: B_LEVEL_WIP | M1: B_LEVEL_FGS | O1: BOH B_LEVEL SUB TOTAL
E2: PFL전 50% | F2: PFL후 90% | G2: PFL전 50% | H2: PFL후 90% | I2: PFL전 50% | J2: PFL후 90% | K2: PFL전 50% | L2: PFL후 90% | M2: PFL전 50% | N2: PFL후 90% | O2: PFL전 50% | P2: PFL후 90%
A3: # | B3: FACTORY | C3: MAT_ID | D3: WORK_DATE | E3: WIP_BEFORE_PFL | F3: WIP_AFTER_PFL | G3: FGS_BEFORE_PFL | H3: FGS_AFTER_PFL | K3: B_WIP_BEFORE_PFL | L3: B_WIP_AFTER_PFL | M3: B_FGS_BEFORE_PFL | N3: B_FGS_AFTER_PFL
A4: 1 | B4: DV01 | C4: 7075P | D4: 20260531 | E4: 0 | F4: 0 | G4: 0 | H4: 0 | I4: =E4+G4 -> 0 | J4: =F4+H4 -> 0 | K4: 6 | L4: 7 | M4: 0 | N4: 0 | O4: =K4+M4 -> 6 | P4: =L4+N4 -> 7
A5: 2 | B5: DV01 | C5: 712TP | D5: 20260531 | E5: 0 | F5: 0 | G5: 0 | H5: 0 | I5: =E5+G5 -> 0 | J5: =F5+H5 -> 0 | K5: 173 | L5: 11 | M5: 0 | N5: 0 | O5: =K5+M5 -> 173 | P5: =L5+N5 -> 11
A6: 3 | B6: DV01 | C6: 716AP | D6: 20260531 | E6: 30912 | F6: 17821 | G6: 0 | H6: 15621 | I6: =E6+G6 -> 30912 | J6: =F6+H6 -> 33442 | K6: 2246 | L6: 292 | M6: 0 | N6: 23 | O6: =K6+M6 -> 2246 | P6: =L6+N6 -> 315
A7: 4 | B7: DV01 | C7: 716BD | D7: 20260531 | E7: 0 | F7: 0 | G7: 0 | H7: 0 | I7: =E7+G7 -> 0 | J7: =F7+H7 -> 0 | K7: 69 | L7: 4 | M7: 0 | N7: 0 | O7: =K7+M7 -> 69 | P7: =L7+N7 -> 4
A8: 5 | B8: DV01 | C8: 716CD | D8: 20260531 | E8: 0 | F8: 0 | G8: 0 | H8: 0 | I8: =E8+G8 -> 0 | J8: =F8+H8 -> 0 | K8: 0 | L8: 1 | M8: 0 | N8: 0 | O8: =K8+M8 -> 0 | P8: =L8+N8 -> 1
A9: 6 | B9: DV01 | C9: 716DD | D9: 20260531 | E9: 0 | F9: 0 | G9: 0 | H9: 0 | I9: =E9+G9 -> 0 | J9: =F9+H9 -> 0 | K9: 328 | L9: 2161 | M9: 0 | N9: 144 | O9: =K9+M9 -> 328 | P9: =L9+N9 -> 2305
A10: 7 | B10: DV01 | C10: 716DTT | D10: 20260531 | E10: 0 | F10: 0 | G10: 0 | H10: 0 | I10: =E10+G10 -> 0 | J10: =F10+H10 -> 0 | K10: 320 | L10: 0 | M10: 0 | N10: 0 | O10: =K10+M10 -> 320 | P10: =L10+N10 -> 0
A11: 8 | B11: DV01 | C11: 716ED | D11: 20260531 | E11: 0 | F11: 0 | G11: 0 | H11: 0 | I11: =E11+G11 -> 0 | J11: =F11+H11 -> 0 | K11: 31 | L11: 1 | M11: 0 | N11: 0 | O11: =K11+M11 -> 31 | P11: =L11+N11 -> 1
A12: 9 | B12: DV01 | C12: 716ETT | D12: 20260531 | E12: 0 | F12: 0 | G12: 0 | H12: 0 | I12: =E12+G12 -> 0 | J12: =F12+H12 -> 0 | K12: 576 | L12: 0 | M12: 0 | N12: 0 | O12: =K12+M12 -> 576 | P12: =L12+N12 -> 0
A13: 10 | B13: DV01 | C13: 716FD | D13: 20260531 | E13: 0 | F13: 0 | G13: 0 | H13: 0 | I13: =E13+G13 -> 0 | J13: =F13+H13 -> 0 | K13: 67 | L13: 1 | M13: 0 | N13: 0 | O13: =K13+M13 -> 67 | P13: =L13+N13 -> 1
A14: 11 | B14: DV01 | C14: 716GD | D14: 20260531 | E14: 0 | F14: 0 | G14: 0 | H14: 0 | I14: =E14+G14 -> 0 | J14: =F14+H14 -> 0 | K14: 2 | L14: 1 | M14: 0 | N14: 0 | O14: =K14+M14 -> 2 | P14: =L14+N14 -> 1
A15: 12 | B15: DV01 | C15: 716JD | D15: 20260531 | E15: 0 | F15: 0 | G15: 0 | H15: 0 | I15: =E15+G15 -> 0 | J15: =F15+H15 -> 0 | K15: 15 | L15: 1 | M15: 0 | N15: 0 | O15: =K15+M15 -> 15 | P15: =L15+N15 -> 1
... A72: 69 | B72: DV01 | C72: 8191D | D72: 20260531 | E72: 0 | F72: 0 | G72: 0 | H72: 0 | I72: =E72+G72 -> 0 | J72: =F72+H72 -> 0 | K72: 30 | L72: 1 | M72: 0 | N72: 0 | O72: =K72+M72 -> 30 | P72: =L72+N72 -> 1
A73: TOTAL | E73: =SUM(E4:E72) -> 36254 | F73: =SUM(F4:F72) -> 20177 | G73: =SUM(G4:G72) -> 0 | H73: =SUM(H4:H72) -> 15624 | I73: =SUM(I4:I72) -> 36254 | J73: =SUM(J4:J72) -> 35801 | K73: =SUM(K4:K72) -> 13148 | L73: =SUM(L4:L72) -> 5431 | ... P73: =SUM(P4:P72) -> 10826

Sheet EOH
E1: 1 | G1: 2 | I1: 3 | K1: 4 | M1: 5 (1+3) | O1: 6 (2+4) | Q1: TOTAL_EOH (MES) 7=5+6
E2: LINE_WIP (A) | G2: LINE_FGs (A) | I2: B_LEVEL WIP (A) | K2: B_LEVEL FGs | M2: T_EOH WIP | O2: T_EOH FGs
E3: PFL전 50% | F3: PFL후 90% | G3: PFL전 50% | H3: PFL후 90% | I3: PFL전 50% | J3: PFL후 90% | K3: PFL전 50% | L3: PFL후 90% | M3: PFL전 50% | N3: PFL후 90% | O3: PFL전 50% | P3: PFL후 90% | Q3: PFL전 50% | R3: PFL후 90%
A4: # | B4: FACTORY | C4: MAT_ID | D4: WORK_DATE | E4: WIP_BEFORE_PFL | F4: WIP_AFTER_PFL | G4: FGS_BEFORE_PFL | H4: FGS_AFTER_PFL | K4: B_WIP_BEFORE_PFL | L4: B_WIP_AFTER_PFL | M4: B_FGS_BEFORE_PFL | N4: B_FGS_AFTER_PFL
A5: 1 | B5: DV01 | C5: 7075P | D5: 20260630 | E5: 0 | F5: 0 | G5: 0 | H5: 0 | K5: 6 | L5: 7 | M5: 0 | N5: 0
A6: 2 | B6: DV01 | C6: 712TP | D6: 20260630 | E6: 0 | F6: 0 | G6: 0 | H6: 0 | K6: 173 | L6: 11 | M6: 0 | N6: 0
A7: 3 | B7: DV01 | C7: 716AP | D7: 20260630 | E7: 33958 | F7: 13774 | G7: 0 | H7: 8103 | K7: 3283 | L7: =502 -> 502 | M7: 0 | N7: =66-13 -> 53 | O7: 72
A8: 4 | B8: DV01 | C8: 716BD | D8: 20260630 | E8: 0 | F8: 0 | G8: 0 | H8: 0 | K8: 69 | L8: 4 | M8: 0 | N8: 0
A9: 5 | B9: DV01 | C9: 716CD | D9: 20260630 | E9: 0 | F9: 0 | G9: 0 | H9: 0 | K9: 0 | L9: 1 | M9: 0 | N9: 0
A10: 6 | B10: DV01 | C10: 716DD | D10: 20260630 | E10: 0 | F10: 0 | G10: 0 | H10: 0 | K10: 328 | L10: 10 | M10: 0 | N10: 0
A11: 7 | B11: DV01 | C11: 716ED | D11: 20260630 | E11: 0 | F11: 0 | G11: 0 | H11: 0 | K11: 31 | L11: 1 | M11: 0 | N11: 0
A12: 8 | B12: DV01 | C12: 716ETT | D12: 20260630 | E12: 0 | F12: 0 | G12: 0 | H12: 0 | K12: 64 | L12: 0 | M12: 0 | N12: 0
A13: 9 | B13: DV01 | C13: 716FD | D13: 20260630 | E13: 0 | F13: 0 | G13: 0 | H13: 0 | K13: 67 | L13: 1 | M13: 0 | N13: 0
A14: 10 | B14: DV01 | C14: 716GD | D14: 20260630 | E14: 0 | F14: 0 | G14: 0 | H14: 0 | K14: 2 | L14: 1 | M14: 0 | N14: 0
A15: 11 | B15: DV01 | C15: 716JD | D15: 20260630 | E15: 0 | F15: 0 | G15: 0 | H15: 0 | K15: 15 | L15: 1 | M15: 0 | N15: 0
A16: 12 | B16: DV01 | C16: 716KD | D16: 20260630 | E16: 0 | F16: 0 | G16: 0 | H16: 0 | K16: 204 | L16: =5 -> 5 | M16: 0 | N16: =1-1 -> 0
A17: 13 | B17: DV01 | C17: 716LD | D17: 20260630 | E17: 0 | F17: 0 | G17: 0 | H17: 0 | K17: 1 | L17: 0 | M17: 0 | N17: 0
A18: 14 | B18: DV01 | C18: 716ND | D18: 20260630 | E18: 0 | F18: 0 | G18: 0 | H18: 0 | K18: 2 | L18: 75 | M18: 0 | N18: 0
A19: 15 | B19: DV01 | C19: 716NTT | D19: 20260630 | E19: 0 | F19: 0 | G19: 0 | H19: 0 | K19: 25 | L19: 0 | M19: 0 | N19: 0
A20: 16 | B20: DV01 | C20: 716OD | D20: 20260630 | E20: 0 | F20: 0 | G20: 0 | H20: 0 | K20: 1 | L20: 46 | M20: 0 | N20: 27
A21: 17 | B21: DV01 | C21: 716T6 | D21: 20260630 | E21: 0 | F21: 0 | G21: 0 | H21: 0 | K21: 1 | L21: 0 | M21: 0 | N21: 0
A22: 18 | B22: DV01 | C22: 716T7 | D22: 20260630 | E22: 0 | F22: 0 | G22: 0 | H22: 0 | K22: 1 | L22: 0 | M22: 0 | N22: 0
A23: 19 | B23: DV01 | C23: 716TB | D23: 20260630 | E23: 0 | F23: 0 | G23: 0 | H23: 0 | K23: 4 | L23: 0 | M23: 0 | N23: 0
A24: 20 | B24: DV01 | C24: 716TE | D24: 20260630 | E24: 0 | F24: 0 | G24: 0 | H24: 0 | K24: 2 | L24: 0 | M24: 0 | N24: 0
A25: 21 | B25: DV01 | C25: 716TG | D25: 20260630 | E25: 0 | F25: 0 | G25: 0 | H25: 0 | K25: 1 | L25: 0 | M25: 0 | N25: 0
A26: 22 | B26: DV01 | C26: 716TH | D26: 20260630 | E26: 0 | F26: 0 | G26: 0 | H26: 0 | K26: 1 | L26: 0 | M26: 0 | N26: 0
A27: 23 | B27: DV01 | C27: 716UCCT | D27: 20260630 | E27: 0 | F27: 0 | G27: 0 | H27: 0 | K27: 2 | L27: 0 | M27: 0 | N27: 0
A28: 24 | B28: DV01 | C28: 7171D | D28: 20260630 | E28: 0 | F28: 0 | G28: 0 | H28: 0 | K28: 8 | L28: 1 | M28: 0 | N28: 0
... A41: 37 | B41: DV01 | C41: 7186D | D41: 20260630 | E41: 0 | F41: 0 | G41: 0 | H41: 0 | K41: 3 | L41: 1 | M41: 0 | N41: 0
A42: 38 | B42: DV01 | C42: 7187D | D42: 20260630 | E42: 0 | F42: 862 | G42: 0 | H42: 0 | K42: 1117 | L42: =571 -> 571 | M42: 0 | N42: =1-1 -> 0
A43: 39 | B43: DV01 | C43: 7188D | D43: 20260630 | E43: 0 | F43: 0 | G43: 0 | H43: 0 | K43: 536 | L43: 50 | M43: 0 | N43: 0
A44: 40 | B44: DV01 | C44: 7189D | D44: 20260630 | E44: 0 | F44: 0 | G44: 0 | H44: 0 | K44: 112 | L44: 85 | M44: 0 | N44: 0
A45: 41 | B45: DV01 | C45: 7191D | D45: 20260630 | E45: 0 | F45: 0 | G45: 0 | H45: 0 | K45: 2 | L45: 1 | M45: 0 | N45: 0
A46: 42 | B46: DV01 | C46: 7192D | D46: 20260630 | E46: 0 | F46: 0 | G46: 0 | H46: 0 | K46: 0 | L46: 1 | M46: 0 | N46: 0
A47: 43 | B47: DV01 | C47: 814OD | D47: 20260630 | E47: 0 | F47: 0 | G47: 0 | H47: 0 | K47: 17 | L47: 0 | M47: 0 | N47: 0
A48: 44 | B48: DV01 | C48: 8178D | D48: 20260630 | E48: 0 | F48: 0 | G48: 0 | H48: 0 | K48: 35 | L48: =525 -> 525 | M48: 0 | N48: =57-57 -> 0
A49: 45 | B49: DV01 | C49: 817AD | D49: 20260630 | E49: 0 | F49: 0 | G49: 0 | H49: 0 | K49: 1 | L49: 1 | M49: 0 | N49: 0
A50: 46 | B50: DV01 | C50: 817BD | D50: 20260630 | E50: 0 | F50: 0 | G50: 0 | H50: 0 | K50: 2 | L50: 2 | M50: 0 | N50: 0
A51: 47 | B51: DV01 | C51: 817CD | D51: 20260630 | E51: 0 | F51: 0 | G51: 0 | H51: 0 | K51: 1 | L51: 1 | M51: 0 | N51: 0
A52: 48 | B52: DV01 | C52: 817DD | D52: 20260630 | E52: 0 | F52: 0 | G52: 0 | H52: 0 | K52: 0 | L52: 1 | M52: 0 | N52: 0
A53: 49 | B53: DV01 | C53: 817NTT | D53: 20260630 | E53: 0 | F53: 0 | G53: 0 | H53: 0 | K53: 1 | L53: 0 | M53: 0 | N53: 0
A54: 50 | B54: DV01 | C54: 8188D | D54: 20260630 | E54: 0 | F54: 0 | G54: 0 | H54: 0 | K54: 27 | L54: 1 | M54: 0 | N54: 0
A55: 51 | B55: DV01 | C55: 8189D | D55: 20260630 | E55: 0 | F55: 0 | G55: 0 | H55: 0 | K55: 3 | L55: 1 | M55: 0 | N55: 0
A56: 52 | B56: DV01 | C56: 818AD | D56: 20260630 | E56: 0 | F56: 0 | G56: 0 | H56: 0 | K56: 16 | L56: 2 | M56: 0 | N56: 0
A57: 53 | B57: DV01 | C57: 818AP | D57: 20260630 | E57: 31232 | F57: 4683 | G57: 0 | H57: 274 | K57: 3253 | L57: 260 | M57: 0 | N57: 1
A58: 54 | B58: DV01 | C58: 818BD | D58: 20260630 | E58: 0 | F58: 0 | G58: 0 | H58: 0 | K58: 344 | L58: 1 | M58: 0 | N58: 0
A59: 55 | B59: DV01 | C59: 818CD | D59: 20260630 | E59: 0 | F59: 0 | G59: 0 | H59: 0 | K59: 5 | L59: 0 | M59: 0 | N59: 0
A60: 56 | B60: DV01 | C60: 818DD | D60: 20260630 | E60: 0 | F60: 0 | G60: 0 | H60: 0 | K60: 19 | L60: 1 | M60: 0 | N60: 0
... A71: 67 | B71: DV01 | C71: 8191D | D71: 20260630 | E71: 0 | F71: 0 | G71: 0 | H71: 0 | K71: 30 | L71: 1 | M71: 0 | N71: 0

Sheet 정의(Định nghĩa)>>>>

Sheet 배부기준 및 단가 산정
B2: 생산환산량 = | D2: 재공품(IN + OUT + LOSS) 수량 | K2: 1 | L2: 자재수불부 확정 | R2: ↓
D3: (PL전 수량 * 50%) + (PL 후 수량 * 90%) | K3: 2 | L3: 경비 확정 | R3: ↓
K4: 3 | L4: 생산실적 확정 | R4: ↓
K5: 4 | L5: 재료비 배부 | R5: ↓
B6: 배부적수 = | D6: 생산환산량 X 모델별 면적 | K6: 5 | L6: 제조경비 배부 | R6: ↓
K7: 6 | L7: 재공품단가 계산 | R7: ↓ | S7: < | T7: ㅡ | U7: ㄱ
K8: 7 | L8: 재공품 기말재공 평가 (PL 전 50%, PL 후 90%) | R8: ↓ | U8: ㅣ
B9: 배부비율 = | D9: 모델별 배부적수 | K9: 8 | L9: 제품제조원가 산정 | R9: ↓ | U9: ㅣ
D10: 당월 총 배부적수 | K10: 8 | L10: 제품 단가 산정 | R10: ↓ | S10: product unit price | U10: ㅣ
K11: 9 | L11: 제품 매출원가&재고산정 | R11: ↓
B13: 재공품 단가 = | D13: (EOH + IN + ETC-IN) 금액
D14: [OUT + ETC-OUT + (PL 전 * 50%) + (PL 후 * 90%)] 수량
B17: 재공재고 금액 = | D17: 재공품 단가 X 포지션별 수량 X 포지션별 평가비율
B20: 제품 단가 = | D20: (BOH + IN+ETC_IN)금액
D21: (BOH + IN+ETC_IN)수량

Sheet Rework Resorting
B3: 재공품
B4: 모델 | C4: 기초 | E4: 입고 | G4: 기타입고 | I4: 출고 | K4: 기타출고 | M4: 로스 | O4: 재고 | Q4: 단가
C5: 수량 | D5: 금액 | E5: 수량 | F5: 금액 | G5: 수량 | H5: 금액 | I5: 수량 | J5: 금액 | K5: 수량 | L5: 금액 | M5: 수량 | N5: 금액 | O5: 수량 | P5: 금액 | S5: 재공품 단가
B6: 716AP | C6: 30 | D6: 300 | E6: 40 | F6: 480 | G6: =K11 -> 10 | H6: =L11 -> 222.85714 | I6: 10 | J6: =D6+F6+H6-L6-N6-P6 -> 222.85714 | O6: =C6+E6+G6-I6-K6-M6 -> 70 | P6: =Q6*O6*50% -> 780 | Q6: =IFERROR((D6+F6+H6)/(O6*50%+I6+K6),0) -> 22.285714 | S6: =(D6+F6+(K11*Q11)) -> 1002.8571
B8: 제품
B9: 모델 | C9: 기초 | E9: 입고 | G9: 기타입고 | I9: 출고 | K9: 기타출고 | M9: 로스 | O9: 재고 | Q9: 단가
C10: 수량 | D10: 금액 | E10: 수량 | F10: 금액 | G10: 수량 | H10: 금액 | I10: 수량 | J10: 금액 | K10: 수량 | L10: 금액 | M10: 수량 | N10: 금액 | O10: 수량 | P10: 금액
B11: 716AP | E11: =I6 -> 10 | F11: =J6 -> 222.85714 | K11: 10 | L11: =Q11*K11 -> 222.85714 | O11: =C11+E11+G11-I11-K11-M11 -> 0 | P11: =D11+F11+H11-J11-L11-N11 -> 0 | Q11: =(D11+F11+H11)/(C11+E11+G11) -> 22.285714 | S11: =(D11+(S6*I11))/(C11+I11) -> #DIV/0!
A15: 1 | B15: 재공품의 기타입고 수량, 금액 = 제품의 기타출고에서 옴
A16: 2 | B16: 제품의 기타출고 수량, 금액 = 평균단가를 이용하여 기타출고금액이 산정된다
A17: 3 | B17: 제품의 평균단가는 = (기초+입고+기타입고)금액 / (기초+입고+기타입고)수량이다
A18: 4 | B18: 제품의 입고 수량, 금액은 재공품의 출고 수량/금액과 동일하다
A19: 5 | B19: 재공품의 출고 금액이 확정되려면 기타입고 수량, 금액을 확정하고 단가를 계산해야 한다.
B20: 다시 1번부터 진행
B22: 기존 재고를 R/W or R/S 진행하는 경우
B23: 당월 재공품을 완성 후 R/W or R/S 진행하는 경우
B28: 재공품 | F28: + | H28: + | J28: - | L28: -
B29: 모델 | C29: 기초(BOH) | E29: 입고(IN) | G29: 기타입고(ETC IN) | I29: 출고(OUT) | K29: 기타출고(ETC OUT) | M29: 로스(LOSS) | O29: 재고(EOH) | Q29: 단가
C30: 수량 | D30: 금액 | E30: 수량 | F30: 금액 | G30: 수량 | H30: 금액 | I30: 수량 | J30: 금액 | K30: 수량 | L30: 금액 | M30: 수량 | N30: 금액 | O30: 수량 | P30: 금액 | S30: 재공품 단가
B31: 716AP | E31: 30 | F31: 300 | G31: 2 | H31: =L36 -> 100 | I31: =1+1 -> 2 | J31: =D31+F31+H31-L31-N31-P31 -> 47.058824 | O31: =C31+E31+G31-I31-K31-M31 -> 30 | P31: =Q31*O31*50% -> 352.94118 | Q31: =IFERROR((D31+F31+H31)/(O31*50%+I31+K31),0) -> 23.529412 | S31: =(D31+F31+H31)/(I31+O31*50%) -> 23.529412
B33: 제품
B34: 모델 | C34: 기초(BOH) | E34: 입고(IN) | G34: 기타입고(ETC IN) | I34: 출고(OUT) | K34: 기타출고(ETC OUT) | M34: 로스(LOSS) | O34: 재고(EOH) | Q34: 단가
C35: 수량 | D35: 금액 | E35: 수량 | F35: 금액 | G35: 수량 | H35: 금액 | I35: 수량 | J35: 금액 | K35: 수량 | L35: 금액 | M35: 수량 | N35: 금액 | O35: 수량 | P35: 금액
B36: 716AP | C36: 1 | D36: 100 | E36: =I31 -> 2 | F36: =J31 -> 47.058824 | K36: 3 | L36: =+D36 -> 100 | O36: =C36+E36+G36-I36-K36-M36 -> 0 | P36: =D36+F36+H36-J36-L36-N36 -> 47.058824 | Q36: =(D36+F36+H36)/(C36+E36+G36) -> 49.019608 | S36: =(D36+(S31*I36))/(C36+I36) -> 100
B38: 제품
B39: 모델 | C39: 기초(BOH) | E39: 입고(IN) | G39: 기타입고(ETC IN) | I39: 출고(OUT) | K39: 기타출고(ETC OUT) | M39: 로스(LOSS) | O39: 재고(EOH) | Q39: 단가
C40: 수량 | D40: 금액 | E40: 수량 | F40: 금액 | G40: 수량 | H40: 금액 | I40: 수량 | J40: 금액 | K40: 수량 | L40: 금액 | M40: 수량 | N40: 금액 | O40: 수량 | P40: 금액
B41: 716AP | C41: 8 | D41: 800 | E41: 2 | F41: 0 | K41: 1 | L41: 0 | O41: =C41+E41+G41-I41-K41-M41 -> 9 | P41: =D41+F41+H41-J41-L41-N41 -> 800 | Q41: =(D41+F41+H41)/(C41+E41+G41) -> 80 | S41: =(D41+(S36*I41))/(C41+I41) -> 100
K42: 1 | L42: 100
B44: 제품
B45: 모델 | C45: 기초(BOH) | E45: 입고(IN) | G45: 기타입고(ETC IN) | I45: 출고(OUT) | K45: 기타출고(ETC OUT) | M45: 기타출고(ETC OUT) | O45: 로스(LOSS) | Q45: 재고(EOH) | S45: 단가
C46: 수량 | D46: 금액 | E46: 수량 | F46: 금액 | G46: 수량 | H46: 금액 | I46: 수량 | J46: 금액 | K46: 수량 | L46: 금액 | M46: 수량 | N46: 금액 | O46: 수량 | P46: 금액 | Q46: 수량 | R46: 금액
B47: 716AP | C47: 1 | D47: 100 | E47: 2 | F47: 0 | K47: 2 | L47: 100 | Q47: =C47+E47+G47-I47-K47-O47 -> 1 | R47: =D47+F47+H47-J47-L47-P47 -> 0 | S47: =(D47+F47+H47)/(C47+E47+G47) -> 33.333333
B50: * R/S R/W 협의사항
B51: 모든 R/S, R/W에 대해 아래와 같이 정의한다.
B52: R/S, R/W에 대해 제품 기타출고 금액은 기초 제품 단가를 활용한다.
B53: -제품 기초수량/금액 ≥ 기타출고(R/S, R/W) 수량 인 경우 전액을 기초금액에서 출고 시킨다.
B54: -제품 기초수량/금액 < 기타출고(R/S, R/W) 수량 인 경우 기초금액에서 출고 시키되 기초금액을 초과 한 경우 금액은 출고하지 않는다.
A56: Case1 | B56: BOH ≥ ETC_OUT
B57: 제품
B58: 모델 | C58: 기초(BOH) | E58: 입고(IN) | G58: 기타입고(ETC IN) | I58: 출고(OUT) | K58: 기타출고(ETC OUT) | M58: 기타출고(ETC OUT) | O58: 로스(LOSS) | Q58: 재고(EOH) | S58: 단가
C59: 수량 | D59: 금액 | E59: 수량 | F59: 금액 | G59: 수량 | H59: 금액 | I59: 수량 | J59: 금액 | K59: 수량 | L59: 금액 | M59: 수량 | N59: 금액 | O59: 수량 | P59: 금액 | Q59: 수량 | R59: 금액
B60: 716AP | C60: 5 | D60: 500 | F60: 0 | K60: 3 | L60: 300 | Q60: =C60+E60+G60-I60-K60-O60 -> 2 | R60: =D60+F60+H60-J60-L60-P60 -> 200 | S60: =(D60+F60+H60)/(C60+E60+G60) -> 100
A62: Case2 | B62: BOH < ETC_OUT
B63: 제품
B64: 모델 | C64: 기초(BOH) | E64: 입고(IN) | G64: 기타입고(ETC IN) | I64: 출고(OUT) | K64: 기타출고(ETC OUT) | M64: 기타출고(ETC OUT) | O64: 로스(LOSS) | Q64: 재고(EOH) | S64: 단가
C65: 수량 | D65: 금액 | E65: 수량 | F65: 금액 | G65: 수량 | H65: 금액 | I65: 수량 | J65: 금액 | K65: 수량 | L65: 금액 | M65: 수량 | N65: 금액 | O65: 수량 | P65: 금액 | Q65: 수량 | R65: 금액
B66: 716AP | C66: 1 | D66: 100 | F66: 0 | K66: 3 | L66: 100 | Q66: =C66+E66+G66-I66-K66-O66 -> -2 | R66: =D66+F66+H66-J66-L66-P66 -> 0 | S66: =(D66+F66+H66)/(C66+E66+G66) -> 100
A68: Case2-1 | B68: BOH < ETC_OUT
B69: 제품
B70: 모델 | C70: 기초(BOH) | E70: 입고(IN) | G70: 기타입고(ETC IN) | I70: 출고(OUT) | K70: 기타출고(ETC OUT) | M70: 기타출고(ETC OUT) | O70: 로스(LOSS) | Q70: 재고(EOH) | S70: 단가
C71: 수량 | D71: 금액 | E71: 수량 | F71: 금액 | G71: 수량 | H71: 금액 | I71: 수량 | J71: 금액 | K71: 수량 | L71: 금액 | M71: 수량 | N71: 금액 | O71: 수량 | P71: 금액 | Q71: 수량 | R71: 금액
B72: 716AP | C72: 0 | D72: 0 | F72: 0 | K72: 3 | L72: 0 | Q72: =C72+E72+G72-I72-K72-O72 -> -3 | R72: =D72+F72+H72-J72-L72-P72 -> 0 | S72: =(D72+F72+H72)/(C72+E72+G72) -> #DIV/0!
B74: * Case2와 Case3에서 재고수량이 마이너스가 뜨는 것은 재공품 출고 (제품 입고) 실적을 제외하였기 때문에 마이너스가 보이지만, 실제로는 재공품을 생산완료 후 입고처리를 하기에 재고 산식에 오류는 발생하지 않음.

Sheet code
C2: SDV | E2: DWV
A3: 1) | C3: LJ97-08434A | E3: 818AP
C4: LJ97-08434A | E4: 818APP
A7: 2) | C7: LJ97-08434A | E7: 818AP
C8: LJ97-08434B | E8: 818AP
C9: LJ97-08434C | E9: 818AP
A15: Case 1 | C15: USC IN PUT | E15: Code change | G15: VPM OUT | I15: Product in | L15: Sales (I/V NAME)
B16: R&D | C16: 716DD | G16: 716DD | I16: =G16 -> 716DD | L16: 716DD
G17: 716DF | I17: =G17 -> 716DF | L17: 716DF
G18: 716DZ | I18: =G18 -> 716DZ | L18: 716DZ
C21: USC IN PUT | E21: after PCLN | G21: PFL~VPM OUT | I21: Product in | L21: Sales (I/V NAME)
A22: Case2 | C22: 716DD | E22: 716APD | G22: 716AP | I22: 716AP | L22: 716AP | N22: MES x
A23: Case3 | C23: 716DD | E23: 716APD | G23: 716APD | I23: 716APD | L23: 716AP | N23: MES O
E24: *New BOM(716APD)

Sheet 종류
B2: 재고자산 종류 Loại tài sản tồn kho | C2: 구분 phân loại | D2: 항목명 Tên danh mục | E2: 번호 Số thứ tự | F2: 컬럼 협의 | G2: 추가 사항
B3: 재공품 (WIP) | C3: 기타입고 Nhập kho khác | D3: CODE변경 | E3: 1 | F3: 컬럼 생성 | G3: MES, ERP 고도화 후 추가 로직 검토 필요
D4: Re-Sorting(재검사) | E4: 2 | F4: OK
D5: Re-work(SI검사) | E5: 3 | F5: OK
D6: 반제품 입고 | E6: 4 | F6: OK
C7: 기타출고 Xuất kho khác | D7: CODE변경 | E7: 5 | F7: 컬럼 생성 | G7: MES, ERP 고도화 후 추가 로직 검토 필요
G8: > PL 전/후 구분 (신규 컬럼 생성 → MES, CMS)
D9: 반제품 출고(유상) | E9: 6 | F9: OK | G9: > PL 전/후 구분 (신규 컬럼 생성 → MES, CMS)
D10: 반제품 출고(무상) | E10: 7 | F10: OK | G10: > PL 전/후 구분 (신규 컬럼 생성 → MES, CMS)
B11: 제품 (PRODUCT) | C11: 기타입고 Nhập kho khác | D11: RMA | E11: 8 | F11: OK
D12: 반제품 입고(유상) | E12: 9 | F12: OK
D13: 반제품 입고(무상) | E13: 10 | F13: OK
C14: 기타출고 Xuất kho khác | D14: Re-Sorting(재검사) | E14: 11 | F14: OK | G14: R/S가 R/W보다 우선 순위로 배부된다.
D15: Re-work(SI검사) | E15: 12 | F15: OK | G15: R/S가 R/W보다 우선 순위로 배부된다.
D16: RMA | E16: 13 | F16: OK | G16: EMI, ERP 컬럼 삭제
D17: 무상매출 | E17: 14 | F17: OK
B20: 1. 재공품의 기타출고, loss에 대해서 PL 전, 후 컬럼 신규 생성
B21: 2. RMA 세금계산서 발행되는 것만 실적 보낼 수 있는지 (MES > ERP or CMS)
B22: 모든 Re-Sorting의 기타출고/기타입고 값은 당월 제품 기초재고를 활용 세부내용은 페이지에서 설명

Sheet 1
B2: 재고자산 종류 | D2: 재공품
B3: 구분 | D3: 기타입고
B4: 항목명 | D4: CODE변경
B6: 정의 : 공정 생산 중 최초 투입 된 모델에서 다른 모델로 생산 변경을 의미한다.
B7: Định nghĩa: Là việc thay đổi sản xuất từ model được đưa vào ban đầu trong quá trình sản xuất sang model khác.
B9: 아래와 같이 2가지 케이스가 발생할 수 있으며 각각 아래와 같이 처리한다. (모델, 수량, 금액은 예시입니다.)
B10: Có thể phát sinh 2 trường hợp như dưới đây, và mỗi trường hợp được xử lý như sau. (Model, số lượng, số tiền chỉ là ví dụ minh họa.)
A12: ① | B12: 전월 투입한 모델에 대해(기초 재공) 당월 다른 모델로 생산 변경 된 경우
A13: ① | B13: Trường hợp model đã đưa vào sản xuất từ tháng trước (WIP đầu kỳ) được thay đổi sang model khác trong tháng này
B14: 6월 (Tháng 6) - WIP
B15: Model | C15: BOH | E15: IN | G15: ETC_IN | I15: OUT | K15: ETC_OUT | M15: LOSS | O15: EOH
C16: 수량 Số lượng | D16: 금액 Số tiền | E16: 수량 Số lượng | F16: 금액 Số tiền | G16: 수량 Số lượng | H16: 금액 Số tiền | I16: 수량 Số lượng | J16: 금액 Số tiền | K16: 수량 Số lượng | L16: 금액 Số tiền | M16: 수량 Số lượng | N16: 금액 Số tiền | O16: 수량 Số lượng | P16: 금액 Số tiền
B17: 716AP | C17: 0 | D17: 0 | E17: 100 | F17: 100 | G17: 0 | H17: 0 | I17: 0 | J17: 0 | K17: 0 | L17: 0 | M17: 0 | N17: 0 | O17: =C17+E17+G17-I17-K17-M17 -> 100 | P17: =D17+F17+H17-J17-L17-N17 -> 100
B18: 06월 716AP 모델에 생산투입을 100개 하였고, 제조원가가 100$ 배부 된 경우, 그리고 모든 수량이 재공 재고로 남아 있는 경우 위와 같이 표현이 됩니다.
B19: Trường hợp trong Tháng 06, đã đưa vào sản xuất 100 sản phẩm model 716AP, chi phí sản xuất được phân bổ là 100$, và toàn bộ số lượng vẫn còn tồn kho dưới dạng sản phẩm dở dang (WIP), thì sẽ được thể hiện như trên.
B21: 7월 (Tháng 7) - WIP | G21: CODE변경 | K21: CODE변경
B22: Model | C22: BOH | E22: IN | G22: ETC_IN | I22: OUT | K22: ETC_OUT | M22: LOSS | O22: EOH
C23: 수량 Số lượng | D23: 금액 Số tiền | E23: 수량 Số lượng | F23: 금액 Số tiền | G23: 수량 Số lượng | H23: 금액 Số tiền | I23: 수량 Số lượng | J23: 금액 Số tiền | K23: 수량 Số lượng | L23: 금액 Số tiền | M23: 수량 Số lượng | N23: 금액 Số tiền | O23: 수량 Số lượng | P23: 금액 Số tiền
B24: 716AP | C24: 100 | D24: 100 | E24: 0 | F24: 0 | G24: 0 | H24: 0 | I24: 0 | J24: 0 | K24: 40 | L24: 40 | M24: 0 | N24: 0 | O24: =C24+E24+G24-I24-K24-M24 -> 60 | P24: =D24+F24+H24-J24-L24-N24 -> 60
B25: 999KP | C25: 0 | D25: 0 | E25: 0 | F25: 0 | G25: 40 | H25: 40 | I25: 0 | J25: 0 | K25: 0 | L25: 0 | M25: 0 | N25: 0 | O25: =C25+E25+G25-I25-K25-M25 -> 40 | P25: =D25+F25+H25-J25-L25-N25 -> 40
B26: 07월 999KP 모델 생산에 716AP의 기초재공 수량을 40개 CODE 변경 한 경우 위와 같이 표현 됩니다.
B27: Trường hợp trong Tháng 07, thay đổi CODE 40 sản phẩm WIP đầu kỳ của model 716AP sang sản xuất model 999KP, thì sẽ được thể hiện như trên.
B29: 또한 CODE변경 된 999KP의 경우 생산량이 없는 경우 ( OUT or LOSS) 기말 재공평가를 진행하지 않고 기타입고의 금액을 100% 반영 합니다.
B30: Ngoài ra, đối với model 999KP đã được thay đổi CODE, trong trường hợp không có sản lượng sản xuất (OUT hoặc LOSS), sẽ không tiến hành đánh giá WIP cuối kỳ, mà phản ánh 100% giá trị của khoản nhập kho khác (Nhập kho khác).
B31: 만약 CODE변경 된 999KP가 생산량이 있는 경우 (OUT or Loss) 기말 재공품의 PL전, 후로 나뉘어 평가합니다.
B32: Nếu model 999KP đã được thay đổi CODE có phát sinh sản lượng sản xuất (OUT hoặc LOSS), thì sẽ đánh giá WIP cuối kỳ bằng cách chia thành trước PL và sau PL.
A34: ② | B34: 당월 투입한 모델에 대해, 다른 모델로 생산 변경 된 경우
A35: ② | B35: Trường hợp model đã đưa vào sản xuất trong tháng này được thay đổi sang model khác
B36: 7월 (Tháng 7) - WIP
B37: Model | C37: BOH | E37: IN | G37: ETC_IN | I37: OUT | K37: ETC_OUT | M37: LOSS | O37: EOH
C38: 수량 Số lượng | D38: 금액 Số tiền | E38: 수량 Số lượng | F38: 금액 Số tiền | G38: 수량 Số lượng | H38: 금액 Số tiền | I38: 수량 Số lượng | J38: 금액 Số tiền | K38: 수량 Số lượng | L38: 금액 Số tiền | M38: 수량 Số lượng | N38: 금액 Số tiền | O38: 수량 Số lượng | P38: 금액 Số tiền
B39: 716AP | D39: 0 | E39: 100 | F39: 100 | G39: 0 | H39: 0 | I39: 0 | J39: 0 | K39: 0 | L39: 0 | M39: 0 | N39: 0 | O39: =C39+E39+G39-I39-K39-M39 -> 100 | P39: =D39+F39+H39-J39-L39-N39 -> 100
B40: 07월에 716AP 모델에 100개 생산투입을 하였고, 제조원가가 100$ 배부 된 경우. (재공 재고는 무시하고 IN의 숫자만 확인 해주십시요)
B41: Trường hợp trong Tháng 07, đã đưa vào sản xuất 100 sản phẩm model 716AP, và chi phí sản xuất được phân bổ là 100$. (Vui lòng bỏ qua tồn kho WIP, chỉ kiểm tra số liệu IN.)
B43: 7월 (Tháng 7) - WIP
B44: Model | C44: BOH | E44: IN | G44: ETC_IN | I44: OUT | K44: ETC_OUT | M44: LOSS | O44: EOH
C45: 수량 Số lượng | D45: 금액 Số tiền | E45: 수량 Số lượng | F45: 금액 Số tiền | G45: 수량 Số lượng | H45: 금액 Số tiền | I45: 수량 Số lượng | J45: 금액 Số tiền | K45: 수량 Số lượng | L45: 금액 Số tiền | M45: 수량 Số lượng | N45: 금액 Số tiền | O45: 수량 Số lượng | P45: 금액 Số tiền
B46: 716AP | D46: 0 | E46: 60 | F46: 60 | G46: 0 | H46: 0 | I46: 0 | J46: 0 | K46: 0 | L46: 0 | M46: 0 | N46: 0 | O46: =C46+E46+G46-I46-K46-M46 -> 60 | P46: =D46+F46+H46-J46-L46-N46 -> 60
B47: 999KP | D47: 0 | E47: 40 | F47: 40 | G47: 0 | H47: 0 | I47: 0 | J47: 0 | K47: 0 | L47: 0 | M47: 0 | N47: 0 | O47: =C47+E47+G47-I47-K47-M47 -> 40 | P47: =D47+F47+H47-J47-L47-N47 -> 40
B48: 당월 투입분에 대해서는 기타출고 → 기타입고가 아닌, 투입 자체의 수량을 변경 된 모델에 적용한다
B49: Đối với phần đưa vào sản xuất trong tháng này, không áp dụng Xuất kho khác → Nhập kho khác, mà áp dụng trực tiếp số lượng đưa vào sản xuất (input) cho model đã được thay đổi.
A51: 46235 | B51: MES, ERP, 구매그룹(영업판매) 파트에서 추가적인 검토사항이 확인되어 CMS 구축 시 컬럼만 신규 생성 후 로직과 데이터 반영은 추후에 진행

Sheet 2
B2: 재고자산 종류 | D2: 재공품
B3: 구분 | D3: 기타입고
B4: 항목명 | D4: Re-Sorting(재검사)
B6: 정의 : 생산완료 된 제품에 대하여 어떠한 사유로 Re-sorting(재검사)를 하는 경우
B7: Định nghĩa: Trường hợp thực hiện Re-sorting (kiểm tra lại) đối với sản phẩm đã hoàn thành sản xuất vì một lý do nào đó
B9: 아래와 같은 케이스가 발생할 수 있으며 아래와 같이 처리한다. (모델, 수량, 금액은 예시입니다.)
B10: Có thể phát sinh trường hợp như dưới đây, và được xử lý như sau. (Model, số lượng, số tiền chỉ là ví dụ minh họa.)
B12: 6월 (Tháng 6) - Product
B13: Model | C13: BOH | E13: IN | G13: ETC_IN | I13: OUT | K13: ETC_OUT | M13: LOSS | O13: EOH
C14: 수량 Số lượng | D14: 금액 Số tiền | E14: 수량 Số lượng | F14: 금액 Số tiền | G14: 수량 Số lượng | H14: 금액 Số tiền | I14: 수량 Số lượng | J14: 금액 Số tiền | K14: 수량 Số lượng | L14: 금액 Số tiền | M14: 수량 Số lượng | N14: 금액 Số tiền | O14: 수량 Số lượng | P14: 금액 Số tiền
B15: 716AP | C15: 100 | D15: 100 | E15: 40 | F15: 40 | G15: 0 | H15: 0 | I15: 0 | J15: 0 | K15: 0 | L15: 0 | M15: 0 | N15: 0 | O15: =C15+E15+G15-I15-K15-M15 -> 140 | P15: =D15+F15+H15-J15-L15-N15 -> 140
B16: 06월 716AP 제품에 대해서 100개의 재고가 있고 (단가 1$) 당월 생산입고가 40개가 됐다고 가정한다 (단가 1$)
B17: Giả định trong Tháng 06, model 716AP có tồn kho 100 sản phẩm (đơn giá 1),vaˋtrongthaˊngnaˋycoˊ40sảnphẩmnhậpkhotừsảnxua^ˊt(đơngiaˊ1), và trong tháng này có 40 sản phẩm nhập kho từ sản xuất (đơn giá 1 ),vaˋtrongthaˊngnaˋycoˊ40sảnphẩmnhậpkhotừsảnxua^ˊt(đơngiaˊ1).
B18: 기타출고되는 제품의 단가는 기초단가를 활용한다. 만약 기초수량과 금액이 부족한 경우 8월1일 협의한 내용을 따른다.
B19: Đơn giá của thành phẩm được xuất kho khác sử dụng đơn giá đầu kỳ. Nếu số lượng và số tiền đầu kỳ không đủ, thì tuân theo nội dung đã thỏa thuận vào ngày 1 tháng 8.
B21: 6월 (Tháng 6) - Product | K21: Re-work(SI검사)
B22: Model | C22: BOH | E22: IN | G22: ETC_IN | I22: OUT | K22: ETC_OUT | M22: LOSS | O22: EOH
C23: 수량 Số lượng | D23: 금액 Số tiền | E23: 수량 Số lượng | F23: 금액 Số tiền | G23: 수량 Số lượng | H23: 금액 Số tiền | I23: 수량 Số lượng | J23: 금액 Số tiền | K23: 수량 Số lượng | L23: 금액 Số tiền | M23: 수량 Số lượng | N23: 금액 Số tiền | O23: 수량 Số lượng | P23: 금액 Số tiền
B24: 716AP | C24: 100 | D24: 100 | E24: 40 | F24: 40 | G24: 0 | H24: 0 | I24: 0 | J24: 0 | K24: 30 | L24: 30 | M24: 0 | N24: 0 | O24: =C24+E24+G24-I24-K24-M24 -> 110 | P24: =D24+F24+H24-J24-L24-N24 -> 110
B26: 6월 (Tháng 6) - WIP | G26: Re-work(SI검사)
B27: Model | C27: BOH | E27: IN | G27: ETC_IN | I27: OUT | K27: ETC_OUT | M27: LOSS | O27: EOH
C28: 수량 Số lượng | D28: 금액 Số tiền | E28: 수량 Số lượng | F28: 금액 Số tiền | G28: 수량 Số lượng | H28: 금액 Số tiền | I28: 수량 Số lượng | J28: 금액 Số tiền | K28: 수량 Số lượng | L28: 금액 Số tiền | M28: 수량 Số lượng | N28: 금액 Số tiền | O28: 수량 Số lượng | P28: 금액 Số tiền
B29: 716AP | C29: 0 | D29: 0 | E29: 0 | F29: 0 | G29: 30 | H29: 30 | I29: 0 | J29: 0 | K29: 0 | L29: 0 | M29: 0 | N29: 0 | O29: =C29+E29+G29-I29-K29-M29 -> 30 | P29: =D29+F29+H29-J29-L29-N29 -> 30
B30: 716AP 제품이 Re-work으로 공정 재투입 할 경우, 제품에서 기타출고하여 동일한 수량과 금액을 재공품의 기타입고로 처리한다.
B31: Trường hợp sản phẩm 716AP được tái nhập vào quy trình sản xuất thông qua Re-work, thì thực hiện xuất kho khác từ thành phẩm, và xử lý nhập kho khác vào WIP (sản phẩm dở dang) với cùng số lượng và số tiền.
B32: 기타입고 된 재공품 716AP의 생산실적이 없는 경우 기말 재공평가를 진행하지 않고 기타입고의 금액을 100% 반영 합니다.
B33: Trường hợp WIP model 716AP đã được nhập kho khác không có sản lượng sản xuất thực tế (OUT hoặc LOSS), thì sẽ không tiến hành đánh giá WIP cuối kỳ, mà phản ánh 100% giá trị của khoản nhập kho khác.
B34: 기타입고 된 재공품 716AP의 생산실적이 있는 경우 (OUT or Loss) 기말 재공품의 PL전, 후로 나뉘어 평가합니다.
B35: Trường hợp WIP model 716AP đã được nhập kho khác có sản lượng sản xuất thực tế (OUT hoặc LOSS), thì sẽ đánh giá WIP cuối kỳ bằng cách chia thành trước PL và sau PL.
B36: 해당 재공품의 생산실적이 반영되는 달에 제조원가가 가산 됩니다.
B37: Chi phí sản xuất sẽ được cộng thêm (gia tăng) vào tháng mà sản lượng sản xuất thực tế của WIP đó được phản ánh.
A40: 검토필요 | B40: WIP
B41: Model | C41: BOH | E41: IN | G41: ETC_IN | I41: OUT | K41: ETC_OUT | M41: LOSS | O41: EOH | U41: 단가
C42: 수량 Số lượng | D42: 금액 Số tiền | E42: 수량 Số lượng | F42: 금액 Số tiền | G42: 수량 Số lượng | H42: 금액 Số tiền | I42: 수량 Số lượng | J42: 금액 Số tiền | K42: 수량 Số lượng | L42: 금액 Số tiền | M42: 수량 Số lượng | N42: 금액 Số tiền | O42: 수량(PL전) Số lượng | P42: 금액(PL전) Số tiền | Q42: 수량(PL후) Số lượng | R42: 금액(PL후) Số tiền | S42: 수량(Total) Số lượng | T42: 금액(Total) Số tiền | U42: 금액 Số tiền
B43: 716AP | C43: 10 | D43: 1000 | E43: 38 | F43: 4257 | G43: 10 | I43: 10 | J43: =I43*U43 -> 1194.7727 | O43: 23 | P43: =O43*U43*50% -> 1373.9886 | Q43: 25 | R43: =Q43*U43*90% -> 2688.2386 | S43: =O43+Q43 -> 48 | T43: =P43+R43 -> 4062.2273 | U43: =(D43+F43+H43)/((I43+K43+(O43*50%)+(Q43*90%))) -> 119.47727
B46: PRODUCT
B47: Model | C47: BOH | E47: IN | G47: ETC_IN | I47: OUT | K47: ETC_OUT | M47: LOSS | O47: EOH | Q47: 단가
C48: 수량 Số lượng | D48: 금액 Số tiền | E48: 수량 Số lượng | F48: 금액 Số tiền | G48: 수량 Số lượng | H48: 금액 Số tiền | I48: 수량 Số lượng | J48: 금액 Số tiền | K48: 수량 Số lượng | L48: 금액 Số tiền | M48: 수량 Số lượng | N48: 금액 Số tiền | O48: 수량 Số lượng | P48: 금액 Số tiền | Q48: 금액 Số tiền
B49: 716AP | E49: =I43 -> 10 | F49: =J43 -> 1194.7727 | L49: =K49*Q49 -> 0 | N49: =M49*Q49 -> 0 | O49: =C49+E49+G49-I49-K49-M49 -> 10 | P49: =O49*Q49 -> 1194.7727 | Q49: =(D49+F49+H49)/(C49+E49+G49) -> 119.47727
B52: PRODUCT - RE SORTING
B53: Model | C53: BOH | E53: IN | G53: ETC_IN | I53: OUT | K53: ETC_OUT | M53: LOSS | O53: EOH | Q53: 단가
C54: 수량 Số lượng | D54: 금액 Số tiền | E54: 수량 Số lượng | F54: 금액 Số tiền | G54: 수량 Số lượng | H54: 금액 Số tiền | I54: 수량 Số lượng | J54: 금액 Số tiền | K54: 수량 Số lượng | L54: 금액 Số tiền | M54: 수량 Số lượng | N54: 금액 Số tiền | O54: 수량 Số lượng | P54: 금액 Số tiền | Q54: 금액 Số tiền
B55: 716AP | E55: 10 | F55: =F49 -> 1194.7727 | K55: 10 | L55: =K55*Q55 -> 1194.7727 | N55: =M55*Q55 -> 0 | O55: =C55+E55+G55-I55-K55-M55 -> 0 | P55: =O55*Q55 -> 0 | Q55: =(D55+F55+H55)/(C55+E55+G55) -> 119.47727
B58: WIP - RE SORTING
B59: Model | C59: BOH | E59: IN | G59: ETC_IN | I59: OUT | K59: ETC_OUT | M59: LOSS | O59: EOH
C60: 수량 Số lượng | D60: 금액 Số tiền | E60: 수량 Số lượng | F60: 금액 Số tiền | G60: 수량 Số lượng | H60: 금액 Số tiền | I60: 수량 Số lượng | J60: 금액 Số tiền | K60: 수량 Số lượng | L60: 금액 Số tiền | M60: 수량 Số lượng | N60: 금액 Số tiền | O60: 수량(PL전) Số lượng | P60: 금액(PL전) Số tiền | Q60: 수량(PL후) Số lượng | R60: 금액(PL후) Số tiền | S60: 수량(Total) Số lượng | T60: 금액(Total) Số tiền
B61: 716AP | G61: 10 | H61: =L55 -> 1194.7727
A64: 46235 | B64: * R/S R/W 협의사항
B65: 모든 R/S, R/W에 대해 아래와 같이 정의한다.
B66: Định nghĩa tất cả các R/S, R/W như sau
B67: R/S, R/W에 대해 제품 기타출고 금액은 기초 제품 단가를 활용한다.
B68: Đối với R/S, R/W, số tiền xuất kho khác của thành phẩm sử dụng đơn giá đầu kỳ của thành phẩm
B69: -제품 기초수량/금액 ≥ 기타출고(R/S, R/W) 수량 인 경우 전액을 기초금액에서 출고 시킨다.
B70: - Trường hợp số lượng/số tiền đầu kỳ của thành phẩm ≥ số lượng xuất kho khác (R/S, R/W), thì xuất kho toàn bộ số tiền từ số tiền đầu kỳ.
B71: -제품 기초수량/금액 < 기타출고(R/S, R/W) 수량 인 경우 기초금액에서 출고 시키되 기초금액을 초과 한 경우 금액은 출고하지 않는다.
B72: - Trường hợp số lượng/số tiền đầu kỳ của thành phẩm < số lượng xuất kho khác (R/S, R/W), thì xuất kho từ số tiền đầu kỳ, nhưng phần số tiền vượt quá số tiền đầu kỳ thì không xuất kho.
A74: Case1 | B74: BOH ≥ ETC_OUT
B75: 제품 (Product)
B76: 모델 | C76: 기초(BOH) | E76: 입고(IN) | G76: 기타입고(ETC IN) | I76: 출고(OUT) | K76: 기타출고(ETC OUT) | M76: 기타출고(ETC OUT) | O76: 로스(LOSS) | Q76: 재고(EOH) | S76: 단가
C77: 수량 | D77: 금액 | E77: 수량 | F77: 금액 | G77: 수량 | H77: 금액 | I77: 수량 | J77: 금액 | K77: 수량 | L77: 금액 | M77: 수량 | N77: 금액 | O77: 수량 | P77: 금액 | Q77: 수량 | R77: 금액
B78: 716AP | C78: 5 | D78: 500 | F78: 0 | K78: 3 | L78: 300 | Q78: =C78+E78+G78-I78-K78-O78 -> 2 | R78: =D78+F78+H78-J78-L78-P78 -> 200 | S78: =(D78+F78+H78)/(C78+E78+G78) -> 100
A80: Case2 | B80: BOH < ETC_OUT
B81: 제품 (Product)
B82: 모델 | C82: 기초(BOH) | E82: 입고(IN) | G82: 기타입고(ETC IN) | I82: 출고(OUT) | K82: 기타출고(ETC OUT) | M82: 기타출고(ETC OUT) | O82: 로스(LOSS) | Q82: 재고(EOH) | S82: 단가
C83: 수량 | D83: 금액 | E83: 수량 | F83: 금액 | G83: 수량 | H83: 금액 | I83: 수량 | J83: 금액 | K83: 수량 | L83: 금액 | M83: 수량 | N83: 금액 | O83: 수량 | P83: 금액 | Q83: 수량 | R83: 금액
B84: 716AP | C84: 1 | D84: 100 | F84: 0 | K84: 3 | L84: 100 | Q84: =C84+E84+G84-I84-K84-O84 -> -2 | R84: =D84+F84+H84-J84-L84-P84 -> 0 | S84: =(D84+F84+H84)/(C84+E84+G84) -> 100
A86: Case2-1 | B86: BOH < ETC_OUT
B87: 제품 (Product)
B88: 모델 | C88: 기초(BOH) | E88: 입고(IN) | G88: 기타입고(ETC IN) | I88: 출고(OUT) | K88: 기타출고(ETC OUT) | M88: 기타출고(ETC OUT) | O88: 로스(LOSS) | Q88: 재고(EOH) | S88: 단가
C89: 수량 | D89: 금액 | E89: 수량 | F89: 금액 | G89: 수량 | H89: 금액 | I89: 수량 | J89: 금액 | K89: 수량 | L89: 금액 | M89: 수량 | N89: 금액 | O89: 수량 | P89: 금액 | Q89: 수량 | R89: 금액
B90: 716AP | C90: 0 | D90: 0 | F90: 0 | K90: 3 | L90: 0 | Q90: =C90+E90+G90-I90-K90-O90 -> -3 | R90: =D90+F90+H90-J90-L90-P90 -> 0 | S90: =(D90+F90+H90)/(C90+E90+G90) -> #DIV/0!
B92: * Case2와 Case3에서 재고수량이 마이너스가 뜨는 것은 재공품 출고 (제품 입고) 실적을 제외하였기 때문에 마이너스가 보이지만, 실제로는 재공품을 생산완료 후 입고처리를 하기에 재고 산식에 오류는 발생하지 않음.
B93: * Ở Case 2 và Case 3, việc số lượng tồn kho hiển thị âm là do đã loại trừ thành tích xuất kho WIP (nhập kho thành phẩm), nên hiển thị âm, nhưng thực tế thì WIP được xử lý nhập kho sau khi hoàn thành sản xuất, nên công thức tồn kho không phát sinh lỗi.

Sheet 3
B2: 재고자산 종류 | D2: 재공품
B3: 구분 | D3: 기타입고
B4: 항목명 | D4: Re-work(SI검사)
B6: 정의 : 생산완료 된 제품에 대하여 공정에 재투입하여 생산하는 경우
B7: Định nghĩa: Trường hợp đưa sản phẩm đã hoàn thành sản xuất tái nhập vào quy trình để sản xuất lại
B9: 아래와 같은 케이스가 발생할 수 있으며 아래와 같이 처리한다. (모델, 수량, 금액은 예시입니다.)
B10: Có thể phát sinh trường hợp như dưới đây, và được xử lý như sau. (Model, số lượng, số tiền chỉ là ví dụ minh họa.)
B12: 6월 (Tháng 6) - Product
B13: Model | C13: BOH | E13: IN | G13: ETC_IN | I13: OUT | K13: ETC_OUT | M13: LOSS | O13: EOH
C14: 수량 Số lượng | D14: 금액 Số tiền | E14: 수량 Số lượng | F14: 금액 Số tiền | G14: 수량 Số lượng | H14: 금액 Số tiền | I14: 수량 Số lượng | J14: 금액 Số tiền | K14: 수량 Số lượng | L14: 금액 Số tiền | M14: 수량 Số lượng | N14: 금액 Số tiền | O14: 수량 Số lượng | P14: 금액 Số tiền
B15: 716AP | C15: 100 | D15: 100 | E15: 40 | F15: 40 | G15: 0 | H15: 0 | I15: 0 | J15: 0 | K15: 0 | L15: 0 | M15: 0 | N15: 0 | O15: =C15+E15+G15-I15-K15-M15 -> 140 | P15: =D15+F15+H15-J15-L15-N15 -> 140
B16: 06월 716AP 제품에 대해서 100개의 재고가 있고 (단가 1$) 당월 생산입고가 40개가 됐다고 가정한다 (단가 1$)
B17: Giả định trong Tháng 06, model 716AP có tồn kho 100 sản phẩm (đơn giá 1),vaˋtrongthaˊngnaˋycoˊ40sảnphẩmnhậpkhotừsảnxua^ˊt(đơngiaˊ1), và trong tháng này có 40 sản phẩm nhập kho từ sản xuất (đơn giá 1 ),vaˋtrongthaˊngnaˋycoˊ40sảnphẩmnhậpkhotừsảnxua^ˊt(đơngiaˊ1).
B18: 기타출고되는 제품의 단가는 기초단가를 활용한다. 만약 기초수량과 금액이 부족한 경우 8월1일 협의한 내용을 따른다.
B19: Đơn giá của thành phẩm được xuất kho khác sử dụng đơn giá đầu kỳ. Nếu số lượng và số tiền đầu kỳ không đủ, thì tuân theo nội dung đã thỏa thuận vào ngày 1 tháng 8.
B21: 6월 (Tháng 6) - Product | K21: Re-work(SI검사)
B22: Model | C22: BOH | E22: IN | G22: ETC_IN | I22: OUT | K22: ETC_OUT | M22: LOSS | O22: EOH
C23: 수량 Số lượng | D23: 금액 Số tiền | E23: 수량 Số lượng | F23: 금액 Số tiền | G23: 수량 Số lượng | H23: 금액 Số tiền | I23: 수량 Số lượng | J23: 금액 Số tiền | K23: 수량 Số lượng | L23: 금액 Số tiền | M23: 수량 Số lượng | N23: 금액 Số tiền | O23: 수량 Số lượng | P23: 금액 Số tiền
B24: 716AP | C24: 100 | D24: 100 | E24: 40 | F24: 40 | G24: 0 | H24: 0 | I24: 0 | J24: 0 | K24: 30 | L24: 30 | M24: 0 | N24: 0 | O24: =C24+E24+G24-I24-K24-M24 -> 110 | P24: =D24+F24+H24-J24-L24-N24 -> 110
B26: 6월 (Tháng 6) - WIP | G26: Re-work(SI검사)
B27: Model | C27: BOH | E27: IN | G27: ETC_IN | I27: OUT | K27: ETC_OUT | M27: LOSS | O27: EOH
C28: 수량 Số lượng | D28: 금액 Số tiền | E28: 수량 Số lượng | F28: 금액 Số tiền | G28: 수량 Số lượng | H28: 금액 Số tiền | I28: 수량 Số lượng | J28: 금액 Số tiền | K28: 수량 Số lượng | L28: 금액 Số tiền | M28: 수량 Số lượng | N28: 금액 Số tiền | O28: 수량 Số lượng | P28: 금액 Số tiền
B29: 716AP | C29: 0 | D29: 0 | E29: 0 | F29: 0 | G29: 30 | H29: 30 | I29: 0 | J29: 0 | K29: 0 | L29: 0 | M29: 0 | N29: 0 | O29: =C29+E29+G29-I29-K29-M29 -> 30 | P29: =D29+F29+H29-J29-L29-N29 -> 30
B30: 716AP 제품이 Re-work으로 공정 재투입 할 경우, 제품에서 기타출고하여 동일한 수량과 금액을 재공품의 기타입고로 처리한다.
B31: Trường hợp sản phẩm 716AP được tái nhập vào quy trình sản xuất thông qua Re-work, thì thực hiện xuất kho khác từ thành phẩm, và xử lý nhập kho khác vào WIP (sản phẩm dở dang) với cùng số lượng và số tiền.
B32: 기타입고 된 재공품 716AP의 생산실적이 없는 경우 기말 재공평가를 진행하지 않고 기타입고의 금액을 100% 반영 합니다.
B33: Trường hợp WIP model 716AP đã được nhập kho khác không có sản lượng sản xuất thực tế (OUT hoặc LOSS), thì sẽ không tiến hành đánh giá WIP cuối kỳ, mà phản ánh 100% giá trị của khoản nhập kho khác.
B34: 기타입고 된 재공품 716AP의 생산실적이 있는 경우 (OUT or Loss) 기말 재공품의 PL전, 후로 나뉘어 평가합니다.
B35: Trường hợp WIP model 716AP đã được nhập kho khác có sản lượng sản xuất thực tế (OUT hoặc LOSS), thì sẽ đánh giá WIP cuối kỳ bằng cách chia thành trước PL và sau PL.
B36: 해당 재공품의 생산실적이 반영되는 달에 제조원가가 가산 됩니다.
B37: Chi phí sản xuất sẽ được cộng thêm (gia tăng) vào tháng mà sản lượng sản xuất thực tế của WIP đó được phản ánh.
A40: 검토필요 | B40: WIP
B41: Model | C41: BOH | E41: IN | G41: ETC_IN | I41: OUT | K41: ETC_OUT | M41: LOSS | O41: EOH | U41: 단가
C42: 수량 Số lượng | D42: 금액 Số tiền | E42: 수량 Số lượng | F42: 금액 Số tiền | G42: 수량 Số lượng | H42: 금액 Số tiền | I42: 수량 Số lượng | J42: 금액 Số tiền | K42: 수량 Số lượng | L42: 금액 Số tiền | M42: 수량 Số lượng | N42: 금액 Số tiền | O42: 수량(PL전) Số lượng | P42: 금액(PL전) Số tiền | Q42: 수량(PL후) Số lượng | R42: 금액(PL후) Số tiền | S42: 수량(Total) Số lượng | T42: 금액(Total) Số tiền | U42: 금액 Số tiền
B43: 716AP | C43: 10 | D43: 1000 | E43: 38 | F43: 4257 | G43: 10 | I43: 10 | J43: =I43*U43 -> 1194.7727 | O43: 23 | P43: =O43*U43*50% -> 1373.9886 | Q43: 25 | R43: =Q43*U43*90% -> 2688.2386 | S43: =O43+Q43 -> 48 | T43: =P43+R43 -> 4062.2273 | U43: =(D43+F43+H43)/((I43+K43+(O43*50%)+(Q43*90%))) -> 119.47727
B46: PRODUCT
B47: Model | C47: BOH | E47: IN | G47: ETC_IN | I47: OUT | K47: ETC_OUT | M47: LOSS | O47: EOH | Q47: 단가
C48: 수량 Số lượng | D48: 금액 Số tiền | E48: 수량 Số lượng | F48: 금액 Số tiền | G48: 수량 Số lượng | H48: 금액 Số tiền | I48: 수량 Số lượng | J48: 금액 Số tiền | K48: 수량 Số lượng | L48: 금액 Số tiền | M48: 수량 Số lượng | N48: 금액 Số tiền | O48: 수량 Số lượng | P48: 금액 Số tiền | Q48: 금액 Số tiền
B49: 716AP | E49: =I43 -> 10 | F49: =J43 -> 1194.7727 | L49: =K49*Q49 -> 0 | N49: =M49*Q49 -> 0 | O49: =C49+E49+G49-I49-K49-M49 -> 10 | P49: =O49*Q49 -> 1194.7727 | Q49: =(D49+F49+H49)/(C49+E49+G49) -> 119.47727
B52: PRODUCT - RE SORTING
B53: Model | C53: BOH | E53: IN | G53: ETC_IN | I53: OUT | K53: ETC_OUT | M53: LOSS | O53: EOH | Q53: 단가
C54: 수량 Số lượng | D54: 금액 Số tiền | E54: 수량 Số lượng | F54: 금액 Số tiền | G54: 수량 Số lượng | H54: 금액 Số tiền | I54: 수량 Số lượng | J54: 금액 Số tiền | K54: 수량 Số lượng | L54: 금액 Số tiền | M54: 수량 Số lượng | N54: 금액 Số tiền | O54: 수량 Số lượng | P54: 금액 Số tiền | Q54: 금액 Số tiền
B55: 716AP | E55: 10 | F55: =F49 -> 1194.7727 | K55: 10 | L55: =K55*Q55 -> 1194.7727 | N55: =M55*Q55 -> 0 | O55: =C55+E55+G55-I55-K55-M55 -> 0 | P55: =O55*Q55 -> 0 | Q55: =(D55+F55+H55)/(C55+E55+G55) -> 119.47727
B58: WIP - RE SORTING
B59: Model | C59: BOH | E59: IN | G59: ETC_IN | I59: OUT | K59: ETC_OUT | M59: LOSS | O59: EOH
C60: 수량 Số lượng | D60: 금액 Số tiền | E60: 수량 Số lượng | F60: 금액 Số tiền | G60: 수량 Số lượng | H60: 금액 Số tiền | I60: 수량 Số lượng | J60: 금액 Số tiền | K60: 수량 Số lượng | L60: 금액 Số tiền | M60: 수량 Số lượng | N60: 금액 Số tiền | O60: 수량(PL전) Số lượng | P60: 금액(PL전) Số tiền | Q60: 수량(PL후) Số lượng | R60: 금액(PL후) Số tiền | S60: 수량(Total) Số lượng | T60: 금액(Total) Số tiền
B61: 716AP | G61: 10 | H61: =L55 -> 1194.7727
A64: 46235 | B64: * R/S R/W 협의사항
B65: 모든 R/S, R/W에 대해 아래와 같이 정의한다.
B66: Định nghĩa tất cả các R/S, R/W như sau
B67: R/S, R/W에 대해 제품 기타출고 금액은 기초 제품 단가를 활용한다.
B68: Đối với R/S, R/W, số tiền xuất kho khác của thành phẩm sử dụng đơn giá đầu kỳ của thành phẩm
B69: -제품 기초수량/금액 ≥ 기타출고(R/S, R/W) 수량 인 경우 전액을 기초금액에서 출고 시킨다.
B70: - Trường hợp số lượng/số tiền đầu kỳ của thành phẩm ≥ số lượng xuất kho khác (R/S, R/W), thì xuất kho toàn bộ số tiền từ số tiền đầu kỳ.
B71: -제품 기초수량/금액 < 기타출고(R/S, R/W) 수량 인 경우 기초금액에서 출고 시키되 기초금액을 초과 한 경우 금액은 출고하지 않는다.
B72: - Trường hợp số lượng/số tiền đầu kỳ của thành phẩm < số lượng xuất kho khác (R/S, R/W), thì xuất kho từ số tiền đầu kỳ, nhưng phần số tiền vượt quá số tiền đầu kỳ thì không xuất kho.
A74: Case1 | B74: BOH ≥ ETC_OUT
B75: 제품 (Product)
B76: 모델 | C76: 기초(BOH) | E76: 입고(IN) | G76: 기타입고(ETC IN) | I76: 출고(OUT) | K76: 기타출고(ETC OUT) | M76: 기타출고(ETC OUT) | O76: 로스(LOSS) | Q76: 재고(EOH) | S76: 단가
C77: 수량 | D77: 금액 | E77: 수량 | F77: 금액 | G77: 수량 | H77: 금액 | I77: 수량 | J77: 금액 | K77: 수량 | L77: 금액 | M77: 수량 | N77: 금액 | O77: 수량 | P77: 금액 | Q77: 수량 | R77: 금액
B78: 716AP | C78: 5 | D78: 500 | F78: 0 | K78: 3 | L78: 300 | Q78: =C78+E78+G78-I78-K78-O78 -> 2 | R78: =D78+F78+H78-J78-L78-P78 -> 200 | S78: =(D78+F78+H78)/(C78+E78+G78) -> 100
A80: Case2 | B80: BOH < ETC_OUT
B81: 제품 (Product)
B82: 모델 | C82: 기초(BOH) | E82: 입고(IN) | G82: 기타입고(ETC IN) | I82: 출고(OUT) | K82: 기타출고(ETC OUT) | M82: 기타출고(ETC OUT) | O82: 로스(LOSS) | Q82: 재고(EOH) | S82: 단가
C83: 수량 | D83: 금액 | E83: 수량 | F83: 금액 | G83: 수량 | H83: 금액 | I83: 수량 | J83: 금액 | K83: 수량 | L83: 금액 | M83: 수량 | N83: 금액 | O83: 수량 | P83: 금액 | Q83: 수량 | R83: 금액
B84: 716AP | C84: 1 | D84: 100 | F84: 0 | K84: 3 | L84: 100 | Q84: =C84+E84+G84-I84-K84-O84 -> -2 | R84: =D84+F84+H84-J84-L84-P84 -> 0 | S84: =(D84+F84+H84)/(C84+E84+G84) -> 100
A86: Case2-1 | B86: BOH < ETC_OUT
B87: 제품 (Product)
B88: 모델 | C88: 기초(BOH) | E88: 입고(IN) | G88: 기타입고(ETC IN) | I88: 출고(OUT) | K88: 기타출고(ETC OUT) | M88: 기타출고(ETC OUT) | O88: 로스(LOSS) | Q88: 재고(EOH) | S88: 단가
C89: 수량 | D89: 금액 | E89: 수량 | F89: 금액 | G89: 수량 | H89: 금액 | I89: 수량 | J89: 금액 | K89: 수량 | L89: 금액 | M89: 수량 | N89: 금액 | O89: 수량 | P89: 금액 | Q89: 수량 | R89: 금액
B90: 716AP | C90: 0 | D90: 0 | F90: 0 | K90: 3 | L90: 0 | Q90: =C90+E90+G90-I90-K90-O90 -> -3 | R90: =D90+F90+H90-J90-L90-P90 -> 0 | S90: =(D90+F90+H90)/(C90+E90+G90) -> #DIV/0!
B92: * Case2와 Case3에서 재고수량이 마이너스가 뜨는 것은 재공품 출고 (제품 입고) 실적을 제외하였기 때문에 마이너스가 보이지만, 실제로는 재공품을 생산완료 후 입고처리를 하기에 재고 산식에 오류는 발생하지 않음.
B93: * Ở Case 2 và Case 3, việc số lượng tồn kho hiển thị âm là do đã loại trừ thành tích xuất kho WIP (nhập kho thành phẩm), nên hiển thị âm, nhưng thực tế thì WIP được xử lý nhập kho sau khi hoàn thành sản xuất, nên công thức tồn kho không phát sinh lỗi.

Sheet 4
B2: 재고자산 종류 | D2: 재공품
B3: 구분 | D3: 기타입고
B4: 항목명 | D4: 반제품 입고
B6: 정의 : USC INPUT이 아닌 다른 경로로 공정 중간으로 재공품이 입고 된 경우
B7: Định nghĩa: Trường hợp WIP (sản phẩm dở dang) được nhập kho vào giữa quy trình sản xuất thông qua con đường khác, không phải USC INPUT
B9: 아래와 같은 케이스가 발생할 수 있으며 아래와 같이 처리한다. (모델, 수량, 금액은 예시입니다.)
B10: Có thể phát sinh trường hợp như dưới đây, và được xử lý như sau. (Model, số lượng, số tiền chỉ là ví dụ minh họa.)
B12: 6월 (Tháng 6) - WIP | G12: 반제품 입고
B13: Model | C13: BOH | E13: IN | G13: ETC_IN | I13: OUT | K13: ETC_OUT | M13: LOSS | O13: EOH
C14: 수량 Số lượng | D14: 금액 Số tiền | E14: 수량 Số lượng | F14: 금액 Số tiền | G14: 수량 Số lượng | H14: 금액 Số tiền | I14: 수량 Số lượng | J14: 금액 Số tiền | K14: 수량 Số lượng | L14: 금액 Số tiền | M14: 수량 Số lượng | N14: 금액 Số tiền | O14: 수량 Số lượng | P14: 금액 Số tiền
B15: 716AP | C15: 0 | D15: 0 | E15: 0 | F15: 0 | G15: 10 | H15: 150 | I15: 0 | J15: 0 | K15: 0 | L15: 0 | M15: 0 | N15: 0 | O15: =C15+E15+G15-I15-K15-M15 -> 10 | P15: =D15+F15+H15-J15-L15-N15 -> 150
B16: 06월 DWKR로 부터 초반 공정을 진행 한 재공품을 수입해 후공정을 진행하는 경우, 재공품의 기타입고로 공정에 투입한다. (수량과 금액은 Invoice에 따르며, 10개를 150$에 수입했다고 가정)
B17: Trường hợp trong Tháng 06, nhập khẩu WIP đã được thực hiện công đoạn đầu từ DWKR và tiến hành công đoạn sau, thì đưa vào quy trình sản xuất thông qua nhập kho khác của WIP. (Số lượng và số tiền theo Invoice, giả định nhập khẩu 10 sản phẩm với giá 150$)
B19: 기타입고 된 재공품 716AP의 생산실적이 없는 경우 기말 재공평가를 진행하지 않고 기타입고의 금액을 100% 반영 합니다.
B20: Trường hợp WIP model 716AP đã được nhập kho khác không có sản lượng sản xuất thực tế (OUT hoặc LOSS), thì sẽ không tiến hành đánh giá WIP cuối kỳ, mà phản ánh 100% giá trị của khoản nhập kho khác.
B21: 기타입고 된 재공품 716AP의 생산실적이 있는 경우 (OUT or Loss) 기말 재공품의 PL전, 후로 나뉘어 평가합니다.
B22: Trường hợp WIP model 716AP đã được nhập kho khác có sản lượng sản xuất thực tế (OUT hoặc LOSS), thì sẽ đánh giá WIP cuối kỳ bằng cách chia thành trước PL và sau PL.
B23: 해당 재공품의 생산실적이 반영되는 달에 제조원가가 가산 됩니다.
B24: Chi phí sản xuất sẽ được cộng thêm (gia tăng) vào tháng mà sản lượng sản xuất thực tế của WIP đó được phản ánh.
B26: 단, 원장으로 수입되는 경우 원재료로 분류하며 가공～박리(컷팅) 후 들어오는 반제품에 한해 위의 구조를 적용한다.
B27: Tuy nhiên, trường hợp nhập khẩu dưới dạng nguyên tấm (nguyên khổ) thì được phân loại là nguyên vật liệu, và cấu trúc nêu trên chỉ áp dụng đối với bán thành phẩm được đưa vào sau khi đã qua gia công ~ bóc tách (cắt).
A62: 46235 | B62: * R/S R/W 협의사항
B63: 모든 R/S, R/W에 대해 아래와 같이 정의한다.
B64: R/S, R/W에 대해 제품 기타출고 금액은 기초 제품 단가를 활용한다.
B65: -제품 기초수량/금액 ≥ 기타출고(R/S, R/W) 수량 인 경우 전액을 기초금액에서 출고 시킨다.
B66: -제품 기초수량/금액 < 기타출고(R/S, R/W) 수량 인 경우 기초금액에서 출고 시키되 기초금액을 초과 한 경우 금액은 출고하지 않는다.
A68: Case1 | B68: BOH ≥ ETC_OUT
B69: 제품
B70: 모델 | C70: 기초(BOH) | E70: 입고(IN) | G70: 기타입고(ETC IN) | I70: 출고(OUT) | K70: 기타출고(ETC OUT) | M70: 기타출고(ETC OUT) | O70: 로스(LOSS) | Q70: 재고(EOH) | S70: 단가
C71: 수량 | D71: 금액 | E71: 수량 | F71: 금액 | G71: 수량 | H71: 금액 | I71: 수량 | J71: 금액 | K71: 수량 | L71: 금액 | M71: 수량 | N71: 금액 | O71: 수량 | P71: 금액 | Q71: 수량 | R71: 금액
B72: 716AP | C72: 5 | D72: 500 | F72: 0 | K72: 3 | L72: 300 | Q72: =C72+E72+G72-I72-K72-O72 -> 2 | R72: =D72+F72+H72-J72-L72-P72 -> 200 | S72: =(D72+F72+H72)/(C72+E72+G72) -> 100
A74: Case2 | B74: BOH < ETC_OUT
B75: 제품
B76: 모델 | C76: 기초(BOH) | E76: 입고(IN) | G76: 기타입고(ETC IN) | I76: 출고(OUT) | K76: 기타출고(ETC OUT) | M76: 기타출고(ETC OUT) | O76: 로스(LOSS) | Q76: 재고(EOH) | S76: 단가
C77: 수량 | D77: 금액 | E77: 수량 | F77: 금액 | G77: 수량 | H77: 금액 | I77: 수량 | J77: 금액 | K77: 수량 | L77: 금액 | M77: 수량 | N77: 금액 | O77: 수량 | P77: 금액 | Q77: 수량 | R77: 금액
B78: 716AP | C78: 1 | D78: 100 | F78: 0 | K78: 3 | L78: 100 | Q78: =C78+E78+G78-I78-K78-O78 -> -2 | R78: =D78+F78+H78-J78-L78-P78 -> 0 | S78: =(D78+F78+H78)/(C78+E78+G78) -> 100
A80: Case2-1 | B80: BOH < ETC_OUT
B81: 제품
B82: 모델 | C82: 기초(BOH) | E82: 입고(IN) | G82: 기타입고(ETC IN) | I82: 출고(OUT) | K82: 기타출고(ETC OUT) | M82: 기타출고(ETC OUT) | O82: 로스(LOSS) | Q82: 재고(EOH) | S82: 단가
C83: 수량 | D83: 금액 | E83: 수량 | F83: 금액 | G83: 수량 | H83: 금액 | I83: 수량 | J83: 금액 | K83: 수량 | L83: 금액 | M83: 수량 | N83: 금액 | O83: 수량 | P83: 금액 | Q83: 수량 | R83: 금액
B84: 716AP | C84: 0 | D84: 0 | F84: 0 | K84: 3 | L84: 0 | Q84: =C84+E84+G84-I84-K84-O84 -> -3 | R84: =D84+F84+H84-J84-L84-P84 -> 0 | S84: =(D84+F84+H84)/(C84+E84+G84) -> #DIV/0!
B86: * Case2와 Case3에서 재고수량이 마이너스가 뜨는 것은 재공품 출고 (제품 입고) 실적을 제외하였기 때문에 마이너스가 보이지만, 실제로는 재공품을 생산완료 후 입고처리를 하기에 재고 산식에 오류는 발생하지 않음.

Sheet 5
B2: 재고자산 종류 | D2: 재공품
B3: 구분 | D3: 기타출고
B4: 항목명 | D4: CODE변경
B6: 정의 : 공정 생산 중 최초 투입 된 모델에서 다른 모델로 생산 변경을 의미한다.
B7: Định nghĩa: Là việc thay đổi sản xuất từ model được đưa vào ban đầu trong quá trình sản xuất sang model khác.
B9: 아래와 같이 2가지 케이스가 발생할 수 있으며 각각 아래와 같이 처리한다. (모델, 수량, 금액은 예시입니다.)
B10: Có thể phát sinh 2 trường hợp như dưới đây, và mỗi trường hợp được xử lý như sau. (Model, số lượng, số tiền chỉ là ví dụ minh họa.)
A12: ① | B12: 전월 투입한 모델에 대해(기초 재공) 당월 다른 모델로 생산 변경 된 경우
A13: ① | B13: Trường hợp model đã đưa vào sản xuất từ tháng trước (WIP đầu kỳ) được thay đổi sang model khác trong tháng này
B14: 6월 (Tháng 6) - WIP
B15: Model | C15: BOH | E15: IN | G15: ETC_IN | I15: OUT | K15: ETC_OUT | M15: LOSS | O15: EOH
C16: 수량 Số lượng | D16: 금액 Số tiền | E16: 수량 Số lượng | F16: 금액 Số tiền | G16: 수량 Số lượng | H16: 금액 Số tiền | I16: 수량 Số lượng | J16: 금액 Số tiền | K16: 수량 Số lượng | L16: 금액 Số tiền | M16: 수량 Số lượng | N16: 금액 Số tiền | O16: 수량 Số lượng | P16: 금액 Số tiền
B17: 716AP | C17: 0 | D17: 0 | E17: 100 | F17: 100 | G17: 0 | H17: 0 | I17: 0 | J17: 0 | K17: 0 | L17: 0 | M17: 0 | N17: 0 | O17: =C17+E17+G17-I17-K17-M17 -> 100 | P17: =D17+F17+H17-J17-L17-N17 -> 100
B18: 06월 716AP 모델에 생산투입을 100개 하였고, 제조원가가 100$ 배부 된 경우, 그리고 모든 수량이 재공 재고로 남아 있는 경우 위와 같이 표현이 됩니다.
B19: Trường hợp trong Tháng 06, đã đưa vào sản xuất 100 sản phẩm model 716AP, chi phí sản xuất được phân bổ là 100$, và toàn bộ số lượng vẫn còn tồn kho dưới dạng sản phẩm dở dang (WIP), thì sẽ được thể hiện như trên.
B21: 7월 (Tháng 7) - WIP | G21: CODE변경 | K21: CODE변경
B22: Model | C22: BOH | E22: IN | G22: ETC_IN | I22: OUT | K22: ETC_OUT | M22: LOSS | O22: EOH
C23: 수량 Số lượng | D23: 금액 Số tiền | E23: 수량 Số lượng | F23: 금액 Số tiền | G23: 수량 Số lượng | H23: 금액 Số tiền | I23: 수량 Số lượng | J23: 금액 Số tiền | K23: 수량 Số lượng | L23: 금액 Số tiền | M23: 수량 Số lượng | N23: 금액 Số tiền | O23: 수량 Số lượng | P23: 금액 Số tiền
B24: 716AP | C24: 100 | D24: 100 | E24: 0 | F24: 0 | G24: 0 | H24: 0 | I24: 0 | J24: 0 | K24: 40 | L24: 40 | M24: 0 | N24: 0 | O24: =C24+E24+G24-I24-K24-M24 -> 60 | P24: =D24+F24+H24-J24-L24-N24 -> 60
B25: 999KP | C25: 0 | D25: 0 | E25: 0 | F25: 0 | G25: 40 | H25: 40 | I25: 0 | J25: 0 | K25: 0 | L25: 0 | M25: 0 | N25: 0 | O25: =C25+E25+G25-I25-K25-M25 -> 40 | P25: =D25+F25+H25-J25-L25-N25 -> 40
B26: 07월 999KP 모델 생산에 716AP의 기초재공 수량을 40개 CODE 변경 한 경우 위와 같이 표현 됩니다.
B27: Trường hợp trong Tháng 07, thay đổi CODE 40 sản phẩm WIP đầu kỳ của model 716AP sang sản xuất model 999KP, thì sẽ được thể hiện như trên.
B29: 또한 CODE변경 된 999KP의 경우 생산량이 없는 경우 ( OUT or LOSS) 기말 재공평가를 진행하지 않고 기타입고의 금액을 100% 반영 합니다.
B30: Ngoài ra, đối với model 999KP đã được thay đổi CODE, trong trường hợp không có sản lượng sản xuất (OUT hoặc LOSS), sẽ không tiến hành đánh giá WIP cuối kỳ, mà phản ánh 100% giá trị của khoản nhập kho khác (Nhập kho khác).
B31: 만약 CODE변경 된 999KP가 생산량이 있는 경우 (OUT or Loss) 기말 재공품의 PL전, 후로 나뉘어 평가합니다.
B32: Nếu model 999KP đã được thay đổi CODE có phát sinh sản lượng sản xuất (OUT hoặc LOSS), thì sẽ đánh giá WIP cuối kỳ bằng cách chia thành trước PL và sau PL.
A34: ② | B34: 당월 투입한 모델에 대해, 다른 모델로 생산 변경 된 경우
A35: ② | B35: Trường hợp model đã đưa vào sản xuất trong tháng này được thay đổi sang model khác
B36: 7월 (Tháng 7) - WIP
B37: Model | C37: BOH | E37: IN | G37: ETC_IN | I37: OUT | K37: ETC_OUT | M37: LOSS | O37: EOH
C38: 수량 Số lượng | D38: 금액 Số tiền | E38: 수량 Số lượng | F38: 금액 Số tiền | G38: 수량 Số lượng | H38: 금액 Số tiền | I38: 수량 Số lượng | J38: 금액 Số tiền | K38: 수량 Số lượng | L38: 금액 Số tiền | M38: 수량 Số lượng | N38: 금액 Số tiền | O38: 수량 Số lượng | P38: 금액 Số tiền
B39: 716AP | D39: 0 | E39: 100 | F39: 100 | G39: 0 | H39: 0 | I39: 0 | J39: 0 | K39: 0 | L39: 0 | M39: 0 | N39: 0 | O39: =C39+E39+G39-I39-K39-M39 -> 100 | P39: =D39+F39+H39-J39-L39-N39 -> 100
B40: 07월에 716AP 모델에 100개 생산투입을 하였고, 제조원가가 100$ 배부 된 경우. (재공 재고는 무시하고 IN의 숫자만 확인 해주십시요)
B41: Trường hợp trong Tháng 07, đã đưa vào sản xuất 100 sản phẩm model 716AP, và chi phí sản xuất được phân bổ là 100$. (Vui lòng bỏ qua tồn kho WIP, chỉ kiểm tra số liệu IN.)
B43: 7월 (Tháng 7) - WIP
B44: Model | C44: BOH | E44: IN | G44: ETC_IN | I44: OUT | K44: ETC_OUT | M44: LOSS | O44: EOH
C45: 수량 Số lượng | D45: 금액 Số tiền | E45: 수량 Số lượng | F45: 금액 Số tiền | G45: 수량 Số lượng | H45: 금액 Số tiền | I45: 수량 Số lượng | J45: 금액 Số tiền | K45: 수량 Số lượng | L45: 금액 Số tiền | M45: 수량 Số lượng | N45: 금액 Số tiền | O45: 수량 Số lượng | P45: 금액 Số tiền
B46: 716AP | D46: 0 | E46: 60 | F46: 60 | G46: 0 | H46: 0 | I46: 0 | J46: 0 | K46: 0 | L46: 0 | M46: 0 | N46: 0 | O46: =C46+E46+G46-I46-K46-M46 -> 60 | P46: =D46+F46+H46-J46-L46-N46 -> 60
B47: 999KP | D47: 0 | E47: 40 | F47: 40 | G47: 0 | H47: 0 | I47: 0 | J47: 0 | K47: 0 | L47: 0 | M47: 0 | N47: 0 | O47: =C47+E47+G47-I47-K47-M47 -> 40 | P47: =D47+F47+H47-J47-L47-N47 -> 40
B48: 당월 투입분에 대해서는 기타출고 → 기타입고가 아닌, 투입 자체의 수량을 변경 된 모델에 적용한다
B49: Đối với phần đưa vào sản xuất trong tháng này, không áp dụng Xuất kho khác → Nhập kho khác, mà áp dụng trực tiếp số lượng đưa vào sản xuất (input) cho model đã được thay đổi.
A51: 46235 | B51: MES, ERP, 구매그룹(영업판매) 파트에서 추가적인 검토사항이 확인되어 CMS 구축 시 컬럼만 신규 생성 후 로직과 데이터 반영은 추후에 진행

Sheet 6
B2: 재고자산 종류 | D2: 재공품
B3: 구분 | D3: 기타출고
B4: 항목명 | D4: 반제품 출고(유상)
B6: 정의 : 공정이 완료되지 않은 재공품을 유상으로 매출하는 경우를 의미한다.
B7: Định nghĩa: Là trường hợp bán có thu tiền (bán hàng thu tiền) đối với WIP (sản phẩm dở dang) chưa hoàn thành quy trình sản xuất.
B9: 아래와 같은 케이스가 발생할 수 있으며 아래와 같이 처리한다. (모델, 수량, 금액은 예시입니다.)
B10: Có thể phát sinh trường hợp như dưới đây, và được xử lý như sau. (Model, số lượng, số tiền chỉ là ví dụ minh họa.)
B12: 재공품 모델에 대해서 공정을 완료하지 않고, 반제품의 형태로 출고를 하는 경우
B13: Trường hợp WIP model chưa hoàn thành quy trình sản xuất, và được xuất kho dưới dạng bán thành phẩm
B14: 6월 (Tháng 6) - WIP
B15: Model | C15: BOH | E15: IN | G15: ETC_IN | I15: OUT | K15: ETC_OUT | O15: LOSS | Q15: EOH
C16: 수량 Số lượng | D16: 금액 Số tiền | E16: 수량 Số lượng | F16: 금액 Số tiền | G16: 수량 Số lượng | H16: 금액 Số tiền | I16: 수량 Số lượng | J16: 금액 Số tiền | K16: 수량(PL전) Số lượng | L16: 금액(PL전) Số tiền | M16: 수량(PL후) Số lượng | N16: 금액(PL후) Số tiền | O16: 수량 Số lượng | P16: 금액 Số tiền | Q16: 수량 Số lượng | R16: 금액 Số tiền
B17: 716AP | C17: 50 | D17: 50 | E17: 100 | F17: 100 | G17: 0 | H17: 0 | I17: 0 | J17: 0 | K17: 10 | L17: 5 | M17: 20 | N17: 18 | O17: 0 | P17: 0 | Q17: =C17+E17+G17-I17-K17-M17-O17 -> 120 | R17: =D17+F17+H17-J17-L17-N17-P17 -> 127
B18: 재공품의 반제품 출고 시 해당 재공품의 위치(PL 전, 후)에 따라 출고 되는 금액이 다르게 적용됩니다.
B19: Khi xuất kho bán thành phẩm của WIP, số tiền xuất kho sẽ được áp dụng khác nhau tùy theo vị trí (trước PL hay sau PL) của WIP đó.
B20: 재공품 단가 X 출고수량 X PL 전(50%)
B21: Đơn giá WIP X Số lượng xuất kho X Trước PL (50%)
B22: 재공품 단가 X 출고수량 X PL 후(90%)
B23: Đơn giá WIP X Số lượng xuất kho X Sau PL (90%)
B24: 6월 (Tháng 6) - Product
B25: Model | C25: BOH | E25: IN | G25: ETC_IN | I25: OUT | K25: ETC_OUT | M25: LOSS | O25: EOH
C26: 수량 Số lượng | D26: 금액 Số tiền | E26: 수량 Số lượng | F26: 금액 Số tiền | G26: 수량 Số lượng | H26: 금액 Số tiền | I26: 수량 Số lượng | J26: 금액 Số tiền | K26: 수량 Số lượng | L26: 금액 Số tiền | M26: 수량 Số lượng | N26: 금액 Số tiền | O26: 수량 Số lượng | P26: 금액 Số tiền
B27: 716AP | C27: 0 | D27: 0 | E27: 0 | F27: 0 | G27: =K17+M17 -> 30 | H27: =L17+N17 -> 23 | I27: 30 | J27: 23 | K27: 0 | L27: 0 | M27: 0 | N27: 0 | O27: =C27+E27+G27-I27-K27-M27 -> 0 | P27: =D27+F27+H27-J27-L27-N27 -> 0
B28: 출고 된 수량과 금액은 제품의 기타입고로 그대로 입고처리 됩니다.
B29: Số lượng và số tiền đã xuất kho sẽ được xử lý nhập kho nguyên trạng dưới dạng nhập kho khác của thành phẩm.
A31: 협의필요 | B31: 반제품 출고를 위한 전제조건으로 반제품 출고되는 재공품의 위치가 어디인지 확인이 필요합니다. (PL 전, 후) - IS&S팀 협의 필요사항
B32: Với tư cách là điều kiện tiên quyết để xuất kho bán thành phẩm, cần xác nhận vị trí của WIP được xuất kho dưới dạng bán thành phẩm (trước PL hay sau PL) - Nội dung cần trao đổi với đội IS&S
B33: 만약, 기타출고되는 재공품의 위치(PL전, 후)를 구할 수 없다면 아래와 같은 하나의 대안을 제시합니다.
B34: Nếu không thể xác định được vị trí (trước PL hay sau PL) của WIP được xuất kho khác, thì đề xuất một phương án thay thế như sau.
B36: 평균진척률 = | D36: (PL전 수량×50%)+(PL후 수량×90%)​ | I36: (Số lượng trước PL × 50%) + (Số lượng sau PL × 90%)
B37: Tỷ lệ tiến độ bình quân | D37: PL전 수량+PL후 수량 | I37: (Số lượng trước PL + Số lượng sau PL)
A40: 46235 | B40: 재공품의 기타출고에 대해 공정의 진척도에 따른 수량 구분 (PL 전, PL 후) 및 데이터 재공 협의 완료
B41: Đã hoàn thành thảo luận về việc phân loại số lượng theo tiến độ quy trình (trước PL, sau PL) đối với Xuất kho khác của WIP, và cung cấp dữ liệu
B42: 제품의 입고금액은 재공품 기타출고의 수량과 금액을 모두 더하여 처리한다. (PL전 + PL후)
B43: Số tiền nhập kho của thành phẩm được xử lý bằng cách cộng tất cả số lượng và số tiền của Xuất kho khác từ WIP (trước PL + sau PL).

Sheet 7
B2: 재고자산 종류 | D2: 재공품
B3: 구분 | D3: 기타출고
B4: 항목명 | D4: 반제품 출고(무상)
B6: 정의 : 공정이 완료되지 않은 재공품을 무상으로 매출하는 경우를 의미한다.
B7: Định nghĩa: Là trường hợp bán có thu tiền (bán hàng thu tiền) đối với WIP (sản phẩm dở dang) chưa hoàn thành quy trình sản xuất.
B9: 아래와 같은 케이스가 발생할 수 있으며 아래와 같이 처리한다. (모델, 수량, 금액은 예시입니다.)
B10: Có thể phát sinh trường hợp như dưới đây, và được xử lý như sau. (Model, số lượng, số tiền chỉ là ví dụ minh họa.)
B12: 재공품 모델에 대해서 공정을 완료하지 않고, 반제품의 형태로 출고를 하는 경우
B13: Trường hợp WIP model chưa hoàn thành quy trình sản xuất, và được xuất kho dưới dạng bán thành phẩm
B14: 6월 (Tháng 6) - WIP
B15: Model | C15: BOH | E15: IN | G15: ETC_IN | I15: OUT | K15: ETC_OUT | O15: LOSS | Q15: EOH
C16: 수량 Số lượng | D16: 금액 Số tiền | E16: 수량 Số lượng | F16: 금액 Số tiền | G16: 수량 Số lượng | H16: 금액 Số tiền | I16: 수량 Số lượng | J16: 금액 Số tiền | K16: 수량(PL전) Số lượng | L16: 금액(PL전) Số tiền | M16: 수량(PL후) Số lượng | N16: 금액(PL후) Số tiền | O16: 수량 Số lượng | P16: 금액 Số tiền | Q16: 수량 Số lượng | R16: 금액 Số tiền
B17: 716AP | C17: 50 | D17: 50 | E17: 100 | F17: 100 | G17: 0 | H17: 0 | I17: 0 | J17: 0 | K17: 10 | L17: 5 | M17: 20 | N17: 18 | O17: 0 | P17: 0 | Q17: =C17+E17+G17-I17-K17-M17-O17 -> 120 | R17: =D17+F17+H17-J17-L17-N17-P17 -> 127
B18: 재공품의 반제품 출고 시 해당 재공품의 위치(PL 전, 후)에 따라 출고 되는 금액이 다르게 적용됩니다.
B19: Khi xuất kho bán thành phẩm của WIP, số tiền xuất kho sẽ được áp dụng khác nhau tùy theo vị trí (trước PL hay sau PL) của WIP đó.
B20: 재공품 단가 X 출고수량 X PL 전(50%)
B21: Đơn giá WIP X Số lượng xuất kho X Trước PL (50%)
B22: 재공품 단가 X 출고수량 X PL 후(90%)
B23: Đơn giá WIP X Số lượng xuất kho X Sau PL (90%)
B24: 6월 (Tháng 6) - Product
B25: Model | C25: BOH | E25: IN | G25: ETC_IN | I25: OUT | K25: ETC_OUT | M25: LOSS | O25: EOH
C26: 수량 Số lượng | D26: 금액 Số tiền | E26: 수량 Số lượng | F26: 금액 Số tiền | G26: 수량 Số lượng | H26: 금액 Số tiền | I26: 수량 Số lượng | J26: 금액 Số tiền | K26: 수량 Số lượng | L26: 금액 Số tiền | M26: 수량 Số lượng | N26: 금액 Số tiền | O26: 수량 Số lượng | P26: 금액 Số tiền
B27: 716AP | C27: 0 | D27: 0 | E27: 0 | F27: 0 | G27: =K17+M17 -> 30 | H27: =L17+N17 -> 23 | I27: 30 | J27: 23 | K27: 0 | L27: 0 | M27: 0 | N27: 0 | O27: =C27+E27+G27-I27-K27-M27 -> 0 | P27: =D27+F27+H27-J27-L27-N27 -> 0
B28: 출고 된 수량과 금액은 제품의 기타입고로 그대로 입고처리 됩니다.
B29: Số lượng và số tiền đã xuất kho sẽ được xử lý nhập kho nguyên trạng dưới dạng nhập kho khác của thành phẩm.
A31: 협의필요 | B31: 반제품 출고를 위한 전제조건으로 반제품 출고되는 재공품의 위치가 어디인지 확인이 필요합니다. (PL 전, 후) - IS&S팀 협의 필요사항
B32: Với tư cách là điều kiện tiên quyết để xuất kho bán thành phẩm, cần xác nhận vị trí của WIP được xuất kho dưới dạng bán thành phẩm (trước PL hay sau PL) - Nội dung cần trao đổi với đội IS&S
B33: 만약, 기타출고되는 재공품의 위치(PL전, 후)를 구할 수 없다면 아래와 같은 하나의 대안을 제시합니다.
B34: Nếu không thể xác định được vị trí (trước PL hay sau PL) của WIP được xuất kho khác, thì đề xuất một phương án thay thế như sau.
B36: 평균진척률 = | D36: (PL전 수량×50%)+(PL후 수량×90%)​ | I36: (Số lượng trước PL × 50%) + (Số lượng sau PL × 90%)
B37: Tỷ lệ tiến độ bình quân | D37: PL전 수량+PL후 수량 | I37: (Số lượng trước PL + Số lượng sau PL)
A40: 46235 | B40: 재공품의 기타출고에 대해 공정의 진척도에 따른 수량 구분 (PL 전, PL 후) 및 데이터 재공 협의 완료
B41: Đã hoàn thành thảo luận về việc phân loại số lượng theo tiến độ quy trình (trước PL, sau PL) đối với Xuất kho khác của WIP, và cung cấp dữ liệu

Sheet 8
B2: 재고자산 종류 | D2: 제품
B3: 구분 | D3: 기타입고
B4: 항목명 | D4: RMA
B6: 정의 : 매출된 제품에 대해 고객의 반품으로 회사에 재입고 되는 경우를 의미한다.
B7: Định nghĩa: Là trường hợp bán có thu tiền (bán hàng thu tiền) đối với WIP (sản phẩm dở dang) chưa hoàn thành quy trình sản xuất.
B9: 아래와 같은 케이스가 발생할 수 있으며 아래와 같이 처리한다. (모델, 수량, 금액은 예시입니다.)
B10: Có thể phát sinh trường hợp như dưới đây, và được xử lý như sau. (Model, số lượng, số tiền chỉ là ví dụ minh họa.)
B12: 판매가 완료 된 제품에 대해서 고객으로부터 반품 받는 경우
B13: Trường hợp nhận hàng trả lại từ khách hàng đối với sản phẩm đã hoàn tất bán hàng
B15: 6월 (Tháng 6) - Product
B16: Model | C16: BOH | E16: IN | G16: ETC_IN | I16: OUT | K16: ETC_OUT | M16: LOSS | O16: EOH
C17: 수량 Số lượng | D17: 금액 Số tiền | E17: 수량 Số lượng | F17: 금액 Số tiền | G17: 수량 Số lượng | H17: 금액 Số tiền | I17: 수량 Số lượng | J17: 금액 Số tiền | K17: 수량 Số lượng | L17: 금액 Số tiền | M17: 수량 Số lượng | N17: 금액 Số tiền | O17: 수량 Số lượng | P17: 금액 Số tiền
B18: 716AP | C18: 0 | D18: 0 | E18: 0 | F18: 0 | G18: 100 | H18: 6000 | I18: 0 | J18: 0 | K18: 0 | L18: 0 | M18: 0 | N18: 0 | O18: =C18+E18+G18-I18-K18-M18 -> 100 | P18: =D18+F18+H18-J18-L18-N18 -> 6000
B19: 기존에 판매한 716AP 제품에 대해서 6월에 100개 (매출원가 6,000$)를 반품 받은 경우 위와 같이 표기 됩니다.
B20: Trường hợp trong Tháng 6, nhận lại 100 sản phẩm 716AP đã bán trước đó (giá vốn hàng bán 6.000$) do khách hàng trả lại, thì sẽ được thể hiện như trên.
A22: 확인필요 | B22: 국내의 경우 반품되는 제품이 [거래명세서입력] 화면을 통해 -출고로 처리되어 재고가 증가하는 구조인데, 베트남에서는 어떤식으로 처리되는지 확인이 필요 - IS&S 확인 필요
B23: Trường hợp trong nước (Hàn Quốc), sản phẩm trả lại được xử lý dưới dạng xuất kho âm (-) thông qua màn hình [Nhập thông tin phiếu giao dịch], từ đó làm tăng tồn kho, nhưng cần xác nhận tại Việt Nam được xử lý theo cách nào - Cần xác nhận với đội IS&S
B24: VN ERP는 반품을 통해 처리가 되긴 하지만, 출고의 -로 처리되는 구조는 동일함
B26: 단, EMI > CMS로 전달하는 과정에서 기타입고/기타출고로 재분류 할 예정
B27: * 입고 : ERP - OUT / MES, CMS - ETC_IN
B28: * 출고 : ERP, MES, CMS - ETC_OUT
A30: 확인필요 | B30: 추후에는 ERP의 제품수불부를 사용하지 않는데, 이후에는 CMS에서 제품 반품 금액을 어떻게 산정할건지?
C32: BOH | D32: IN | E32: ETC_In | F32: OUT | G32: EOH
C33: 10 | F33: 10 | G33: =C33+D33-F33 -> 0
C34: 10 | F34: -10 | G34: =C34+D34-F34 -> 20 | H34: AS-IS
C35: 10 | E35: 10 | G35: =C35+D35-F35+E35 -> 20 | H35: TO-BE
C37: 25. 01 | D37: 25. 02 | E37: 25. 03 | F37: 25. 04 | G37: 25. 05 | H37: 25. 06 | I37: 25. 07 | J37: 25. 08 | K37: 25. 09 | L37: 25. 10 | M37: 25. 11 | N37: 25. 12 | O37: 26. 01 | P37: TOTAL
B38: PRODUCT-OUT | C38: 100 | D38: 100 | E38: 100 | F38: 4235 | G38: 7 | H38: 56 | I38: 13 | J38: 89 | K38: 3 | L38: 4981 | M38: 3 | N38: 456 | P38: =SUM(C38:O38) -> 10143
B39: PRODUCT - RETURN | O39: 500
B40: PRODUCT - RETURN | D40: 100 | E40: 100 | H40: 50 | I40: 10 | L40: 240 | P40: =SUM(C40:O40) -> 500 | Q40: 1)
B41: PRODUCT - RETURN | L41: 41 | M41: 3 | N41: 456 | P41: =SUM(C41:O41) -> 500 | Q41: 2)
K44: RMA
B45: 818AP | K45: ERP 필요 데이터
C46: ERP | E46: CMS | J46: 1 | K46: 반품 된 제품 목록(품번)
B47: 25. 01 | C47: 10 | D47: 100 | E47: 10 | F47: 100 | J47: 2 | K47: 반품 된 제품 수량 (제품별/품번)
B48: 25. 02 | C48: 10 | D48: 100 | E48: 10 | F48: 100 | J48: 3 | K48: 반품 된 제품의 최초 판매월
B49: 25. 03 | C49: 10 | D49: 100 | E49: 10 | F49: 100 | J49: 4 | K49: 반품 된 제품의 최초 판매 시 매출원가
B50: 25. 04 | C50: 10 | D50: 100 | E50: 10 | F50: 100 | K50: [수출claim품목조회] 화면
B51: 25. 05 | C51: 10 | D51: 100 | E51: 10 | F51: 100 | K51: BL 날짜 (년/월) 일은 필요 없음
B52: 25. 06 | C52: 10 | D52: 100 | E52: 10 | F52: 100
C53: 수량 | D53: 금액 | E53: 수량 | F53: 금액 | K53: 반품되는 제품은 아래와 같이 분류 됨
A55: 1 | B55: Invoice에 따라 모델명, 수량, 당시매출원가를 확인하여 기타입고 처리하는 방법
B57: I/V (PDF) > 모델/수량/판매월 체크 | K57: I/V 기타입고처리 / OUT
B59: CMS > 로드
B61: CMS > I/V 모델 기준으로 과거 판매월을 찾아가서 매출원가 추출 (여러월)
B63: CMS > 당월 제품 기타입고에서 과거 매출원가를 모두 더하여 표기
A65: 2 | B65: 가장 최근 매출원가를 사용하여 기타입고 처리하는 방법
A68: 46235 | B68: RMA 반품(Product return)에 대해, SDV에서 세금계산서가 발행되는 경우로 한정한다.
B69: Đối với hàng trả lại RMA(Product return), giới hạn trong trường hợp hóa đơn thuế (tax invoice) được phát hành từ SDV.
B70: 세금계산서 발행 없이 실물을 교환처리 하는 경우 이 구조에 적용하지 않는다. (ERP에 실적 없는 경우)
B71: Trường hợp xử lý đổi hàng thực tế mà không phát hành hóa đơn thuế thì không áp dụng vào cấu trúc này. (Trường hợp không có thành tích trên ERP)
B72: 반품되는 제품은 [수출Claim품목조회] 화면을 통해 매출이 발생한 모델별, 수량, BL일자, BL일자의 매출원가를 조회하여 판매 당시의 매출원가를 기타입고되는 금액으로 지정한다.
B73: Đối với sản phẩm bị trả lại, tra cứu theo model, số lượng, ngày BL, và giá vốn hàng bán theo ngày BL đã phát sinh doanh thu thông qua màn hình [Tra cứu mặt hàng Claim xuất khẩu], và chỉ định giá vốn hàng bán tại thời điểm bán hàng làm số tiền nhập kho khác.
B74: 단, ERP도입 기준의 판매원가와 / CMS도입 기준의 판매원가는 서로 다른 프로그램에서 조회가 되기에 BL일자에 따라 ERP의 데이터와 CMS의 데이터를 사용하는 구분을 지정한다.
B75: Tuy nhiên, do giá vốn bán hàng theo tiêu chuẩn triển khai ERP và giá vốn bán hàng theo tiêu chuẩn triển khai CMS được tra cứu từ các chương trình khác nhau, nên chỉ định phân loại việc sử dụng dữ liệu của ERP hoặc dữ liệu của CMS tùy theo ngày BL.

Sheet 9
B2: 재고자산 종류 | D2: 제품
B3: 구분 | D3: 기타입고
B4: 항목명 | D4: 반제품 입고(유상)
B6: 정의 : 정상 공정을 거쳐 생산입고가 아닌 공정 중간에 입고되는 재공품이며, 유상매출로 이어지는 경우를 의미한다. (6번 sheet의 제품 기준)
B7: Định nghĩa: Là WIP (sản phẩm dở dang) được nhập kho vào giữa quy trình sản xuất, không phải nhập kho từ sản xuất qua quy trình bình thường, và dẫn đến việc bán hàng thu tiền. (Dựa trên tiêu chuẩn thành phẩm ở sheet số 6)
B9: 아래와 같은 케이스가 발생할 수 있으며 아래와 같이 처리한다. (모델, 수량, 금액은 예시입니다.)
B10: Có thể phát sinh trường hợp như dưới đây, và được xử lý như sau. (Model, số lượng, số tiền chỉ là ví dụ minh họa.)
B12: 재공품 모델에 대해서 공정을 완료하지 않고, 반제품의 형태로 출고를 하는 경우
B13: Trường hợp WIP model chưa hoàn thành quy trình sản xuất, và được xuất kho dưới dạng bán thành phẩm
B14: 6월 (Tháng 6) - WIP
B15: Model | C15: BOH | E15: IN | G15: ETC_IN | I15: OUT | K15: ETC_OUT | O15: LOSS | Q15: EOH
C16: 수량 Số lượng | D16: 금액 Số tiền | E16: 수량 Số lượng | F16: 금액 Số tiền | G16: 수량 Số lượng | H16: 금액 Số tiền | I16: 수량 Số lượng | J16: 금액 Số tiền | K16: 수량(PL전) Số lượng | L16: 금액(PL전) Số tiền | M16: 수량(PL후) Số lượng | N16: 금액(PL후) Số tiền | O16: 수량 Số lượng | P16: 금액 Số tiền | Q16: 수량 Số lượng | R16: 금액 Số tiền
B17: 716AP | C17: 50 | D17: 50 | E17: 100 | F17: 100 | G17: 0 | H17: 0 | I17: 0 | J17: 0 | K17: 10 | L17: 5 | M17: 20 | N17: 18 | O17: 0 | P17: 0 | Q17: =C17+E17+G17-I17-K17-M17-O17 -> 120 | R17: =D17+F17+H17-J17-L17-N17-P17 -> 127
B18: 재공품의 반제품 출고 시 해당 재공품의 위치(PL 전, 후)에 따라 출고 되는 금액이 다르게 적용됩니다.
B19: Khi xuất kho bán thành phẩm của WIP, số tiền xuất kho sẽ được áp dụng khác nhau tùy theo vị trí (trước PL hay sau PL) của WIP đó.
B20: 재공품 단가 X 출고수량 X PL 전(50%)
B21: Đơn giá WIP X Số lượng xuất kho X Trước PL (50%)
B22: 재공품 단가 X 출고수량 X PL 후(90%)
B23: Đơn giá WIP X Số lượng xuất kho X Sau PL (90%)
B24: 6월 (Tháng 6) - Product
B25: Model | C25: BOH | E25: IN | G25: ETC_IN | I25: OUT | K25: ETC_OUT | M25: LOSS | O25: EOH
C26: 수량 Số lượng | D26: 금액 Số tiền | E26: 수량 Số lượng | F26: 금액 Số tiền | G26: 수량 Số lượng | H26: 금액 Số tiền | I26: 수량 Số lượng | J26: 금액 Số tiền | K26: 수량 Số lượng | L26: 금액 Số tiền | M26: 수량 Số lượng | N26: 금액 Số tiền | O26: 수량 Số lượng | P26: 금액 Số tiền
B27: 716AP | C27: 0 | D27: 0 | E27: 0 | F27: 0 | G27: =K17+M17 -> 30 | H27: =L17+N17 -> 23 | I27: 30 | J27: 23 | K27: 0 | L27: 0 | M27: 0 | N27: 0 | O27: =C27+E27+G27-I27-K27-M27 -> 0 | P27: =D27+F27+H27-J27-L27-N27 -> 0
B28: 출고 된 수량과 금액은 제품의 기타입고로 그대로 입고처리 됩니다.
B29: Số lượng và số tiền đã xuất kho sẽ được xử lý nhập kho nguyên trạng dưới dạng nhập kho khác của thành phẩm.
B30: 유상매출과 무상매출은 매출 금액의 유무이지 매출원가는 모두 동일하게 반영됩니다.
B31: Bán hàng thu tiền và bán hàng không thu tiền chỉ khác nhau ở việc có hay không có doanh thu bán hàng, còn giá vốn hàng bán đều được phản ánh giống nhau.
A33: 협의필요 | B33: 반제품 출고를 위한 전제조건으로 반제품 출고되는 재공품의 위치가 어디인지 확인이 필요합니다. (PL 전, 후) - IS&S팀 협의 필요사항
B34: Với tư cách là điều kiện tiên quyết để xuất kho bán thành phẩm, cần xác nhận vị trí của WIP được xuất kho dưới dạng bán thành phẩm (trước PL hay sau PL) - Nội dung cần trao đổi với đội IS&S
B36: 만약, 기타출고되는 재공품의 위치(PL전, 후)를 구할 수 없다면 아래와 같은 하나의 대안을 제시합니다.
B37: Nếu không thể xác định được vị trí (trước PL hay sau PL) của WIP được xuất kho khác, thì đề xuất một phương án thay thế như sau.
B39: 평균진척률 = | D39: (PL전 수량×50%)+(PL후 수량×90%)​ | I39: (Số lượng trước PL × 50%) + (Số lượng sau PL × 90%)
B40: Tỷ lệ tiến độ bình quân | D40: PL전 수량+PL후 수량 | I40: (Số lượng trước PL + Số lượng sau PL)
B42: 제품의 입고금액은 재공품 기타출고의 수량과 금액을 모두 더하여 처리한다. (PL전 + PL후)
B43: Số tiền nhập kho của thành phẩm được xử lý bằng cách cộng tất cả số lượng và số tiền của Xuất kho khác từ WIP (trước PL + sau PL).

Sheet 10
B2: 재고자산 종류 | D2: 제품
B3: 구분 | D3: 기타입고
B4: 항목명 | D4: 반제품 입고(무상)
B6: 정의 : 정상 공정을 거쳐 생산입고가 아닌 공정 중간에 입고되는 재공품이며, 무상매출로 이어지는 경우를 의미한다. (7번 sheet의 제품 기준)
B7: Định nghĩa: Là WIP (sản phẩm dở dang) được nhập kho vào giữa quy trình sản xuất, không phải nhập kho từ sản xuất qua quy trình bình thường, và dẫn đến việc bán hàng không thu tiền. (Dựa trên tiêu chuẩn thành phẩm ở sheet số 7)
B9: 아래와 같은 케이스가 발생할 수 있으며 아래와 같이 처리한다. (모델, 수량, 금액은 예시입니다.)
B10: Có thể phát sinh trường hợp như dưới đây, và được xử lý như sau. (Model, số lượng, số tiền chỉ là ví dụ minh họa.)
B12: 재공품 모델에 대해서 공정을 완료하지 않고, 반제품의 형태로 출고를 하는 경우
B13: Trường hợp WIP model chưa hoàn thành quy trình sản xuất, và được xuất kho dưới dạng bán thành phẩm
B14: 6월 (Tháng 6) - WIP
B15: Model | C15: BOH | E15: IN | G15: ETC_IN | I15: OUT | K15: ETC_OUT | O15: LOSS | Q15: EOH
C16: 수량 Số lượng | D16: 금액 Số tiền | E16: 수량 Số lượng | F16: 금액 Số tiền | G16: 수량 Số lượng | H16: 금액 Số tiền | I16: 수량 Số lượng | J16: 금액 Số tiền | K16: 수량(PL전) Số lượng | L16: 금액(PL전) Số tiền | M16: 수량(PL후) Số lượng | N16: 금액(PL후) Số tiền | O16: 수량 Số lượng | P16: 금액 Số tiền | Q16: 수량 Số lượng | R16: 금액 Số tiền
B17: 716AP | C17: 50 | D17: 50 | E17: 100 | F17: 100 | G17: 0 | H17: 0 | I17: 0 | J17: 0 | K17: 10 | L17: 5 | M17: 20 | N17: 18 | O17: 0 | P17: 0 | Q17: =C17+E17+G17-I17-K17-M17-O17 -> 120 | R17: =D17+F17+H17-J17-L17-N17-P17 -> 127
B18: 재공품의 반제품 출고 시 해당 재공품의 위치(PL 전, 후)에 따라 출고 되는 금액이 다르게 적용됩니다.
B19: Khi xuất kho bán thành phẩm của WIP, số tiền xuất kho sẽ được áp dụng khác nhau tùy theo vị trí (trước PL hay sau PL) của WIP đó.
B20: 재공품 단가 X 출고수량 X PL 전(50%)
B21: Đơn giá WIP X Số lượng xuất kho X Trước PL (50%)
B22: 재공품 단가 X 출고수량 X PL 후(90%)
B23: Đơn giá WIP X Số lượng xuất kho X Sau PL (90%)
B24: 6월 (Tháng 6) - Product
B25: Model | C25: BOH | E25: IN | G25: ETC_IN | I25: OUT | K25: ETC_OUT | M25: LOSS | O25: EOH
C26: 수량 Số lượng | D26: 금액 Số tiền | E26: 수량 Số lượng | F26: 금액 Số tiền | G26: 수량 Số lượng | H26: 금액 Số tiền | I26: 수량 Số lượng | J26: 금액 Số tiền | K26: 수량 Số lượng | L26: 금액 Số tiền | M26: 수량 Số lượng | N26: 금액 Số tiền | O26: 수량 Số lượng | P26: 금액 Số tiền
B27: 716AP | C27: 0 | D27: 0 | E27: 0 | F27: 0 | G27: =K17+M17 -> 30 | H27: =L17+N17 -> 23 | I27: 30 | J27: 23 | K27: 0 | L27: 0 | M27: 0 | N27: 0 | O27: =C27+E27+G27-I27-K27-M27 -> 0 | P27: =D27+F27+H27-J27-L27-N27 -> 0
B28: 출고 된 수량과 금액은 제품의 기타입고로 그대로 입고처리 됩니다.
B29: Số lượng và số tiền đã xuất kho sẽ được xử lý nhập kho nguyên trạng dưới dạng nhập kho khác của thành phẩm.
B30: 유상매출과 무상매출은 매출 금액의 유무이지 매출원가는 모두 동일하게 반영됩니다.
B31: Bán hàng thu tiền và bán hàng không thu tiền chỉ khác nhau ở việc có hay không có doanh thu bán hàng, còn giá vốn hàng bán đều được phản ánh giống nhau.
A33: 협의필요 | B33: 반제품 출고를 위한 전제조건으로 반제품 출고되는 재공품의 위치가 어디인지 확인이 필요합니다. (PL 전, 후) - IS&S팀 협의 필요사항
B34: Với tư cách là điều kiện tiên quyết để xuất kho bán thành phẩm, cần xác nhận vị trí của WIP được xuất kho dưới dạng bán thành phẩm (trước PL hay sau PL) - Nội dung cần trao đổi với đội IS&S
B35: 만약, 기타출고되는 재공품의 위치(PL전, 후)를 구할 수 없다면 아래와 같은 하나의 대안을 제시합니다.
B36: Nếu không thể xác định được vị trí (trước PL hay sau PL) của WIP được xuất kho khác, thì đề xuất một phương án thay thế như sau.
B38: 평균진척률 = | D38: (PL전 수량×50%)+(PL후 수량×90%)​ | I38: (Số lượng trước PL × 50%) + (Số lượng sau PL × 90%)
B39: Tỷ lệ tiến độ bình quân | D39: PL전 수량+PL후 수량 | I39: (Số lượng trước PL + Số lượng sau PL)
B42: 제품의 입고금액은 재공품 기타출고의 수량과 금액을 모두 더하여 처리한다. (PL전 + PL후)
B43: Số tiền nhập kho của thành phẩm được xử lý bằng cách cộng tất cả số lượng và số tiền của Xuất kho khác từ WIP (trước PL + sau PL).

Sheet 11
B2: 재고자산 종류 | D2: 제품
B3: 구분 | D3: 기타출고
B4: 항목명 | D4: Re-Sorting(재검사)
B6: 정의 : 생산완료 된 제품에 대하여 어떠한 사유로 Re-sorting(재검사)를 하는 경우 (2번 sheet의 제품 기준)
B7: Định nghĩa: Trường hợp thực hiện Re-sorting (kiểm tra lại) đối với sản phẩm đã hoàn thành sản xuất vì một lý do nào đó (Dựa trên tiêu chuẩn thành phẩm ở sheet số 2)
B9: 아래와 같은 케이스가 발생할 수 있으며 아래와 같이 처리한다. (모델, 수량, 금액은 예시입니다.)
B10: Có thể phát sinh trường hợp như dưới đây, và được xử lý như sau. (Model, số lượng, số tiền chỉ là ví dụ minh họa.)
B12: 6월 (Tháng 6) - Product
B13: Model | C13: BOH | E13: IN | G13: ETC_IN | I13: OUT | K13: ETC_OUT | M13: LOSS | O13: EOH
C14: 수량 Số lượng | D14: 금액 Số tiền | E14: 수량 Số lượng | F14: 금액 Số tiền | G14: 수량 Số lượng | H14: 금액 Số tiền | I14: 수량 Số lượng | J14: 금액 Số tiền | K14: 수량 Số lượng | L14: 금액 Số tiền | M14: 수량 Số lượng | N14: 금액 Số tiền | O14: 수량 Số lượng | P14: 금액 Số tiền
B15: 716AP | C15: 100 | D15: 100 | E15: 40 | F15: 40 | G15: 0 | H15: 0 | I15: 0 | J15: 0 | K15: 0 | L15: 0 | M15: 0 | N15: 0 | O15: =C15+E15+G15-I15-K15-M15 -> 140 | P15: =D15+F15+H15-J15-L15-N15 -> 140
B16: 06월 716AP 제품에 대해서 100개의 재고가 있고 (단가 1$) 당월 생산입고가 40개가 됐다고 가정한다 (단가 1$)
B17: Giả định trong Tháng 06, model 716AP có tồn kho 100 sản phẩm (đơn giá 1),vaˋtrongthaˊngnaˋycoˊ40sảnphẩmnhậpkhotừsảnxua^ˊt(đơngiaˊ1), và trong tháng này có 40 sản phẩm nhập kho từ sản xuất (đơn giá 1 ),vaˋtrongthaˊngnaˋycoˊ40sảnphẩmnhậpkhotừsảnxua^ˊt(đơngiaˊ1).
B18: 기타출고되는 제품의 단가는 기초단가를 활용한다. 만약 기초수량과 금액이 부족한 경우 8월1일 협의한 내용을 따른다.
B19: Đơn giá của thành phẩm được xuất kho khác sử dụng đơn giá đầu kỳ. Nếu số lượng và số tiền đầu kỳ không đủ, thì tuân theo nội dung đã thỏa thuận vào ngày 1 tháng 8.
B21: 6월 (Tháng 6) - Product | K21: Re-Sorting(재검사)
B22: Model | C22: BOH | E22: IN | G22: ETC_IN | I22: OUT | K22: ETC_OUT | M22: LOSS | O22: EOH
C23: 수량 Số lượng | D23: 금액 Số tiền | E23: 수량 Số lượng | F23: 금액 Số tiền | G23: 수량 Số lượng | H23: 금액 Số tiền | I23: 수량 Số lượng | J23: 금액 Số tiền | K23: 수량 Số lượng | L23: 금액 Số tiền | M23: 수량 Số lượng | N23: 금액 Số tiền | O23: 수량 Số lượng | P23: 금액 Số tiền
B24: 716AP | C24: 100 | D24: 100 | E24: 40 | F24: 40 | G24: 0 | H24: 0 | I24: 0 | J24: 0 | K24: 30 | L24: 30 | M24: 0 | N24: 0 | O24: =C24+E24+G24-I24-K24-M24 -> 110 | P24: =D24+F24+H24-J24-L24-N24 -> 110
B26: 6월 (Tháng 6) - WIP | G26: Re-Sorting(재검사)
B27: Model | C27: BOH | E27: IN | G27: ETC_IN | I27: OUT | K27: ETC_OUT | M27: LOSS | O27: EOH
C28: 수량 Số lượng | D28: 금액 Số tiền | E28: 수량 Số lượng | F28: 금액 Số tiền | G28: 수량 Số lượng | H28: 금액 Số tiền | I28: 수량 Số lượng | J28: 금액 Số tiền | K28: 수량 Số lượng | L28: 금액 Số tiền | M28: 수량 Số lượng | N28: 금액 Số tiền | O28: 수량 Số lượng | P28: 금액 Số tiền
B29: 716AP | C29: 0 | D29: 0 | E29: 0 | F29: 0 | G29: 30 | H29: 30 | I29: 0 | J29: 0 | K29: 0 | L29: 0 | M29: 0 | N29: 0 | O29: =C29+E29+G29-I29-K29-M29 -> 30 | P29: =D29+F29+H29-J29-L29-N29 -> 30
B30: 716AP 제품이 Re-sorting으로 검사를 다시 진행 할 경우, 제품에서 기타출고하여 동일한 수량과 금액을 재공품의 기타입고로 처리한다.
B31: Trường hợp sản phẩm 716AP được kiểm tra lại (tái kiểm) thông qua Re-sorting, thì thực hiện xuất kho khác từ thành phẩm, và xử lý nhập kho khác vào WIP (sản phẩm dở dang) với cùng số lượng và số tiền.
B32: 기타입고 된 재공품 716AP의 생산실적이 없는 경우 기말 재공평가를 진행하지 않고 기타입고의 금액을 100% 반영 합니다.
B33: Trường hợp WIP model 716AP đã được nhập kho khác không có sản lượng sản xuất thực tế (OUT hoặc LOSS), thì sẽ không tiến hành đánh giá WIP cuối kỳ, mà phản ánh 100% giá trị của khoản nhập kho khác.
B34: 기타입고 된 재공품 716AP의 생산실적이 있는 경우 (OUT or Loss) 기말 재공품의 PL전, 후로 나뉘어 평가합니다.
B35: Trường hợp WIP model 716AP đã được nhập kho khác có sản lượng sản xuất thực tế (OUT hoặc LOSS), thì sẽ đánh giá WIP cuối kỳ bằng cách chia thành trước PL và sau PL.
B36: 해당 재공품의 생산실적이 반영되는 달에 제조원가가 가산 됩니다.
B37: Chi phí sản xuất sẽ được cộng thêm (gia tăng) vào tháng mà sản lượng sản xuất thực tế của WIP đó được phản ánh.
A64: 46235 | B64: * R/S R/W 협의사항
B65: 모든 R/S, R/W에 대해 아래와 같이 정의한다.
B66: Định nghĩa tất cả các R/S, R/W như sau
B67: R/S, R/W에 대해 제품 기타출고 금액은 기초 제품 단가를 활용한다.
B68: Đối với R/S, R/W, số tiền xuất kho khác của thành phẩm sử dụng đơn giá đầu kỳ của thành phẩm
B69: -제품 기초수량/금액 ≥ 기타출고(R/S, R/W) 수량 인 경우 전액을 기초금액에서 출고 시킨다.
B70: - Trường hợp số lượng/số tiền đầu kỳ của thành phẩm ≥ số lượng xuất kho khác (R/S, R/W), thì xuất kho toàn bộ số tiền từ số tiền đầu kỳ.
B71: -제품 기초수량/금액 < 기타출고(R/S, R/W) 수량 인 경우 기초금액에서 출고 시키되 기초금액을 초과 한 경우 금액은 출고하지 않는다.
B72: - Trường hợp số lượng/số tiền đầu kỳ của thành phẩm < số lượng xuất kho khác (R/S, R/W), thì xuất kho từ số tiền đầu kỳ, nhưng phần số tiền vượt quá số tiền đầu kỳ thì không xuất kho.
A74: Case1 | B74: BOH ≥ ETC_OUT
B75: 제품 (Product)
B76: 모델 | C76: 기초(BOH) | E76: 입고(IN) | G76: 기타입고(ETC IN) | I76: 출고(OUT) | K76: 기타출고(ETC OUT) | M76: 기타출고(ETC OUT) | O76: 로스(LOSS) | Q76: 재고(EOH) | S76: 단가
C77: 수량 | D77: 금액 | E77: 수량 | F77: 금액 | G77: 수량 | H77: 금액 | I77: 수량 | J77: 금액 | K77: 수량 | L77: 금액 | M77: 수량 | N77: 금액 | O77: 수량 | P77: 금액 | Q77: 수량 | R77: 금액
B78: 716AP | C78: 5 | D78: 500 | F78: 0 | K78: 3 | L78: 300 | Q78: =C78+E78+G78-I78-K78-O78 -> 2 | R78: =D78+F78+H78-J78-L78-P78 -> 200 | S78: =(D78+F78+H78)/(C78+E78+G78) -> 100
A80: Case2 | B80: BOH < ETC_OUT
B81: 제품 (Product)
B82: 모델 | C82: 기초(BOH) | E82: 입고(IN) | G82: 기타입고(ETC IN) | I82: 출고(OUT) | K82: 기타출고(ETC OUT) | M82: 기타출고(ETC OUT) | O82: 로스(LOSS) | Q82: 재고(EOH) | S82: 단가
C83: 수량 | D83: 금액 | E83: 수량 | F83: 금액 | G83: 수량 | H83: 금액 | I83: 수량 | J83: 금액 | K83: 수량 | L83: 금액 | M83: 수량 | N83: 금액 | O83: 수량 | P83: 금액 | Q83: 수량 | R83: 금액
B84: 716AP | C84: 1 | D84: 100 | F84: 0 | K84: 3 | L84: 100 | Q84: =C84+E84+G84-I84-K84-O84 -> -2 | R84: =D84+F84+H84-J84-L84-P84 -> 0 | S84: =(D84+F84+H84)/(C84+E84+G84) -> 100
A86: Case2-1 | B86: BOH < ETC_OUT
B87: 제품 (Product)
B88: 모델 | C88: 기초(BOH) | E88: 입고(IN) | G88: 기타입고(ETC IN) | I88: 출고(OUT) | K88: 기타출고(ETC OUT) | M88: 기타출고(ETC OUT) | O88: 로스(LOSS) | Q88: 재고(EOH) | S88: 단가
C89: 수량 | D89: 금액 | E89: 수량 | F89: 금액 | G89: 수량 | H89: 금액 | I89: 수량 | J89: 금액 | K89: 수량 | L89: 금액 | M89: 수량 | N89: 금액 | O89: 수량 | P89: 금액 | Q89: 수량 | R89: 금액
B90: 716AP | C90: 0 | D90: 0 | F90: 0 | K90: 3 | L90: 0 | Q90: =C90+E90+G90-I90-K90-O90 -> -3 | R90: =D90+F90+H90-J90-L90-P90 -> 0 | S90: =(D90+F90+H90)/(C90+E90+G90) -> #DIV/0!
B92: * Case2와 Case3에서 재고수량이 마이너스가 뜨는 것은 재공품 출고 (제품 입고) 실적을 제외하였기 때문에 마이너스가 보이지만, 실제로는 재공품을 생산완료 후 입고처리를 하기에 재고 산식에 오류는 발생하지 않음.
B93: * Ở Case 2 và Case 3, việc số lượng tồn kho hiển thị âm là do đã loại trừ thành tích xuất kho WIP (nhập kho thành phẩm), nên hiển thị âm, nhưng thực tế thì WIP được xử lý nhập kho sau khi hoàn thành sản xuất, nên công thức tồn kho không phát sinh lỗi.

Sheet 12
B2: 재고자산 종류 | D2: 제품
B3: 구분 | D3: 기타출고
B4: 항목명 | D4: Re-work(SI검사)
B6: 정의 : 생산완료 된 제품에 대하여 공정에 재투입하여 생산하는 경우 (3번 sheet의 제품 기준)
B7: Định nghĩa: Trường hợp đưa sản phẩm đã hoàn thành sản xuất tái nhập vào quy trình để sản xuất lại (Dựa trên tiêu chuẩn thành phẩm ở sheet số 3)
B9: 아래와 같은 케이스가 발생할 수 있으며 아래와 같이 처리한다. (모델, 수량, 금액은 예시입니다.)
B10: Có thể phát sinh trường hợp như dưới đây, và được xử lý như sau. (Model, số lượng, số tiền chỉ là ví dụ minh họa.)
B12: 6월 (Tháng 6) - Product
B13: Model | C13: BOH | E13: IN | G13: ETC_IN | I13: OUT | K13: ETC_OUT | M13: LOSS | O13: EOH
C14: 수량 Số lượng | D14: 금액 Số tiền | E14: 수량 Số lượng | F14: 금액 Số tiền | G14: 수량 Số lượng | H14: 금액 Số tiền | I14: 수량 Số lượng | J14: 금액 Số tiền | K14: 수량 Số lượng | L14: 금액 Số tiền | M14: 수량 Số lượng | N14: 금액 Số tiền | O14: 수량 Số lượng | P14: 금액 Số tiền
B15: 716AP | C15: 100 | D15: 100 | E15: 40 | F15: 40 | G15: 0 | H15: 0 | I15: 0 | J15: 0 | K15: 0 | L15: 0 | M15: 0 | N15: 0 | O15: =C15+E15+G15-I15-K15-M15 -> 140 | P15: =D15+F15+H15-J15-L15-N15 -> 140
B16: 06월 716AP 제품에 대해서 100개의 재고가 있고 (단가 1$) 당월 생산입고가 40개가 됐다고 가정한다 (단가 1$)
B17: Giả định trong Tháng 06, model 716AP có tồn kho 100 sản phẩm (đơn giá 1),vaˋtrongthaˊngnaˋycoˊ40sảnphẩmnhậpkhotừsảnxua^ˊt(đơngiaˊ1), và trong tháng này có 40 sản phẩm nhập kho từ sản xuất (đơn giá 1 ),vaˋtrongthaˊngnaˋycoˊ40sảnphẩmnhậpkhotừsảnxua^ˊt(đơngiaˊ1).
B18: 기타출고되는 제품의 단가는 기초단가를 활용한다. 만약 기초수량과 금액이 부족한 경우 8월1일 협의한 내용을 따른다.
B19: Đơn giá của thành phẩm được xuất kho khác sử dụng đơn giá đầu kỳ. Nếu số lượng và số tiền đầu kỳ không đủ, thì tuân theo nội dung đã thỏa thuận vào ngày 1 tháng 8.
B21: 6월 (Tháng 6) - Product | K21: Re-work(SI검사)
B22: Model | C22: BOH | E22: IN | G22: ETC_IN | I22: OUT | K22: ETC_OUT | M22: LOSS | O22: EOH
C23: 수량 Số lượng | D23: 금액 Số tiền | E23: 수량 Số lượng | F23: 금액 Số tiền | G23: 수량 Số lượng | H23: 금액 Số tiền | I23: 수량 Số lượng | J23: 금액 Số tiền | K23: 수량 Số lượng | L23: 금액 Số tiền | M23: 수량 Số lượng | N23: 금액 Số tiền | O23: 수량 Số lượng | P23: 금액 Số tiền
B24: 716AP | C24: 100 | D24: 100 | E24: 40 | F24: 40 | G24: 0 | H24: 0 | I24: 0 | J24: 0 | K24: 30 | L24: 30 | M24: 0 | N24: 0 | O24: =C24+E24+G24-I24-K24-M24 -> 110 | P24: =D24+F24+H24-J24-L24-N24 -> 110
B26: 6월 (Tháng 6) - WIP | G26: Re-work(SI검사)
B27: Model | C27: BOH | E27: IN | G27: ETC_IN | I27: OUT | K27: ETC_OUT | M27: LOSS | O27: EOH
C28: 수량 Số lượng | D28: 금액 Số tiền | E28: 수량 Số lượng | F28: 금액 Số tiền | G28: 수량 Số lượng | H28: 금액 Số tiền | I28: 수량 Số lượng | J28: 금액 Số tiền | K28: 수량 Số lượng | L28: 금액 Số tiền | M28: 수량 Số lượng | N28: 금액 Số tiền | O28: 수량 Số lượng | P28: 금액 Số tiền
B29: 716AP | C29: 0 | D29: 0 | E29: 0 | F29: 0 | G29: 30 | H29: 30 | I29: 0 | J29: 0 | K29: 0 | L29: 0 | M29: 0 | N29: 0 | O29: =C29+E29+G29-I29-K29-M29 -> 30 | P29: =D29+F29+H29-J29-L29-N29 -> 30
B30: 716AP 제품이 Re-work으로 공정 재투입 할 경우, 제품에서 기타출고하여 동일한 수량과 금액을 재공품의 기타입고로 처리한다.
B31: Trường hợp sản phẩm 716AP được tái nhập vào quy trình sản xuất thông qua Re-work, thì thực hiện xuất kho khác từ thành phẩm, và xử lý nhập kho khác vào WIP (sản phẩm dở dang) với cùng số lượng và số tiền.
B32: 기타입고 된 재공품 716AP의 생산실적이 없는 경우 기말 재공평가를 진행하지 않고 기타입고의 금액을 100% 반영 합니다.
B33: Trường hợp WIP model 716AP đã được nhập kho khác không có sản lượng sản xuất thực tế (OUT hoặc LOSS), thì sẽ không tiến hành đánh giá WIP cuối kỳ, mà phản ánh 100% giá trị của khoản nhập kho khác.
B34: 기타입고 된 재공품 716AP의 생산실적이 있는 경우 (OUT or Loss) 기말 재공품의 PL전, 후로 나뉘어 평가합니다.
B35: Trường hợp WIP model 716AP đã được nhập kho khác có sản lượng sản xuất thực tế (OUT hoặc LOSS), thì sẽ đánh giá WIP cuối kỳ bằng cách chia thành trước PL và sau PL.
B36: 해당 재공품의 생산실적이 반영되는 달에 제조원가가 가산 됩니다.
B37: Chi phí sản xuất sẽ được cộng thêm (gia tăng) vào tháng mà sản lượng sản xuất thực tế của WIP đó được phản ánh.
A64: 46235 | B64: * R/S R/W 협의사항
B65: 모든 R/S, R/W에 대해 아래와 같이 정의한다.
B66: Định nghĩa tất cả các R/S, R/W như sau
B67: R/S, R/W에 대해 제품 기타출고 금액은 기초 제품 단가를 활용한다.
B68: Đối với R/S, R/W, số tiền xuất kho khác của thành phẩm sử dụng đơn giá đầu kỳ của thành phẩm
B69: -제품 기초수량/금액 ≥ 기타출고(R/S, R/W) 수량 인 경우 전액을 기초금액에서 출고 시킨다.
B70: - Trường hợp số lượng/số tiền đầu kỳ của thành phẩm ≥ số lượng xuất kho khác (R/S, R/W), thì xuất kho toàn bộ số tiền từ số tiền đầu kỳ.
B71: -제품 기초수량/금액 < 기타출고(R/S, R/W) 수량 인 경우 기초금액에서 출고 시키되 기초금액을 초과 한 경우 금액은 출고하지 않는다.
B72: - Trường hợp số lượng/số tiền đầu kỳ của thành phẩm < số lượng xuất kho khác (R/S, R/W), thì xuất kho từ số tiền đầu kỳ, nhưng phần số tiền vượt quá số tiền đầu kỳ thì không xuất kho.
A74: Case1 | B74: BOH ≥ ETC_OUT
B75: 제품 (Product)
B76: 모델 | C76: 기초(BOH) | E76: 입고(IN) | G76: 기타입고(ETC IN) | I76: 출고(OUT) | K76: 기타출고(ETC OUT) | M76: 기타출고(ETC OUT) | O76: 로스(LOSS) | Q76: 재고(EOH) | S76: 단가
C77: 수량 | D77: 금액 | E77: 수량 | F77: 금액 | G77: 수량 | H77: 금액 | I77: 수량 | J77: 금액 | K77: 수량 | L77: 금액 | M77: 수량 | N77: 금액 | O77: 수량 | P77: 금액 | Q77: 수량 | R77: 금액
B78: 716AP | C78: 5 | D78: 500 | F78: 0 | K78: 3 | L78: 300 | Q78: =C78+E78+G78-I78-K78-O78 -> 2 | R78: =D78+F78+H78-J78-L78-P78 -> 200 | S78: =(D78+F78+H78)/(C78+E78+G78) -> 100
A80: Case2 | B80: BOH < ETC_OUT
B81: 제품 (Product)
B82: 모델 | C82: 기초(BOH) | E82: 입고(IN) | G82: 기타입고(ETC IN) | I82: 출고(OUT) | K82: 기타출고(ETC OUT) | M82: 기타출고(ETC OUT) | O82: 로스(LOSS) | Q82: 재고(EOH) | S82: 단가
C83: 수량 | D83: 금액 | E83: 수량 | F83: 금액 | G83: 수량 | H83: 금액 | I83: 수량 | J83: 금액 | K83: 수량 | L83: 금액 | M83: 수량 | N83: 금액 | O83: 수량 | P83: 금액 | Q83: 수량 | R83: 금액
B84: 716AP | C84: 1 | D84: 100 | F84: 0 | K84: 3 | L84: 100 | Q84: =C84+E84+G84-I84-K84-O84 -> -2 | R84: =D84+F84+H84-J84-L84-P84 -> 0 | S84: =(D84+F84+H84)/(C84+E84+G84) -> 100
A86: Case2-1 | B86: BOH < ETC_OUT
B87: 제품 (Product)
B88: 모델 | C88: 기초(BOH) | E88: 입고(IN) | G88: 기타입고(ETC IN) | I88: 출고(OUT) | K88: 기타출고(ETC OUT) | M88: 기타출고(ETC OUT) | O88: 로스(LOSS) | Q88: 재고(EOH) | S88: 단가
C89: 수량 | D89: 금액 | E89: 수량 | F89: 금액 | G89: 수량 | H89: 금액 | I89: 수량 | J89: 금액 | K89: 수량 | L89: 금액 | M89: 수량 | N89: 금액 | O89: 수량 | P89: 금액 | Q89: 수량 | R89: 금액
B90: 716AP | C90: 0 | D90: 0 | F90: 0 | K90: 3 | L90: 0 | Q90: =C90+E90+G90-I90-K90-O90 -> -3 | R90: =D90+F90+H90-J90-L90-P90 -> 0 | S90: =(D90+F90+H90)/(C90+E90+G90) -> #DIV/0!
B92: * Case2와 Case3에서 재고수량이 마이너스가 뜨는 것은 재공품 출고 (제품 입고) 실적을 제외하였기 때문에 마이너스가 보이지만, 실제로는 재공품을 생산완료 후 입고처리를 하기에 재고 산식에 오류는 발생하지 않음.
B93: * Ở Case 2 và Case 3, việc số lượng tồn kho hiển thị âm là do đã loại trừ thành tích xuất kho WIP (nhập kho thành phẩm), nên hiển thị âm, nhưng thực tế thì WIP được xử lý nhập kho sau khi hoàn thành sản xuất, nên công thức tồn kho không phát sinh lỗi.

Sheet 13
B2: 재고자산 종류 | D2: 제품
B3: 구분 | D3: 기타출고
B4: 항목명 | D4: RMA
B6: 정의 :
B7: Định nghĩa:
B9: 아래와 같은 케이스가 발생할 수 있으며 아래와 같이 처리한다. (모델, 수량, 금액은 예시입니다.)
B10: Có thể phát sinh trường hợp như dưới đây, và được xử lý như sau. (Model, số lượng, số tiền chỉ là ví dụ minh họa.)
A12: 확인필요 | B12: 내용 검토 필요
A14: 46235 | B14: RMA 반품(Product return)에 대해, SDV에서 세금계산서가 발행되는 경우로 한정한다.
B15: Đối với hàng trả lại RMA(Product return), giới hạn trong trường hợp hóa đơn thuế (tax invoice) được phát hành từ SDV.
B16: 세금계산서 발행 없이 실물을 교환처리 하는 경우 이 구조에 적용하지 않는다. (ERP에 실적 없는 경우)
B17: Trường hợp xử lý đổi hàng thực tế mà không phát hành hóa đơn thuế thì không áp dụng vào cấu trúc này. (Trường hợp không có thành tích trên ERP)
B18: 따라서 제품-기타출고의 RMA 컬럼은 삭제한다.
B19: Do đó, xóa cột RMA trong mục Xuất kho khác - Thành phẩm.

Sheet 14
B2: 재고자산 종류 | D2: 제품
B3: 구분 | D3: 기타출고
B4: 항목명 | D4: 무상매출
B6: 정의 : 제품에 대해 정상 매출이 아닌 무상으로 매출을 진행하는 경우
B7: Định nghĩa: Trường hợp tiến hành bán hàng không thu tiền đối với thành phẩm, không phải bán hàng thu tiền bình thường
B9: 아래와 같은 케이스가 발생할 수 있으며 아래와 같이 처리한다. (모델, 수량, 금액은 예시입니다.)
B10: Có thể phát sinh trường hợp như dưới đây, và được xử lý như sau. (Model, số lượng, số tiền chỉ là ví dụ minh họa.)
B12: 6월 (Tháng 6) - Product | K12: 무상매출
B13: Model | C13: BOH | E13: IN | G13: ETC_IN | I13: OUT | K13: ETC_OUT | M13: LOSS | O13: EOH
C14: 수량 Số lượng | D14: 금액 Số tiền | E14: 수량 Số lượng | F14: 금액 Số tiền | G14: 수량 Số lượng | H14: 금액 Số tiền | I14: 수량 Số lượng | J14: 금액 Số tiền | K14: 수량 Số lượng | L14: 금액 Số tiền | M14: 수량 Số lượng | N14: 금액 Số tiền | O14: 수량 Số lượng | P14: 금액 Số tiền
B15: 716AP | C15: 100 | D15: 100 | E15: 40 | F15: 40 | G15: 0 | H15: 0 | I15: 0 | J15: 0 | K15: 30 | L15: 30 | M15: 0 | N15: 0 | O15: =C15+E15+G15-I15-K15-M15 -> 110 | P15: =D15+F15+H15-J15-L15-N15 -> 110
B16: 06월 716AP 제품에 대해서 100개의 재고가 있고 (단가 1$) 당월 생산입고가 40개가 됐다고 가정한다 (단가 1$)
B17: Giả định trong Tháng 06, model 716AP có tồn kho 100 sản phẩm (đơn giá 1),vaˋtrongthaˊngnaˋycoˊ40sảnphẩmnhậpkhotừsảnxua^ˊt(đơngiaˊ1), và trong tháng này có 40 sản phẩm nhập kho từ sản xuất (đơn giá 1 ),vaˋtrongthaˊngnaˋycoˊ40sảnphẩmnhậpkhotừsảnxua^ˊt(đơngiaˊ1).
B18: 716AP 제품이 무상으로 30개 매출 된 경우 위와 같이 표기한다.
B19: Trường hợp 30 sản phẩm 716AP được bán không thu tiền, thì sẽ được thể hiện như trên.
